Workbook

Sheet Übersicht
A1: Via Romae – Questgruppierung und Implementierung v0.9
A2: 40 Questdefinitionen mit 396 Ablauf-Schritten; EnemyBalance und Stores sind verbindliche Balancing-/Datenverträge für GDD v0.16 und GeoJSON v0.9.
A4: Regulär | B4: Tag 1 | C4: Tag 2 | D4: Medien | E4: Hidden | F4: Bosse | G4: Ein-Ort | H4: Mehrort | I4: Ø Eignung | J4: Rote Pflichtorte | K4: Unique Gegner | L4: Unique Tag 1 | M4: Unique Tag 2 | N4: Questdefs | O4: Ablaufschritte | P4: Dialogknoten | Q4: Charaktere | R4: Rätsel | S4: Kampfprofile | T4: Navigation | U4: Timerquests | V4: Checks OK
A5: =COUNTA(Questgruppen!$B$5:$B$30) -> 26 | B5: =COUNTIF(Questgruppen!$C$5:$C$30,"DAY_1") -> 16 | C5: =COUNTIF(Questgruppen!$C$5:$C$30,"DAY_2") -> 10 | D5: =COUNTIF(Sonderquests!$C$5:$C$18,"MEDIA_LOCAL")+COUNTIF(Sonderquests!$C$5:$C$18,"MEDIA_LANGZEIT") -> 7 | E5: =COUNTIF(Sonderquests!$C$5:$C$18,"HIDDEN") -> 5 | F5: =COUNTIF(Sonderquests!$C$5:$C$18,"WORLD_BOSS") -> 2 | G5: =COUNTIF(Questgruppen!$F$5:$F$30,1) -> 6 | H5: =COUNTIFS(Questgruppen!$F$5:$F$30,">=2",Questgruppen!$F$5:$F$30,"<=5") -> 20 | I5: =ROUND(AVERAGE(Questgruppen!$AB$5:$AB$30),1) -> 4.3 | J5: =SUM(Questgruppen!$V$5:$V$30) -> 0 | K5: =COUNTA('Unique Gegner'!$B$5:$B$16) -> 12 | L5: =COUNTIF('Unique Gegner'!$D$5:$D$16,"DAY_1") -> 8 | M5: =COUNTIF('Unique Gegner'!$D$5:$D$16,"DAY_2") -> 4 | N5: =COUNTA('Quest Master'!A5:A44) -> 40 | O5: =COUNTA(Questablauf!A5:A400) -> 396 | P5: =COUNTA(Dialoge!A5:A124) -> 120 | Q5: =COUNTA(Charaktere!A5:A40) -> 36 | R5: =COUNTA(Rätsel!A5:A116) -> 112 | S5: =COUNTA(Kampfprofile!A5:A39) -> 35 | T5: =COUNTA(Navigation!A5:A8) -> 4 | U5: =COUNTA(Timer!A5:A10) -> 6 | V5: =COUNTIF(Abdeckung!U5:U16,"OK")+COUNTIF(Abdeckung!T19:T22,"OK") -> 16
A8: Hauptmechanik | B8: Reguläre Quests | C8: Empfohlener Korridor | D8: Bewertung | E8: Kommentar
A9: BEOBACHTUNG_SUCHE | B9: =COUNTIF(Questgruppen!$J$5:$J$30,A9) -> 4 | C9: 4–6 | D9: =IF(AND(B9>=4,B9<=6),"AUSGEWOGEN","PRUEFEN") -> AUSGEWOGEN | E9: GPS-Ort und lokale Beobachtung bleiben in jeder Quest Basiselemente.
A10: ZUORDNUNG_REIHENFOLGE | B10: =COUNTIF(Questgruppen!$J$5:$J$30,A10) -> 6 | C10: 4–6 | D10: =IF(AND(B10>=4,B10<=6),"AUSGEWOGEN","PRUEFEN") -> AUSGEWOGEN | E10: GPS-Ort und lokale Beobachtung bleiben in jeder Quest Basiselemente.
A11: KURZTEXT_RAETSEL | B11: =COUNTIF(Questgruppen!$J$5:$J$30,A11) -> 4 | C11: 4–6 | D11: =IF(AND(B11>=4,B11<=6),"AUSGEWOGEN","PRUEFEN") -> AUSGEWOGEN | E11: GPS-Ort und lokale Beobachtung bleiben in jeder Quest Basiselemente.
A12: DIALOG_ENTSCHEIDUNG | B12: =COUNTIF(Questgruppen!$J$5:$J$30,A12) -> 6 | C12: 4–6 | D12: =IF(AND(B12>=4,B12<=6),"AUSGEWOGEN","PRUEFEN") -> AUSGEWOGEN | E12: GPS-Ort und lokale Beobachtung bleiben in jeder Quest Basiselemente.
A13: KAMPF | B13: =COUNTIF(Questgruppen!$J$5:$J$30,A13) -> 6 | C13: 4–6 | D13: =IF(AND(B13>=4,B13<=6),"AUSGEWOGEN","PRUEFEN") -> AUSGEWOGEN | E13: GPS-Ort und lokale Beobachtung bleiben in jeder Quest Basiselemente.
A16: Wichtigste Entscheidung | B16: Begründung
A17: Die Kombinationen sind Quest-Card-reif, aber noch nicht eventfreigegeben. Aktueller Sichtbeleg, blinder Antworttest und Event-Recheck bleiben Pflicht.
A18: Nicht als Pflichtort verwendet: Obelisco della Minerva, Portico d’Ottavia, Piazza del Teatro di Pompeo, Meta Sudans und Arco di Via Nola.
A19: Operativ schwächste Kernkombinationen: Tore des Borgo, Das gebändigte Wasser, Stimmen der Republik und Tore der Aurelianischen Mauer. Sie benötigen die stärksten Fallbacks.

Sheet Matrixcheck
A1: Via Romae – Abgleich mit der Questmatrix
A2: Sollwerte aus den bisherigen Entscheidungen versus die konkrete Gruppierung.
A4: Dimension | B4: Ausprägung | C4: Soll | D4: Ist | E4: Check | F4: Bedeutung | G4: Abweichung | H4: Kommentar
A5: Reguläre Quests | B5: Tag 1 | C5: 16 | D5: =COUNTIF(Questgruppen!$C$5:$C$30,"DAY_1") -> 16 | E5: =IF(C5=D5,"OK","PRUEFEN") -> OK | F5: Tagesmenge | G5: =D5-C5 -> 0
A6: Reguläre Quests | B6: Tag 2 | C6: 10 | D6: =COUNTIF(Questgruppen!$C$5:$C$30,"DAY_2") -> 10 | E6: =IF(C6=D6,"OK","PRUEFEN") -> OK | F6: Tagesmenge | G6: =D6-C6 -> 0 | H6: 9–10 waren erlaubt; 10 nutzt die obere Zielgröße.
A7: Dauer | B7: 5–15 | C7: 8 | D7: =COUNTIF(Questgruppen!$G$5:$G$30,"5–15") -> 8 | E7: =IF(C7=D7,"OK","PRUEFEN") -> OK | F7: Kurze Quests | G7: =D7-C7 -> 0 | H7: Gleich viele wie 15–25.
A8: Dauer | B8: 15–25 | C8: 8 | D8: =COUNTIF(Questgruppen!$G$5:$G$30,"15–25") -> 8 | E8: =IF(C8=D8,"OK","PRUEFEN") -> OK | F8: Mittlere Quests | G8: =D8-C8 -> 0 | H8: Gleich viele wie 5–15.
A9: Dauer | B9: 25–35 | C9: 7 | D9: =COUNTIF(Questgruppen!$G$5:$G$30,"25–35") -> 7 | E9: =IF(C9=D9,"OK","PRUEFEN") -> OK | F9: Längere Quests | G9: =D9-C9 -> 0
A10: Dauer | B10: 35–45 | C10: 3 | D10: =COUNTIF(Questgruppen!$G$5:$G$30,"35–45") -> 3 | E10: =IF(C10=D10,"OK","PRUEFEN") -> OK | F10: Große Routen | G10: =D10-C10 -> 0
A11: Orte pro Quest | B11: 1 Ort | C11: 6 | D11: =COUNTIF(Questgruppen!$F$5:$F$30,1) -> 6 | E11: =IF(C11=D11,"OK","PRUEFEN") -> OK | F11: Reduzierter Ein-Ort-Anteil | G11: =D11-C11 -> 0 | H11: Nur rund ein Viertel der regulären Quests.
A12: Orte pro Quest | B12: 2–5 Orte | C12: 20 | D12: =COUNTIFS(Questgruppen!$F$5:$F$30,">=2",Questgruppen!$F$5:$F$30,"<=5") -> 20 | E12: =IF(C12=D12,"OK","PRUEFEN") -> OK | F12: Mehrortquests | G12: =D12-C12 -> 0
A13: Medien | B13: Tag 1 lokal | C13: 3 | D13: =COUNTIFS(Sonderquests!$C$5:$C$18,"MEDIA_LOCAL",Sonderquests!$D$5:$D$18,"DAY_1") -> 3 | E13: =IF(C13=D13,"OK","PRUEFEN") -> OK | F13: Separate Medienquests | G13: =D13-C13 -> 0
A14: Medien | B14: Tag 2 lokal | C14: 3 | D14: =COUNTIFS(Sonderquests!$C$5:$C$18,"MEDIA_LOCAL",Sonderquests!$D$5:$D$18,"DAY_2") -> 3 | E14: =IF(C14=D14,"OK","PRUEFEN") -> OK | F14: Separate Medienquests | G14: =D14-C14 -> 0
A15: Langzeit | B15: Bilderchronik | C15: 1 | D15: =COUNTIF(Sonderquests!$C$5:$C$18,"MEDIA_LANGZEIT") -> 1 | E15: =IF(C15=D15,"OK","PRUEFEN") -> OK | F15: Separater Chronikslot | G15: =D15-C15 -> 0
A16: Hidden | B16: Optionale Nebenquests | C16: 5 | D16: =COUNTIF(Sonderquests!$C$5:$C$18,"HIDDEN") -> 5 | E16: =IF(C16=D16,"OK","PRUEFEN") -> OK | F16: Zählen nicht zum Limit | G16: =D16-C16 -> 0 | H16: Zielkorridor war 4–6.
A17: Boss | B17: World Bosses | C17: 2 | D17: =COUNTIF(Sonderquests!$C$5:$C$18,"WORLD_BOSS") -> 2 | E17: =IF(C17=D17,"OK","PRUEFEN") -> OK | F17: Zählen nicht zum Limit | G17: =D17-C17 -> 0 | H17: Je ein Tagesfinale.
A18: Klassen | B18: Historienanker | C18: 4 | D18: =COUNTIF(Questgruppen!$M$5:$M$30,"SWISS_GUARD")+COUNTIF(Questgruppen!$M$5:$M$30,"CONDOTTIERE")+COUNTIF(Questgruppen!$M$5:$M$30,"SCULPTOR")+COUNTIF(Questgruppen!$M$5:$M$30,"CLERIC") -> 4 | E18: =IF(C18=D18,"OK","PRUEFEN") -> OK | F18: Je eine Quest pro Klasse | G18: =D18-C18 -> 0 | H18: Schweizergardist, Condottiere, Bildhauer, Kleriker.
A19: Sicherheit | B19: Rote Pflichtstationen | C19: 0 | D19: =SUM(Questgruppen!$V$5:$V$30) -> 0 | E19: =IF(C19=D19,"OK","PRUEFEN") -> OK | F19: Harter Ausschluss | G19: =D19-C19 -> 0
A20: Dauer | B20: Plausibilitätscheck OK | C20: 26 | D20: =COUNTIF(Questgruppen!$S$5:$S$30,"OK") -> 26 | E20: =IF(C20=D20,"OK","PRUEFEN") -> OK | F20: Gehzeit + Interaktion im Band | G20: =D20-C20 -> 0 | H20: Planungswert, kein Routing.
A21: Unique Gegner | B21: Tag 1 | C21: 8 | D21: =COUNTIF('Unique Gegner'!$D$5:$D$16,"DAY_1") -> 8 | E21: =IF(C21=D21,"OK","PRUEFEN") -> OK | F21: Eigenständige optionale Begegnungen | G21: =D21-C21 -> 0 | H21: Zählen weder zu regulären Quests noch Hidden Quests oder World Bosses.
A22: Unique Gegner | B22: Tag 2 | C22: 4 | D22: =COUNTIF('Unique Gegner'!$D$5:$D$16,"DAY_2") -> 4 | E22: =IF(C22=D22,"OK","PRUEFEN") -> OK | F22: Eigenständige optionale Begegnungen | G22: =D22-C22 -> 0 | H22: Rarität, Angriffsmuster und Stärke werden im Combat-Balancing festgelegt.

Sheet Questgruppen
A1: Via Romae – 26 reguläre Questgruppen
A2: 16 Quests an Tag 1, 10 an Tag 2. Sechs Ein-Ort-Quests; alle roten Kandidaten ausgeschlossen.
A4: Nr. | B4: Quest-ID | C4: Tag | D4: Arbeitstitel | E4: Orte in Reihenfolge | F4: Orte | G4: Dauerklasse | H4: Min | I4: Max | J4: Hauptmechanik | K4: Thema | L4: Epoche | M4: Klassenanker | N4: Gegner / Begegnung | O4: Gehstrecke (m) | P4: Gehminuten | Q4: Interaktionsminuten | R4: Gesamtminuten | S4: Dauercheck | T4: Grün | U4: Gelb | V4: Rot | W4: Route | X4: Narrativ | Y4: Hinweis | Z4: Zugang | AA4: Mechanikfit | AB4: Gesamtscore | AC4: Empfehlung | AD4: Hauptrisiko | AE4: Fallback
A5: 1 | B5: D1-Q01 | C5: DAY_1 | D5: Der Fluchtkorridor | E5: Petersplatz → Passetto di Borgo → Engelsburg | F5: =COUNTIF(Ortszuordnung!$A$5:$A$85,B5) -> 3 | G5: 25–35 | H5: 25 | I5: 35 | J5: DIALOG_ENTSCHEIDUNG | K5: Sacco di Roma, päpstlicher Schutz | L5: RENAISSANCE | M5: SWISS_GUARD | N5: Schatten des Passetto | O5: =SUMIF(Ortszuordnung!$A$5:$A$85,B5,Ortszuordnung!$S$5:$S$85) -> 1015 | P5: =ROUND(O5/Kriterien!$B$5,0) -> 14 | Q5: 18 | R5: =P5+Q5 -> 32 | S5: =IF(AND(R5>=H5,R5<=I5),"OK",IF(R5<H5,"ZU_KURZ","ZU_LANG")) -> OK | T5: =COUNTIFS(Ortszuordnung!$A$5:$A$85,B5,Ortszuordnung!$K$5:$K$85,"GRUEN") -> 2 | U5: =COUNTIFS(Ortszuordnung!$A$5:$A$85,B5,Ortszuordnung!$K$5:$K$85,"GELB") -> 1 | V5: =COUNTIFS(Ortszuordnung!$A$5:$A$85,B5,Ortszuordnung!$K$5:$K$85,"ROT") -> 0 | W5: 4.2 | X5: 5 | Y5: 3.8 | Z5: 3.4 | AA5: 4.8 | AB5: =ROUND(W5*Kriterien!$B$7+X5*Kriterien!$B$8+Y5*Kriterien!$B$9+Z5*Kriterien!$B$10+AA5*Kriterien!$B$11,1) -> 4.3 | AC5: =IF(V5>0,"NICHT_EMPFOHLEN",IF(AB5>=4.2,"SEHR_GUT",IF(AB5>=3.6,"GUT",IF(AB5>=3,"BEDINGT","NICHT_EMPFOHLEN")))) -> SEHR_GUT | AD5: Petersplatz: Menschenmenge und aktuelle Sicht der Bodenmarkierung. | AE5: Bei unklarer Bodenmarkierung startet die Quest am Passetto mit dessen Mauerverlauf.
A6: 2 | B6: D1-Q02 | C6: DAY_1 | D6: Tore des Borgo | E6: St.-Pellegrino-Tor → Porta Cavalleggeri → Porta Santo Spirito | F6: =COUNTIF(Ortszuordnung!$A$5:$A$85,B6) -> 3 | G6: 25–35 | H6: 25 | I6: 35 | J6: KAMPF | K6: Befestigung, päpstliche Macht | L6: RENAISSANCE | M6: CONDOTTIERE | N6: Cavalleggero Pontificio | O6: =SUMIF(Ortszuordnung!$A$5:$A$85,B6,Ortszuordnung!$S$5:$S$85) -> 970 | P6: =ROUND(O6/Kriterien!$B$5,0) -> 13 | Q6: 18 | R6: =P6+Q6 -> 31 | S6: =IF(AND(R6>=H6,R6<=I6),"OK",IF(R6<H6,"ZU_KURZ","ZU_LANG")) -> OK | T6: =COUNTIFS(Ortszuordnung!$A$5:$A$85,B6,Ortszuordnung!$K$5:$K$85,"GRUEN") -> 1 | U6: =COUNTIFS(Ortszuordnung!$A$5:$A$85,B6,Ortszuordnung!$K$5:$K$85,"GELB") -> 2 | V6: =COUNTIFS(Ortszuordnung!$A$5:$A$85,B6,Ortszuordnung!$K$5:$K$85,"ROT") -> 0 | W6: 3.8 | X6: 4.6 | Y6: 3.2 | Z6: 3.3 | AA6: 4.7 | AB6: =ROUND(W6*Kriterien!$B$7+X6*Kriterien!$B$8+Y6*Kriterien!$B$9+Z6*Kriterien!$B$10+AA6*Kriterien!$B$11,1) -> 3.9 | AC6: =IF(V6>0,"NICHT_EMPFOHLEN",IF(AB6>=4.2,"SEHR_GUT",IF(AB6>=3.6,"GUT",IF(AB6>=3,"BEDINGT","NICHT_EMPFOHLEN")))) -> GUT | AD6: Zwei Hinweise sind relativ klein; Cavalleggeri ist nur als Mauerrest erhalten. | AE6: Wenn Porta Cavalleggeri nicht eindeutig ist, endet die Quest an Porta Santo Spirito.
A7: 3 | B7: D1-Q03 | C7: DAY_1 | D7: Der Dreizack | E7: Piazza del Popolo → Obelisco Flaminio → Porta del Popolo | F7: =COUNTIF(Ortszuordnung!$A$5:$A$85,B7) -> 3 | G7: 15–25 | H7: 15 | I7: 25 | J7: BEOBACHTUNG_SUCHE | K7: Stadteingang und Stadtplanung | L7: ANTIKE_BIS_NEUZEIT | O7: =SUMIF(Ortszuordnung!$A$5:$A$85,B7,Ortszuordnung!$S$5:$S$85) -> 125 | P7: =ROUND(O7/Kriterien!$B$5,0) -> 2 | Q7: 15 | R7: =P7+Q7 -> 17 | S7: =IF(AND(R7>=H7,R7<=I7),"OK",IF(R7<H7,"ZU_KURZ","ZU_LANG")) -> OK | T7: =COUNTIFS(Ortszuordnung!$A$5:$A$85,B7,Ortszuordnung!$K$5:$K$85,"GRUEN") -> 3 | U7: =COUNTIFS(Ortszuordnung!$A$5:$A$85,B7,Ortszuordnung!$K$5:$K$85,"GELB") -> 0 | V7: =COUNTIFS(Ortszuordnung!$A$5:$A$85,B7,Ortszuordnung!$K$5:$K$85,"ROT") -> 0 | W7: 5 | X7: 4.5 | Y7: 4.8 | Z7: 4.2 | AA7: 4.8 | AB7: =ROUND(W7*Kriterien!$B$7+X7*Kriterien!$B$8+Y7*Kriterien!$B$9+Z7*Kriterien!$B$10+AA7*Kriterien!$B$11,1) -> 4.7 | AC7: =IF(V7>0,"NICHT_EMPFOHLEN",IF(AB7>=4.2,"SEHR_GUT",IF(AB7>=3.6,"GUT",IF(AB7>=3,"BEDINGT","NICHT_EMPFOHLEN")))) -> SEHR_GUT | AD7: Hohe Besucherzahl, aber alle Hinweise sind groß. | AE7: Bei dichter Menschenmenge nur Silhouetten und Großformen verwenden.
A8: 4 | B8: D1-Q04 | C8: DAY_1 | D8: Antinoos über Rom | E8: Obelisco di Antinoo → Fontana della Dea di Roma → Balconata del Pincio | F8: =COUNTIF(Ortszuordnung!$A$5:$A$85,B8) -> 3 | G8: 15–25 | H8: 15 | I8: 25 | J8: KAMPF | K8: Antinoos, Romulus und Remus, Pincio | L8: ANTIKE_REZEPTION | N8: Ombra di Antinoo | O8: =SUMIF(Ortszuordnung!$A$5:$A$85,B8,Ortszuordnung!$S$5:$S$85) -> 347 | P8: =ROUND(O8/Kriterien!$B$5,0) -> 5 | Q8: 15 | R8: =P8+Q8 -> 20 | S8: =IF(AND(R8>=H8,R8<=I8),"OK",IF(R8<H8,"ZU_KURZ","ZU_LANG")) -> OK | T8: =COUNTIFS(Ortszuordnung!$A$5:$A$85,B8,Ortszuordnung!$K$5:$K$85,"GRUEN") -> 3 | U8: =COUNTIFS(Ortszuordnung!$A$5:$A$85,B8,Ortszuordnung!$K$5:$K$85,"GELB") -> 0 | V8: =COUNTIFS(Ortszuordnung!$A$5:$A$85,B8,Ortszuordnung!$K$5:$K$85,"ROT") -> 0 | W8: 4.8 | X8: 4.5 | Y8: 4.5 | Z8: 4 | AA8: 4.7 | AB8: =ROUND(W8*Kriterien!$B$7+X8*Kriterien!$B$8+Y8*Kriterien!$B$9+Z8*Kriterien!$B$10+AA8*Kriterien!$B$11,1) -> 4.5 | AC8: =IF(V8>0,"NICHT_EMPFOHLEN",IF(AB8>=4.2,"SEHR_GUT",IF(AB8>=3.6,"GUT",IF(AB8>=3,"BEDINGT","NICHT_EMPFOHLEN")))) -> SEHR_GUT | AD8: Parkzugang und Tageszeit beachten. | AE8: Bei gesperrtem Pincio wird die Quest deaktiviert; kein entfernter Ersatzpunkt.
A9: 5 | B9: D1-Q05 | C9: DAY_1 | D9: Die steinerne Barke | E9: Spanischer Platz | F9: =COUNTIF(Ortszuordnung!$A$5:$A$85,B9) -> 1 | G9: 5–15 | H9: 5 | I9: 15 | J9: BEOBACHTUNG_SUCHE | K9: Barocke Stadtinszenierung | L9: BAROCK | O9: =SUMIF(Ortszuordnung!$A$5:$A$85,B9,Ortszuordnung!$S$5:$S$85) -> 0 | P9: =ROUND(O9/Kriterien!$B$5,0) -> 0 | Q9: 8 | R9: =P9+Q9 -> 8 | S9: =IF(AND(R9>=H9,R9<=I9),"OK",IF(R9<H9,"ZU_KURZ","ZU_LANG")) -> OK | T9: =COUNTIFS(Ortszuordnung!$A$5:$A$85,B9,Ortszuordnung!$K$5:$K$85,"GRUEN") -> 1 | U9: =COUNTIFS(Ortszuordnung!$A$5:$A$85,B9,Ortszuordnung!$K$5:$K$85,"GELB") -> 0 | V9: =COUNTIFS(Ortszuordnung!$A$5:$A$85,B9,Ortszuordnung!$K$5:$K$85,"ROT") -> 0 | W9: 5 | X9: 4 | Y9: 4.2 | Z9: 3 | AA9: 4.4 | AB9: =ROUND(W9*Kriterien!$B$7+X9*Kriterien!$B$8+Y9*Kriterien!$B$9+Z9*Kriterien!$B$10+AA9*Kriterien!$B$11,1) -> 4.2 | AC9: =IF(V9>0,"NICHT_EMPFOHLEN",IF(AB9>=4.2,"SEHR_GUT",IF(AB9>=3.6,"GUT",IF(AB9>=3,"BEDINGT","NICHT_EMPFOHLEN")))) -> SEHR_GUT | AD9: Extreme Menschenmenge; nur die große Bootsform ist robust. | AE9: Fallback ist die Richtung der großen Treppe zu Trinità dei Monti.
A10: 6 | B10: D1-Q06 | C10: DAY_1 | D10: Berninis Werkstatt | E10: Piazza Navona → Neptunsbrunnen → Mohrenbrunnen | F10: =COUNTIF(Ortszuordnung!$A$5:$A$85,B10) -> 3 | G10: 15–25 | H10: 15 | I10: 25 | J10: ZUORDNUNG_REIHENFOLGE | K10: Bildhauerei und barocke Platzdramaturgie | L10: BAROCK | M10: SCULPTOR | O10: =SUMIF(Ortszuordnung!$A$5:$A$85,B10,Ortszuordnung!$S$5:$S$85) -> 355 | P10: =ROUND(O10/Kriterien!$B$5,0) -> 5 | Q10: 18 | R10: =P10+Q10 -> 23 | S10: =IF(AND(R10>=H10,R10<=I10),"OK",IF(R10<H10,"ZU_KURZ","ZU_LANG")) -> OK | T10: =COUNTIFS(Ortszuordnung!$A$5:$A$85,B10,Ortszuordnung!$K$5:$K$85,"GRUEN") -> 3 | U10: =COUNTIFS(Ortszuordnung!$A$5:$A$85,B10,Ortszuordnung!$K$5:$K$85,"GELB") -> 0 | V10: =COUNTIFS(Ortszuordnung!$A$5:$A$85,B10,Ortszuordnung!$K$5:$K$85,"ROT") -> 0 | W10: 5 | X10: 5 | Y10: 4.5 | Z10: 3.4 | AA10: 5 | AB10: =ROUND(W10*Kriterien!$B$7+X10*Kriterien!$B$8+Y10*Kriterien!$B$9+Z10*Kriterien!$B$10+AA10*Kriterien!$B$11,1) -> 4.6 | AC10: =IF(V10>0,"NICHT_EMPFOHLEN",IF(AB10>=4.2,"SEHR_GUT",IF(AB10>=3.6,"GUT",IF(AB10>=3,"BEDINGT","NICHT_EMPFOHLEN")))) -> SEHR_GUT | AD10: Menschenmenge; nur große Figurenattribute verwenden. | AE10: Fallback: Zahl und Lage der drei Brunnen statt einzelner Figurendetails.
A11: 7 | B11: D1-Q07 | C11: DAY_1 | D11: Agrippas Zeichen | E11: Pantheon → Obelisco Macuteo | F11: =COUNTIF(Ortszuordnung!$A$5:$A$85,B11) -> 2 | G11: 5–15 | H11: 5 | I11: 15 | J11: KURZTEXT_RAETSEL | K11: Pantheon und ägyptische Wiederverwendung | L11: ANTIKE_UND_PAEPSTLICHES_ROM | N11: Mummia dell’Iseo | O11: =SUMIF(Ortszuordnung!$A$5:$A$85,B11,Ortszuordnung!$S$5:$S$85) -> 96 | P11: =ROUND(O11/Kriterien!$B$5,0) -> 1 | Q11: 10 | R11: =P11+Q11 -> 11 | S11: =IF(AND(R11>=H11,R11<=I11),"OK",IF(R11<H11,"ZU_KURZ","ZU_LANG")) -> OK | T11: =COUNTIFS(Ortszuordnung!$A$5:$A$85,B11,Ortszuordnung!$K$5:$K$85,"GRUEN") -> 2 | U11: =COUNTIFS(Ortszuordnung!$A$5:$A$85,B11,Ortszuordnung!$K$5:$K$85,"GELB") -> 0 | V11: =COUNTIFS(Ortszuordnung!$A$5:$A$85,B11,Ortszuordnung!$K$5:$K$85,"ROT") -> 0 | W11: 5 | X11: 4.7 | Y11: 4.3 | Z11: 3.7 | AA11: 4.5 | AB11: =ROUND(W11*Kriterien!$B$7+X11*Kriterien!$B$8+Y11*Kriterien!$B$9+Z11*Kriterien!$B$10+AA11*Kriterien!$B$11,1) -> 4.5 | AC11: =IF(V11>0,"NICHT_EMPFOHLEN",IF(AB11>=4.2,"SEHR_GUT",IF(AB11>=3.6,"GUT",IF(AB11>=3,"BEDINGT","NICHT_EMPFOHLEN")))) -> SEHR_GUT | AD11: Pantheon-Außenpunkt und Besucherdichte müssen aktuell bestätigt werden. | AE11: Fallback: Portikusform am Pantheon und Obelisk-auf-Brunnen-Beziehung.
A12: 8 | B12: D1-Q08 | C12: DAY_1 | D12: Kaiserbotschaften | E12: Obelisco di Montecitorio → Mark-Aurel-Säule | F12: =COUNTIF(Ortszuordnung!$A$5:$A$85,B12) -> 2 | G12: 5–15 | H12: 5 | I12: 15 | J12: ZUORDNUNG_REIHENFOLGE | K12: Imperiale Erinnerung im Stadtraum | L12: ANTIKE_UND_NEUZEIT | O12: =SUMIF(Ortszuordnung!$A$5:$A$85,B12,Ortszuordnung!$S$5:$S$85) -> 139 | P12: =ROUND(O12/Kriterien!$B$5,0) -> 2 | Q12: 10 | R12: =P12+Q12 -> 12 | S12: =IF(AND(R12>=H12,R12<=I12),"OK",IF(R12<H12,"ZU_KURZ","ZU_LANG")) -> OK | T12: =COUNTIFS(Ortszuordnung!$A$5:$A$85,B12,Ortszuordnung!$K$5:$K$85,"GRUEN") -> 2 | U12: =COUNTIFS(Ortszuordnung!$A$5:$A$85,B12,Ortszuordnung!$K$5:$K$85,"GELB") -> 0 | V12: =COUNTIFS(Ortszuordnung!$A$5:$A$85,B12,Ortszuordnung!$K$5:$K$85,"ROT") -> 0 | W12: 4.8 | X12: 4.6 | Y12: 4.8 | Z12: 4 | AA12: 4.5 | AB12: =ROUND(W12*Kriterien!$B$7+X12*Kriterien!$B$8+Y12*Kriterien!$B$9+Z12*Kriterien!$B$10+AA12*Kriterien!$B$11,1) -> 4.6 | AC12: =IF(V12>0,"NICHT_EMPFOHLEN",IF(AB12>=4.2,"SEHR_GUT",IF(AB12>=3.6,"GUT",IF(AB12>=3,"BEDINGT","NICHT_EMPFOHLEN")))) -> SEHR_GUT | AD12: Verkehr und Menschenmenge, Hinweise selbst sind groß. | AE12: Fallback: Form des Reliefbands beziehungsweise Schriftart am Obelisken.
A13: 9 | B13: D1-Q09 | C13: DAY_1 | D13: Das gebändigte Wasser | E13: Trevi-Brunnen → Acquedotto Vergine → Tritonenbrunnen | F13: =COUNTIF(Ortszuordnung!$A$5:$A$85,B13) -> 3 | G13: 25–35 | H13: 25 | I13: 35 | J13: KAMPF | K13: Wasserversorgung und Brunnenkunst | L13: ANTIKE_BIS_BAROCK | N13: Ratto dell’Acqua Virgo | O13: =SUMIF(Ortszuordnung!$A$5:$A$85,B13,Ortszuordnung!$S$5:$S$85) -> 747 | P13: =ROUND(O13/Kriterien!$B$5,0) -> 10 | Q13: 18 | R13: =P13+Q13 -> 28 | S13: =IF(AND(R13>=H13,R13<=I13),"OK",IF(R13<H13,"ZU_KURZ","ZU_LANG")) -> OK | T13: =COUNTIFS(Ortszuordnung!$A$5:$A$85,B13,Ortszuordnung!$K$5:$K$85,"GRUEN") -> 1 | U13: =COUNTIFS(Ortszuordnung!$A$5:$A$85,B13,Ortszuordnung!$K$5:$K$85,"GELB") -> 2 | V13: =COUNTIFS(Ortszuordnung!$A$5:$A$85,B13,Ortszuordnung!$K$5:$K$85,"ROT") -> 0 | W13: 3.7 | X13: 4.8 | Y13: 3.2 | Z13: 2.8 | AA13: 4.6 | AB13: =ROUND(W13*Kriterien!$B$7+X13*Kriterien!$B$8+Y13*Kriterien!$B$9+Z13*Kriterien!$B$10+AA13*Kriterien!$B$11,1) -> 3.9 | AC13: =IF(V13>0,"NICHT_EMPFOHLEN",IF(AB13>=4.2,"SEHR_GUT",IF(AB13>=3.6,"GUT",IF(AB13>=3,"BEDINGT","NICHT_EMPFOHLEN")))) -> GUT | AD13: Trevi ist extrem voll; die antiken Arkaden sind teilweise verdeckt. | AE13: Wenn die Arkaden verdeckt sind, nutzt die gleichörtige Materialfrage und setzt die Route fort.
A14: 10 | B14: D1-Q10 | C14: DAY_1 | D14: Macht auf dem Quirinal | E14: Piazza Scanderbeg → Obelisco del Quirinale → Quirinalspalast | F14: =COUNTIF(Ortszuordnung!$A$5:$A$85,B14) -> 3 | G14: 25–35 | H14: 25 | I14: 35 | J14: DIALOG_ENTSCHEIDUNG | K14: Söldner, Papst und Republik | L14: RENAISSANCE_BIS_GEGENWART | N14: Corazziere del Colle | O14: =SUMIF(Ortszuordnung!$A$5:$A$85,B14,Ortszuordnung!$S$5:$S$85) -> 534 | P14: =ROUND(O14/Kriterien!$B$5,0) -> 7 | Q14: 22 | R14: =P14+Q14 -> 29 | S14: =IF(AND(R14>=H14,R14<=I14),"OK",IF(R14<H14,"ZU_KURZ","ZU_LANG")) -> OK | T14: =COUNTIFS(Ortszuordnung!$A$5:$A$85,B14,Ortszuordnung!$K$5:$K$85,"GRUEN") -> 2 | U14: =COUNTIFS(Ortszuordnung!$A$5:$A$85,B14,Ortszuordnung!$K$5:$K$85,"GELB") -> 1 | V14: =COUNTIFS(Ortszuordnung!$A$5:$A$85,B14,Ortszuordnung!$K$5:$K$85,"ROT") -> 0 | W14: 4.5 | X14: 4.6 | Y14: 3.5 | Z14: 3.2 | AA14: 4.7 | AB14: =ROUND(W14*Kriterien!$B$7+X14*Kriterien!$B$8+Y14*Kriterien!$B$9+Z14*Kriterien!$B$10+AA14*Kriterien!$B$11,1) -> 4.1 | AC14: =IF(V14>0,"NICHT_EMPFOHLEN",IF(AB14>=4.2,"SEHR_GUT",IF(AB14>=3.6,"GUT",IF(AB14>=3,"BEDINGT","NICHT_EMPFOHLEN")))) -> GUT | AD14: Scanderbeg-Inschrift ist klein; am Palast Sicherheitsabstand einhalten. | AE14: Bei unleserlicher Scanderbeg-Inschrift beginnt die Quest am Quirinal-Obelisken.
A15: 11 | B15: D1-Q11 | C15: DAY_1 | D15: Zeichen der Unbefleckten | E15: Colonna dell'Immacolata | F15: =COUNTIF(Ortszuordnung!$A$5:$A$85,B15) -> 1 | G15: 5–15 | H15: 5 | I15: 15 | J15: KURZTEXT_RAETSEL | K15: Marienverehrung und Stadtsymbolik | L15: NEUZEIT | O15: =SUMIF(Ortszuordnung!$A$5:$A$85,B15,Ortszuordnung!$S$5:$S$85) -> 0 | P15: =ROUND(O15/Kriterien!$B$5,0) -> 0 | Q15: 9 | R15: =P15+Q15 -> 9 | S15: =IF(AND(R15>=H15,R15<=I15),"OK",IF(R15<H15,"ZU_KURZ","ZU_LANG")) -> OK | T15: =COUNTIFS(Ortszuordnung!$A$5:$A$85,B15,Ortszuordnung!$K$5:$K$85,"GRUEN") -> 1 | U15: =COUNTIFS(Ortszuordnung!$A$5:$A$85,B15,Ortszuordnung!$K$5:$K$85,"GELB") -> 0 | V15: =COUNTIFS(Ortszuordnung!$A$5:$A$85,B15,Ortszuordnung!$K$5:$K$85,"ROT") -> 0 | W15: 5 | X15: 4.2 | Y15: 4.7 | Z15: 3.8 | AA15: 4.2 | AB15: =ROUND(W15*Kriterien!$B$7+X15*Kriterien!$B$8+Y15*Kriterien!$B$9+Z15*Kriterien!$B$10+AA15*Kriterien!$B$11,1) -> 4.4 | AC15: =IF(V15>0,"NICHT_EMPFOHLEN",IF(AB15>=4.2,"SEHR_GUT",IF(AB15>=3.6,"GUT",IF(AB15>=3,"BEDINGT","NICHT_EMPFOHLEN")))) -> SEHR_GUT | AD15: Menschenmenge, aber klare Silhouette. | AE15: Fallback: Zahl der großen Sockelfiguren.
A16: 12 | B16: D1-Q12 | C16: DAY_1 | D16: Stimmen der Republik | E16: Ponte Sisto → Palazzo Farnese → Campo de' Fiori → Largo di Torre Argentina | F16: =COUNTIF(Ortszuordnung!$A$5:$A$85,B16) -> 4 | G16: 35–45 | H16: 35 | I16: 45 | J16: DIALOG_ENTSCHEIDUNG | K16: Macht, Markt und republikanische Erinnerung | L16: ANTIKE_BIS_NEUZEIT | O16: =SUMIF(Ortszuordnung!$A$5:$A$85,B16,Ortszuordnung!$S$5:$S$85) -> 1009 | P16: =ROUND(O16/Kriterien!$B$5,0) -> 13 | Q16: 24 | R16: =P16+Q16 -> 37 | S16: =IF(AND(R16>=H16,R16<=I16),"OK",IF(R16<H16,"ZU_KURZ","ZU_LANG")) -> OK | T16: =COUNTIFS(Ortszuordnung!$A$5:$A$85,B16,Ortszuordnung!$K$5:$K$85,"GRUEN") -> 2 | U16: =COUNTIFS(Ortszuordnung!$A$5:$A$85,B16,Ortszuordnung!$K$5:$K$85,"GELB") -> 2 | V16: =COUNTIFS(Ortszuordnung!$A$5:$A$85,B16,Ortszuordnung!$K$5:$K$85,"ROT") -> 0 | W16: 4.2 | X16: 5 | Y16: 3.6 | Z16: 3.3 | AA16: 4.8 | AB16: =ROUND(W16*Kriterien!$B$7+X16*Kriterien!$B$8+Y16*Kriterien!$B$9+Z16*Kriterien!$B$10+AA16*Kriterien!$B$11,1) -> 4.2 | AC16: =IF(V16>0,"NICHT_EMPFOHLEN",IF(AB16>=4.2,"SEHR_GUT",IF(AB16>=3.6,"GUT",IF(AB16>=3,"BEDINGT","NICHT_EMPFOHLEN")))) -> SEHR_GUT | AD16: Campo-Marktzeiten, Palazzo-Sicherheitsbereich und Überblick am Largo. | AE16: Jeder Abschnitt ist modular deaktivierbar; mindestens drei der vier Stationen müssen verfügbar sein.
A17: 13 | B17: D1-Q13 | C17: DAY_1 | D17: Roms große Bühne | E17: Basilica di Sant'Andrea della Valle → Fontana delle Tartarughe → Marcellustheater | F17: =COUNTIF(Ortszuordnung!$A$5:$A$85,B17) -> 3 | G17: 15–25 | H17: 15 | I17: 25 | J17: ZUORDNUNG_REIHENFOLGE | K17: Theater, Fassade und barocke Inszenierung | L17: ANTIKE_BIS_BAROCK | N17: Custode delle Tartarughe | O17: =SUMIF(Ortszuordnung!$A$5:$A$85,B17,Ortszuordnung!$S$5:$S$85) -> 784 | P17: =ROUND(O17/Kriterien!$B$5,0) -> 10 | Q17: 15 | R17: =P17+Q17 -> 25 | S17: =IF(AND(R17>=H17,R17<=I17),"OK",IF(R17<H17,"ZU_KURZ","ZU_LANG")) -> OK | T17: =COUNTIFS(Ortszuordnung!$A$5:$A$85,B17,Ortszuordnung!$K$5:$K$85,"GRUEN") -> 2 | U17: =COUNTIFS(Ortszuordnung!$A$5:$A$85,B17,Ortszuordnung!$K$5:$K$85,"GELB") -> 1 | V17: =COUNTIFS(Ortszuordnung!$A$5:$A$85,B17,Ortszuordnung!$K$5:$K$85,"ROT") -> 0 | W17: 4 | X17: 4.4 | Y17: 3.4 | Z17: 3.4 | AA17: 4.4 | AB17: =ROUND(W17*Kriterien!$B$7+X17*Kriterien!$B$8+Y17*Kriterien!$B$9+Z17*Kriterien!$B$10+AA17*Kriterien!$B$11,1) -> 3.9 | AC17: =IF(V17>0,"NICHT_EMPFOHLEN",IF(AB17>=4.2,"SEHR_GUT",IF(AB17>=3.6,"GUT",IF(AB17>=3,"BEDINGT","NICHT_EMPFOHLEN")))) -> GUT | AD17: Sant’Andrea-Fassadensicht und Schildkröten müssen aktuell bestätigt werden. | AE17: Fallback: Großformen an Sant’Andrea und Teatro; Tartarughen-Detail bei Bedarf auslassen.
A18: 14 | B18: D1-Q14 | C18: DAY_1 | D18: Die steinerne Insel | E18: Isola Tiberina | F18: =COUNTIF(Ortszuordnung!$A$5:$A$85,B18) -> 1 | G18: 5–15 | H18: 5 | I18: 15 | J18: KURZTEXT_RAETSEL | K18: Tiberinsel und Heiltradition | L18: ANTIKE_BIS_GEGENWART | O18: =SUMIF(Ortszuordnung!$A$5:$A$85,B18,Ortszuordnung!$S$5:$S$85) -> 0 | P18: =ROUND(O18/Kriterien!$B$5,0) -> 0 | Q18: 10 | R18: =P18+Q18 -> 10 | S18: =IF(AND(R18>=H18,R18<=I18),"OK",IF(R18<H18,"ZU_KURZ","ZU_LANG")) -> OK | T18: =COUNTIFS(Ortszuordnung!$A$5:$A$85,B18,Ortszuordnung!$K$5:$K$85,"GRUEN") -> 0 | U18: =COUNTIFS(Ortszuordnung!$A$5:$A$85,B18,Ortszuordnung!$K$5:$K$85,"GELB") -> 1 | V18: =COUNTIFS(Ortszuordnung!$A$5:$A$85,B18,Ortszuordnung!$K$5:$K$85,"ROT") -> 0 | W18: 5 | X18: 4.5 | Y18: 3.3 | Z18: 3.5 | AA18: 4.4 | AB18: =ROUND(W18*Kriterien!$B$7+X18*Kriterien!$B$8+Y18*Kriterien!$B$9+Z18*Kriterien!$B$10+AA18*Kriterien!$B$11,1) -> 4.1 | AC18: =IF(V18>0,"NICHT_EMPFOHLEN",IF(AB18>=4.2,"SEHR_GUT",IF(AB18>=3.6,"GUT",IF(AB18>=3,"BEDINGT","NICHT_EMPFOHLEN")))) -> GUT | AD18: Die Schiffsform ist nur vom richtigen Blickwinkel eindeutig. | AE18: Fallback: allgemeine Inselform und sichtbare Brückenbeziehung.
A19: 15 | B19: D1-Q15 | C19: DAY_1 | D19: Cecilias Stimmen | E19: Basilica di Santa Cecilia in Trastevere → Santa Maria in Trastevere | F19: =COUNTIF(Ortszuordnung!$A$5:$A$85,B19) -> 2 | G19: 15–25 | H19: 15 | I19: 25 | J19: DIALOG_ENTSCHEIDUNG | K19: Märtyrertradition, Musik und Titelkirchen | L19: FRUEHCHRISTLICH_BIS_MITTELALTER | M19: CLERIC | O19: =SUMIF(Ortszuordnung!$A$5:$A$85,B19,Ortszuordnung!$S$5:$S$85) -> 706 | P19: =ROUND(O19/Kriterien!$B$5,0) -> 9 | Q19: 16 | R19: =P19+Q19 -> 25 | S19: =IF(AND(R19>=H19,R19<=I19),"OK",IF(R19<H19,"ZU_KURZ","ZU_LANG")) -> OK | T19: =COUNTIFS(Ortszuordnung!$A$5:$A$85,B19,Ortszuordnung!$K$5:$K$85,"GRUEN") -> 1 | U19: =COUNTIFS(Ortszuordnung!$A$5:$A$85,B19,Ortszuordnung!$K$5:$K$85,"GELB") -> 1 | V19: =COUNTIFS(Ortszuordnung!$A$5:$A$85,B19,Ortszuordnung!$K$5:$K$85,"ROT") -> 0 | W19: 4.2 | X19: 5 | Y19: 3.3 | Z19: 3.2 | AA19: 4.8 | AB19: =ROUND(W19*Kriterien!$B$7+X19*Kriterien!$B$8+Y19*Kriterien!$B$9+Z19*Kriterien!$B$10+AA19*Kriterien!$B$11,1) -> 4.1 | AC19: =IF(V19>0,"NICHT_EMPFOHLEN",IF(AB19>=4.2,"SEHR_GUT",IF(AB19>=3.6,"GUT",IF(AB19>=3,"BEDINGT","NICHT_EMPFOHLEN")))) -> GUT | AD19: Santa Cecilia muss vollständig vom öffentlichen Außenpunkt funktionieren. | AE19: Wenn Santa Cecilia außen nicht eindeutig ist, startet die Quest auf der Piazza Santa Maria.
A20: 16 | B20: D1-Q16 | C20: DAY_1 | D20: Republik auf dem Gianicolo | E20: Gianicolense-Mauern → Mausoleo Ossario Garibaldino → Fontana Dell'Acqua Paola → Monumento a Garibaldi → Monumento ad Anita Garibaldi | F20: =COUNTIF(Ortszuordnung!$A$5:$A$85,B20) -> 5 | G20: 35–45 | H20: 35 | I20: 45 | J20: KAMPF | K20: Risorgimento und Verteidigung Roms | L20: 19_JAHRHUNDERT | N20: Garibaldino delle Mura | O20: =SUMIF(Ortszuordnung!$A$5:$A$85,B20,Ortszuordnung!$S$5:$S$85) -> 1404 | P20: =ROUND(O20/Kriterien!$B$5,0) -> 19 | Q20: 25 | R20: =P20+Q20 -> 44 | S20: =IF(AND(R20>=H20,R20<=I20),"OK",IF(R20<H20,"ZU_KURZ","ZU_LANG")) -> OK | T20: =COUNTIFS(Ortszuordnung!$A$5:$A$85,B20,Ortszuordnung!$K$5:$K$85,"GRUEN") -> 5 | U20: =COUNTIFS(Ortszuordnung!$A$5:$A$85,B20,Ortszuordnung!$K$5:$K$85,"GELB") -> 0 | V20: =COUNTIFS(Ortszuordnung!$A$5:$A$85,B20,Ortszuordnung!$K$5:$K$85,"ROT") -> 0 | W20: 3.5 | X20: 5 | Y20: 4.4 | Z20: 3.8 | AA20: 5 | AB20: =ROUND(W20*Kriterien!$B$7+X20*Kriterien!$B$8+Y20*Kriterien!$B$9+Z20*Kriterien!$B$10+AA20*Kriterien!$B$11,1) -> 4.4 | AC20: =IF(V20>0,"NICHT_EMPFOHLEN",IF(AB20>=4.2,"SEHR_GUT",IF(AB20>=3.6,"GUT",IF(AB20>=3,"BEDINGT","NICHT_EMPFOHLEN")))) -> SEHR_GUT | AD20: Steigung und längere Gehstrecke; kein Problem der Eintrittspflicht. | AE20: Die Quest kann auf vier Stationen gekürzt werden; Fontana Acqua Paola bleibt als Revive-Punkt erhalten.
A21: 17 | B21: D2-Q01 | C21: DAY_2 | D21: Stern des Kapitols | E21: Kapitolsplatz → Giulio Cesare | F21: =COUNTIF(Ortszuordnung!$A$5:$A$85,B21) -> 2 | G21: 15–25 | H21: 15 | I21: 25 | J21: ZUORDNUNG_REIHENFOLGE | K21: Kapitolinische Machtbilder | L21: ANTIKE_UND_RENAISSANCE | O21: =SUMIF(Ortszuordnung!$A$5:$A$85,B21,Ortszuordnung!$S$5:$S$85) -> 271 | P21: =ROUND(O21/Kriterien!$B$5,0) -> 4 | Q21: 15 | R21: =P21+Q21 -> 19 | S21: =IF(AND(R21>=H21,R21<=I21),"OK",IF(R21<H21,"ZU_KURZ","ZU_LANG")) -> OK | T21: =COUNTIFS(Ortszuordnung!$A$5:$A$85,B21,Ortszuordnung!$K$5:$K$85,"GRUEN") -> 1 | U21: =COUNTIFS(Ortszuordnung!$A$5:$A$85,B21,Ortszuordnung!$K$5:$K$85,"GELB") -> 1 | V21: =COUNTIFS(Ortszuordnung!$A$5:$A$85,B21,Ortszuordnung!$K$5:$K$85,"ROT") -> 0 | W21: 4.8 | X21: 4.8 | Y21: 4 | Z21: 4 | AA21: 4.7 | AB21: =ROUND(W21*Kriterien!$B$7+X21*Kriterien!$B$8+Y21*Kriterien!$B$9+Z21*Kriterien!$B$10+AA21*Kriterien!$B$11,1) -> 4.5 | AC21: =IF(V21>0,"NICHT_EMPFOHLEN",IF(AB21>=4.2,"SEHR_GUT",IF(AB21>=3.6,"GUT",IF(AB21>=3,"BEDINGT","NICHT_EMPFOHLEN")))) -> SEHR_GUT | AD21: Caesar-Attribut besitzt nur mittlere Quellen- und Sichtstärke. | AE21: Fallback: nur das robuste Stern-im-Oval-Muster des Platzes verwenden.
A22: 18 | B22: D2-Q02 | C22: DAY_2 | D22: Quadrigen der Einheit | E22: Nationaldenkmal für Viktor Emanuel II. | F22: =COUNTIF(Ortszuordnung!$A$5:$A$85,B22) -> 1 | G22: 5–15 | H22: 5 | I22: 15 | J22: BEOBACHTUNG_SUCHE | K22: Risorgimento und Nationalstaat | L22: 19_BIS_20_JAHRHUNDERT | O22: =SUMIF(Ortszuordnung!$A$5:$A$85,B22,Ortszuordnung!$S$5:$S$85) -> 0 | P22: =ROUND(O22/Kriterien!$B$5,0) -> 0 | Q22: 9 | R22: =P22+Q22 -> 9 | S22: =IF(AND(R22>=H22,R22<=I22),"OK",IF(R22<H22,"ZU_KURZ","ZU_LANG")) -> OK | T22: =COUNTIFS(Ortszuordnung!$A$5:$A$85,B22,Ortszuordnung!$K$5:$K$85,"GRUEN") -> 1 | U22: =COUNTIFS(Ortszuordnung!$A$5:$A$85,B22,Ortszuordnung!$K$5:$K$85,"GELB") -> 0 | V22: =COUNTIFS(Ortszuordnung!$A$5:$A$85,B22,Ortszuordnung!$K$5:$K$85,"ROT") -> 0 | W22: 5 | X22: 4.2 | Y22: 4.3 | Z22: 3.7 | AA22: 4.2 | AB22: =ROUND(W22*Kriterien!$B$7+X22*Kriterien!$B$8+Y22*Kriterien!$B$9+Z22*Kriterien!$B$10+AA22*Kriterien!$B$11,1) -> 4.3 | AC22: =IF(V22>0,"NICHT_EMPFOHLEN",IF(AB22>=4.2,"SEHR_GUT",IF(AB22>=3.6,"GUT",IF(AB22>=3,"BEDINGT","NICHT_EMPFOHLEN")))) -> SEHR_GUT | AD22: Menschenmenge; Quadrigen bleiben als Großform sichtbar. | AE22: Fallback: zentrale Reiterfigur statt Dachdetails.
A23: 19 | B23: D2-Q03 | C23: DAY_2 | D23: Arena und Triumph | E23: Konstantinsbogen → Kolosseum → Ludus Magnus | F23: =COUNTIF(Ortszuordnung!$A$5:$A$85,B23) -> 3 | G23: 25–35 | H23: 25 | I23: 35 | J23: KAMPF | K23: Triumph, Spektakel und Gladiatorentraining | L23: ANTIKE | N23: Gladiator des Ludus | O23: =SUMIF(Ortszuordnung!$A$5:$A$85,B23,Ortszuordnung!$S$5:$S$85) -> 446 | P23: =ROUND(O23/Kriterien!$B$5,0) -> 6 | Q23: 20 | R23: =P23+Q23 -> 26 | S23: =IF(AND(R23>=H23,R23<=I23),"OK",IF(R23<H23,"ZU_KURZ","ZU_LANG")) -> OK | T23: =COUNTIFS(Ortszuordnung!$A$5:$A$85,B23,Ortszuordnung!$K$5:$K$85,"GRUEN") -> 3 | U23: =COUNTIFS(Ortszuordnung!$A$5:$A$85,B23,Ortszuordnung!$K$5:$K$85,"GELB") -> 0 | V23: =COUNTIFS(Ortszuordnung!$A$5:$A$85,B23,Ortszuordnung!$K$5:$K$85,"ROT") -> 0 | W23: 5 | X23: 5 | Y23: 4.7 | Z23: 3.6 | AA23: 5 | AB23: =ROUND(W23*Kriterien!$B$7+X23*Kriterien!$B$8+Y23*Kriterien!$B$9+Z23*Kriterien!$B$10+AA23*Kriterien!$B$11,1) -> 4.7 | AC23: =IF(V23>0,"NICHT_EMPFOHLEN",IF(AB23>=4.2,"SEHR_GUT",IF(AB23>=3.6,"GUT",IF(AB23>=3,"BEDINGT","NICHT_EMPFOHLEN")))) -> SEHR_GUT | AD23: Sehr hohe Besucherzahl; nur Außenräume und Großformen. | AE23: Bei Überfüllung wird die Quest auf Konstantinsbogen und Ludus Magnus reduziert.
A24: 20 | B24: D2-Q04 | C24: DAY_2 | D24: Handel, Götter und Wahrheit | E24: Mund der Wahrheit → Tempel des Hercules Victor → Arco degli Argentari → Janusbogen | F24: =COUNTIF(Ortszuordnung!$A$5:$A$85,B24) -> 4 | G24: 35–45 | H24: 35 | I24: 45 | J24: DIALOG_ENTSCHEIDUNG | K24: Forum Boarium, Handel und Kulte | L24: ANTIKE_BIS_MITTELALTER | N24: Custode di Giano | O24: =SUMIF(Ortszuordnung!$A$5:$A$85,B24,Ortszuordnung!$S$5:$S$85) -> 390 | P24: =ROUND(O24/Kriterien!$B$5,0) -> 5 | Q24: 30 | R24: =P24+Q24 -> 35 | S24: =IF(AND(R24>=H24,R24<=I24),"OK",IF(R24<H24,"ZU_KURZ","ZU_LANG")) -> OK | T24: =COUNTIFS(Ortszuordnung!$A$5:$A$85,B24,Ortszuordnung!$K$5:$K$85,"GRUEN") -> 3 | U24: =COUNTIFS(Ortszuordnung!$A$5:$A$85,B24,Ortszuordnung!$K$5:$K$85,"GELB") -> 1 | V24: =COUNTIFS(Ortszuordnung!$A$5:$A$85,B24,Ortszuordnung!$K$5:$K$85,"ROT") -> 0 | W24: 5 | X24: 5 | Y24: 4.1 | Z24: 3.4 | AA24: 4.8 | AB24: =ROUND(W24*Kriterien!$B$7+X24*Kriterien!$B$8+Y24*Kriterien!$B$9+Z24*Kriterien!$B$10+AA24*Kriterien!$B$11,1) -> 4.5 | AC24: =IF(V24>0,"NICHT_EMPFOHLEN",IF(AB24>=4.2,"SEHR_GUT",IF(AB24>=3.6,"GUT",IF(AB24>=3,"BEDINGT","NICHT_EMPFOHLEN")))) -> SEHR_GUT | AD24: Bocca della Verità kann eine lange Warteschlange haben. | AE24: Bei Warteschlange wird die Bocca nur aus Distanz genutzt oder durch die Tempelform ersetzt.
A25: 21 | B25: D2-Q05 | C25: DAY_2 | D25: Masken über dem Circus | E25: Tritonenbrunnen → Belvedere Romolo E Remo → Maskenbrunnen bei Santa Sabina | F25: =COUNTIF(Ortszuordnung!$A$5:$A$85,B25) -> 3 | G25: 15–25 | H25: 15 | I25: 25 | J25: ZUORDNUNG_REIHENFOLGE | K25: Wasserfiguren und Aventinblick | L25: ANTIKE_REZEPTION_BIS_NEUZEIT | N25: Mascherone dell’Aventino | O25: =SUMIF(Ortszuordnung!$A$5:$A$85,B25,Ortszuordnung!$S$5:$S$85) -> 1079 | P25: =ROUND(O25/Kriterien!$B$5,0) -> 14 | Q25: 11 | R25: =P25+Q25 -> 25 | S25: =IF(AND(R25>=H25,R25<=I25),"OK",IF(R25<H25,"ZU_KURZ","ZU_LANG")) -> OK | T25: =COUNTIFS(Ortszuordnung!$A$5:$A$85,B25,Ortszuordnung!$K$5:$K$85,"GRUEN") -> 3 | U25: =COUNTIFS(Ortszuordnung!$A$5:$A$85,B25,Ortszuordnung!$K$5:$K$85,"GELB") -> 0 | V25: =COUNTIFS(Ortszuordnung!$A$5:$A$85,B25,Ortszuordnung!$K$5:$K$85,"ROT") -> 0 | W25: 4.2 | X25: 4.7 | Y25: 4.6 | Z25: 4 | AA25: 4.6 | AB25: =ROUND(W25*Kriterien!$B$7+X25*Kriterien!$B$8+Y25*Kriterien!$B$9+Z25*Kriterien!$B$10+AA25*Kriterien!$B$11,1) -> 4.5 | AC25: =IF(V25>0,"NICHT_EMPFOHLEN",IF(AB25>=4.2,"SEHR_GUT",IF(AB25>=3.6,"GUT",IF(AB25>=3,"BEDINGT","NICHT_EMPFOHLEN")))) -> SEHR_GUT | AD25: Kurzer Anstieg; Blickrichtung am Belvedere muss eindeutig sein. | AE25: Bei gesperrtem Brunnenbereich bleibt der Belvedere-Panoramafallback.
A26: 22 | B26: D2-Q06 | C26: DAY_2 | D26: Das steinerne Schiff | E26: Fontana della Navicella | F26: =COUNTIF(Ortszuordnung!$A$5:$A$85,B26) -> 1 | G26: 5–15 | H26: 5 | I26: 15 | J26: KURZTEXT_RAETSEL | K26: Antikenrezeption am Celio | L26: ANTIKE_REZEPTION | O26: =SUMIF(Ortszuordnung!$A$5:$A$85,B26,Ortszuordnung!$S$5:$S$85) -> 0 | P26: =ROUND(O26/Kriterien!$B$5,0) -> 0 | Q26: 9 | R26: =P26+Q26 -> 9 | S26: =IF(AND(R26>=H26,R26<=I26),"OK",IF(R26<H26,"ZU_KURZ","ZU_LANG")) -> OK | T26: =COUNTIFS(Ortszuordnung!$A$5:$A$85,B26,Ortszuordnung!$K$5:$K$85,"GRUEN") -> 1 | U26: =COUNTIFS(Ortszuordnung!$A$5:$A$85,B26,Ortszuordnung!$K$5:$K$85,"GELB") -> 0 | V26: =COUNTIFS(Ortszuordnung!$A$5:$A$85,B26,Ortszuordnung!$K$5:$K$85,"ROT") -> 0 | W26: 5 | X26: 4.2 | Y26: 4.4 | Z26: 4 | AA26: 4.1 | AB26: =ROUND(W26*Kriterien!$B$7+X26*Kriterien!$B$8+Y26*Kriterien!$B$9+Z26*Kriterien!$B$10+AA26*Kriterien!$B$11,1) -> 4.4 | AC26: =IF(V26>0,"NICHT_EMPFOHLEN",IF(AB26>=4.2,"SEHR_GUT",IF(AB26>=3.6,"GUT",IF(AB26>=3,"BEDINGT","NICHT_EMPFOHLEN")))) -> SEHR_GUT | AD26: Nur die Großform des Schiffs verwenden. | AE26: Fallback: Ausrichtung des Schiffs statt kleiner Details.
A27: 23 | B27: D2-Q07 | C27: DAY_2 | D27: Sitz der Kirche | E27: Lateranbasilika → Lateranischer Obelisk → Porta San Giovanni | F27: =COUNTIF(Ortszuordnung!$A$5:$A$85,B27) -> 3 | G27: 15–25 | H27: 15 | I27: 25 | J27: DIALOG_ENTSCHEIDUNG | K27: Lateran, Papsttum und Stadttor | L27: ANTIKE_BIS_BAROCK | O27: =SUMIF(Ortszuordnung!$A$5:$A$85,B27,Ortszuordnung!$S$5:$S$85) -> 657 | P27: =ROUND(O27/Kriterien!$B$5,0) -> 9 | Q27: 16 | R27: =P27+Q27 -> 25 | S27: =IF(AND(R27>=H27,R27<=I27),"OK",IF(R27<H27,"ZU_KURZ","ZU_LANG")) -> OK | T27: =COUNTIFS(Ortszuordnung!$A$5:$A$85,B27,Ortszuordnung!$K$5:$K$85,"GRUEN") -> 3 | U27: =COUNTIFS(Ortszuordnung!$A$5:$A$85,B27,Ortszuordnung!$K$5:$K$85,"GELB") -> 0 | V27: =COUNTIFS(Ortszuordnung!$A$5:$A$85,B27,Ortszuordnung!$K$5:$K$85,"ROT") -> 0 | W27: 4.7 | X27: 5 | Y27: 4.5 | Z27: 3.7 | AA27: 4.8 | AB27: =ROUND(W27*Kriterien!$B$7+X27*Kriterien!$B$8+Y27*Kriterien!$B$9+Z27*Kriterien!$B$10+AA27*Kriterien!$B$11,1) -> 4.6 | AC27: =IF(V27>0,"NICHT_EMPFOHLEN",IF(AB27>=4.2,"SEHR_GUT",IF(AB27>=3.6,"GUT",IF(AB27>=3,"BEDINGT","NICHT_EMPFOHLEN")))) -> SEHR_GUT | AD27: Menschenmenge und Verkehr, aber robuste Großformen. | AE27: Bei Verkehrssperre bleibt die Quest auf Basilika-Außenfassade und Obelisk.
A28: 24 | B28: D2-Q08 | C28: DAY_2 | D28: Tore der Aurelianischen Mauer | E28: Porta Latina → Porta Metronia | F28: =COUNTIF(Ortszuordnung!$A$5:$A$85,B28) -> 2 | G28: 25–35 | H28: 25 | I28: 35 | J28: ZUORDNUNG_REIHENFOLGE | K28: Stadtmauer und Verkehrsumbau | L28: ANTIKE_BIS_GEGENWART | N28: Scorpione delle Mura | O28: =SUMIF(Ortszuordnung!$A$5:$A$85,B28,Ortszuordnung!$S$5:$S$85) -> 899 | P28: =ROUND(O28/Kriterien!$B$5,0) -> 12 | Q28: 14 | R28: =P28+Q28 -> 26 | S28: =IF(AND(R28>=H28,R28<=I28),"OK",IF(R28<H28,"ZU_KURZ","ZU_LANG")) -> OK | T28: =COUNTIFS(Ortszuordnung!$A$5:$A$85,B28,Ortszuordnung!$K$5:$K$85,"GRUEN") -> 1 | U28: =COUNTIFS(Ortszuordnung!$A$5:$A$85,B28,Ortszuordnung!$K$5:$K$85,"GELB") -> 1 | V28: =COUNTIFS(Ortszuordnung!$A$5:$A$85,B28,Ortszuordnung!$K$5:$K$85,"ROT") -> 0 | W28: 3.2 | X28: 4.5 | Y28: 4.3 | Z28: 3.1 | AA28: 4.4 | AB28: =ROUND(W28*Kriterien!$B$7+X28*Kriterien!$B$8+Y28*Kriterien!$B$9+Z28*Kriterien!$B$10+AA28*Kriterien!$B$11,1) -> 4 | AC28: =IF(V28>0,"NICHT_EMPFOHLEN",IF(AB28>=4.2,"SEHR_GUT",IF(AB28>=3.6,"GUT",IF(AB28>=3,"BEDINGT","NICHT_EMPFOHLEN")))) -> GUT | AD28: Längere Gehstrecke und Verkehrsumfeld an Porta Metronia. | AE28: Wenn Porta Metronia nicht sicher anspielbar ist, wird nur Porta Latina als Kurzquest aktiviert.
A29: 25 | B29: D2-Q09 | C29: DAY_2 | D29: Schichten des Esquilino | E29: Basilika Groß Sankt Marien → Obelisco Esquilino → Thermae Traianae | F29: =COUNTIF(Ortszuordnung!$A$5:$A$85,B29) -> 3 | G29: 25–35 | H29: 25 | I29: 35 | J29: BEOBACHTUNG_SUCHE | K29: Kirche, Obelisk und antike Thermen | L29: ANTIKE_BIS_BAROCK | N29: Vapore delle Terme | O29: =SUMIF(Ortszuordnung!$A$5:$A$85,B29,Ortszuordnung!$S$5:$S$85) -> 1027 | P29: =ROUND(O29/Kriterien!$B$5,0) -> 14 | Q29: 20 | R29: =P29+Q29 -> 34 | S29: =IF(AND(R29>=H29,R29<=I29),"OK",IF(R29<H29,"ZU_KURZ","ZU_LANG")) -> OK | T29: =COUNTIFS(Ortszuordnung!$A$5:$A$85,B29,Ortszuordnung!$K$5:$K$85,"GRUEN") -> 2 | U29: =COUNTIFS(Ortszuordnung!$A$5:$A$85,B29,Ortszuordnung!$K$5:$K$85,"GELB") -> 1 | V29: =COUNTIFS(Ortszuordnung!$A$5:$A$85,B29,Ortszuordnung!$K$5:$K$85,"ROT") -> 0 | W29: 4 | X29: 5 | Y29: 4 | Z29: 3.2 | AA29: 4.6 | AB29: =ROUND(W29*Kriterien!$B$7+X29*Kriterien!$B$8+Y29*Kriterien!$B$9+Z29*Kriterien!$B$10+AA29*Kriterien!$B$11,1) -> 4.2 | AC29: =IF(V29>0,"NICHT_EMPFOHLEN",IF(AB29>=4.2,"SEHR_GUT",IF(AB29>=3.6,"GUT",IF(AB29>=3,"BEDINGT","NICHT_EMPFOHLEN")))) -> SEHR_GUT | AD29: Santa Maria Maggiore ist Bosszone und sehr belebt; Parkzugang zu den Thermen prüfen. | AE29: Bei Parkschließung endet die Quest am Esquilino-Obelisken.
A30: 26 | B30: D2-Q10 | C30: DAY_2 | D30: Wasser über dem Tor | E30: Porta Maggiore und Aqua Claudia | F30: =COUNTIF(Ortszuordnung!$A$5:$A$85,B30) -> 1 | G30: 5–15 | H30: 5 | I30: 15 | J30: KAMPF | K30: Aqua Claudia und Stadttor | L30: ANTIKE | N30: Idra dell’Aqua Claudia | O30: =SUMIF(Ortszuordnung!$A$5:$A$85,B30,Ortszuordnung!$S$5:$S$85) -> 0 | P30: =ROUND(O30/Kriterien!$B$5,0) -> 0 | Q30: 10 | R30: =P30+Q30 -> 10 | S30: =IF(AND(R30>=H30,R30<=I30),"OK",IF(R30<H30,"ZU_KURZ","ZU_LANG")) -> OK | T30: =COUNTIFS(Ortszuordnung!$A$5:$A$85,B30,Ortszuordnung!$K$5:$K$85,"GRUEN") -> 1 | U30: =COUNTIFS(Ortszuordnung!$A$5:$A$85,B30,Ortszuordnung!$K$5:$K$85,"GELB") -> 0 | V30: =COUNTIFS(Ortszuordnung!$A$5:$A$85,B30,Ortszuordnung!$K$5:$K$85,"ROT") -> 0 | W30: 5 | X30: 4.8 | Y30: 4.6 | Z30: 3.2 | AA30: 5 | AB30: =ROUND(W30*Kriterien!$B$7+X30*Kriterien!$B$8+Y30*Kriterien!$B$9+Z30*Kriterien!$B$10+AA30*Kriterien!$B$11,1) -> 4.6 | AC30: =IF(V30>0,"NICHT_EMPFOHLEN",IF(AB30>=4.2,"SEHR_GUT",IF(AB30>=3.6,"GUT",IF(AB30>=3,"BEDINGT","NICHT_EMPFOHLEN")))) -> SEHR_GUT | AD30: Sicherer Gehwegpunkt im Verkehrsknoten ist zwingend. | AE30: Bei ungeeignetem Gehwegpunkt wird die Quest vollständig deaktiviert.

Sheet Questdesign
A1: Via Romae – Questdesign-Entwürfe
A2: Narrativer Hook, Spielerhandlung, Belohnungsvariation, Hidden Opportunity und Fallback je regulärer Quest.
A4: Quest-ID | B4: Tag | C4: Arbeitstitel | D4: Narrativer Hook | E4: Kernhandlung der Spieler | F4: Sekundärmechaniken | G4: Belohnungsvariation | H4: Hidden Opportunity | I4: Fallback | J4: Redaktionsnotiz
A5: D1-Q01 | B5: DAY_1 | C5: Der Fluchtkorridor | D5: Rekonstruiert den Fluchtweg vom Petersplatz über den Passetto bis zur Engelsburg. | E5: An jedem Ort einen dauerhaften Hinweis identifizieren; am Ende entscheiden, wie die Nachhut den Rückzug deckt. | F5: GPS_ROUTE|BEOBACHTUNG|ZUORDNUNG|OPTIONALER_KAMPF | G5: Die Schlussentscheidung verändert Ruhm, Schutzbonus oder Kampfbelohnung. | H5: Ein unauffälliges Wappen kann einen kurzen Zusatzdialog der Schweizergarde öffnen. | I5: Bei unklarer Bodenmarkierung startet die Quest am Passetto mit dessen Mauerverlauf. | J5: Verbindlicher Klassenanker Schweizergardist; nur Außenpunkte.
A6: D1-Q02 | B6: DAY_1 | C6: Tore des Borgo | D6: Vergleicht drei sehr unterschiedliche Tore und entscheidet, welches ein Söldnerführer verteidigen würde. | E6: Torformen und Wappen zuordnen; taktische Entscheidung; Kampf gegen den päpstlichen Reiter. | F6: GPS_ROUTE|WAPPENSUCHE|FASSADENVERGLEICH|DIALOG | G6: Richtige Taktik gewährt Rüstungsbonus im Kampf. | H6: Das Borgia-Stiermotiv kann eine kurze Wappenspur auslösen. | I6: Wenn Porta Cavalleggeri nicht eindeutig ist, endet die Quest an Porta Santo Spirito. | J6: Verbindlicher Klassenanker Condottiere; aktuelle Sichtprüfung besonders wichtig.
A7: D1-Q03 | B7: DAY_1 | C7: Der Dreizack | D7: Lest Piazza, Obelisk und Tor als gemeinsam inszenierten nördlichen Eingang Roms. | E7: Dreizack erkennen, Löwen zählen und die Toröffnungen in die richtige historische Reihenfolge bringen. | F7: PANORAMABLICK|ZAEHLEN|REIHENFOLGE | G7: Fehlerfreie Reihenfolge gibt einen Navigationsbonus. | H7: Ein falscher Weg im Dreizack kann zu einer kurzen Irrläufer-Entscheidung führen. | I7: Bei dichter Menschenmenge nur Silhouetten und Großformen verwenden.
A8: D1-Q04 | B8: DAY_1 | C8: Antinoos über Rom | D8: Verbindet ägyptische Zeichen, Roms Gründungsbild und den Blick über die Stadt. | E8: Zeichen und Figuren zuordnen; die korrekte Deutung schwächt den Schatten des Antinoos. | F8: MYTHENFIGUREN|AUSSICHTSABGLEICH|ZUORDNUNG | G8: Jede richtige Zuordnung entfernt eine Gegnerfähigkeit. | H8: Die Wölfin kann eine optionale Gründungslegende öffnen. | I8: Bei gesperrtem Pincio wird die Quest deaktiviert; kein entfernter Ersatzpunkt.
A9: D1-Q05 | B9: DAY_1 | C9: Die steinerne Barke | D9: Erkennt, weshalb der Brunnen wie ein halb gesunkenes Boot wirkt. | E9: Ort erreichen, Großform bestimmen und zwischen vier Objektformen wählen. | F9: OBJEKTFORM|MULTIPLE_CHOICE | G9: Schneller Abschluss; kleiner Wissensbonus für die Bernini-Zuordnung. | H9: Keine Hidden-Komponente empfohlen: zu viele Passanten. | I9: Fallback ist die Richtung der großen Treppe zu Trinità dei Monti.
A10: D1-Q06 | B10: DAY_1 | C10: Berninis Werkstatt | D10: Lest die drei Brunnen als Werkstatt- und Inszenierungsraum des Barock. | E10: Brunnen ablaufen, Figurenattribute zuordnen und eine Werkstattentscheidung treffen. | F10: FIGURENDETAIL|VERGLEICH|DIALOG | G10: Die Werkstattwahl verändert Material- oder Ruhmbelohnung. | H10: Ein falsch zugeordnetes Tier kann einen humorvollen Lehrlingsauftrag öffnen. | I10: Fallback: Zahl und Lage der drei Brunnen statt einzelner Figurendetails. | J10: Verbindlicher Klassenanker Bildhauer; überschneidet sich bewusst mit Medienquest.
A11: D1-Q07 | B11: DAY_1 | C11: Agrippas Zeichen | D11: Entschlüsselt zwei kurze sichtbare Hinweise auf demselben Platz. | E11: AGRIPPA als normalisierte Texteingabe erfassen und den Obelisken seinem heutigen Träger zuordnen. | F11: INSCHRIFT|OBJEKTBEZIEHUNG|OPTIONALER_KAMPF | G11: Fehlerfreie Texteingabe schwächt die Mumie des Iseums. | H11: Die Hieroglyphen können einen optionalen Gegnerhinweis auslösen. | I11: Fallback: Portikusform am Pantheon und Obelisk-auf-Brunnen-Beziehung.
A12: D1-Q08 | B12: DAY_1 | C12: Kaiserbotschaften | D12: Vergleicht zwei Säulenmonumente und ihre sehr unterschiedlichen Bildsprachen. | E12: Hieroglyphen und Spiralrelief erkennen; Zweck und Bildsprache zuordnen. | F12: SCHRIFTERKENNUNG|RELIEFMUSTER|VERGLEICH | G12: Richtige Zuordnung gibt einen kurzen Wissensbonus. | H12: Keine zusätzliche Hidden Quest nötig. | I12: Fallback: Form des Reliefbands beziehungsweise Schriftart am Obelisken.
A13: D1-Q09 | B13: DAY_1 | C13: Das gebändigte Wasser | D13: Folgt der Aqua Virgo von sichtbaren Arkaden bis zu zwei monumentalen Brunnenbildern. | E13: Wasserweg nachvollziehen, große Figuren zählen und den Kanalratten-Gegner stellen. | F13: GPS_ROUTE|ARKADEN|FIGURENVERGLEICH | G13: Jeder korrekt gelesene Wasserhinweis reduziert eine Gift-/Schmutzfähigkeit. | H13: Die Arkaden können den versteckten Auftrag „Ratte des Aquädukts“ öffnen. | I13: Wenn die Arkaden verdeckt sind, nutzt die gleichörtige Materialfrage und setzt die Route fort.
A14: D1-Q10 | B14: DAY_1 | C14: Macht auf dem Quirinal | D14: Verfolgt, wie militärische und staatliche Macht am Quirinal sichtbar wird. | E14: Name, Pferdegruppe und heutige Institution erfassen; anschließend Loyalität wählen. | F14: INSCHRIFT|PFERDEGRUPPE|GESCHICHTSWAHL|OPTIONALER_KAMPF | G14: Die Loyalitätswahl verändert Dialog und Begegnungsbelohnung. | H14: Das Porträtrelief kann einen kurzen Söldnerkodex-Zweig öffnen. | I14: Bei unleserlicher Scanderbeg-Inschrift beginnt die Quest am Quirinal-Obelisken.
A15: D1-Q11 | B15: DAY_1 | C15: Zeichen der Unbefleckten | D15: Lest die Säule als Schichtung von antikem Material und neuzeitlicher Frömmigkeit. | E15: Spitzenfigur identifizieren und ihre Bedeutung in einer kurzen Auswahlfrage deuten. | F15: SILHOUETTE|SYMBOLDEUTUNG|MULTIPLE_CHOICE | G15: Kleine Wissens- oder Glaubensbelohnung. | H15: Keine Hidden-Komponente empfohlen. | I15: Fallback: Zahl der großen Sockelfiguren.
A16: D1-Q12 | B16: DAY_1 | C16: Stimmen der Republik | D16: Vergleicht, wie Brücke, Palast, Markt und Ruinen politische Macht erzählen. | E16: Vier große Hinweise sammeln und am Ende entscheiden, wessen Stimme im Stadtbild dominiert. | F16: GPS_ROUTE|WAPPEN|DENKMAL|GESCHICHTSWAHL | G16: Die Entscheidung verändert Ruhm, Wissen oder Denare. | H16: Giordano Brunos geschlossenes Buch kann einen Nebenauftrag auslösen. | I16: Jeder Abschnitt ist modular deaktivierbar; mindestens drei der vier Stationen müssen verfügbar sein.
A17: D1-Q13 | B17: DAY_1 | C17: Roms große Bühne | D17: Ordnet drei sehr verschiedene städtische Bühnen nach ihrer historischen Schicht. | E17: Fassadenasymmetrie, Brunnenfiguren und Arkadengeschosse erkennen und zeitlich ordnen. | F17: FASSADENDETAIL|FIGURENZAHL|SCHICHTENLESEN | G17: Richtige Reihenfolge gibt einen Dramaturgiebonus für die Bilderchronik. | H17: Die vier Schildkröten öffnen optional einen Wächterkampf. | I17: Fallback: Großformen an Sant’Andrea und Teatro; Tartarughen-Detail bei Bedarf auslassen.
A18: D1-Q14 | B18: DAY_1 | C18: Die steinerne Insel | D18: Verbindet die Schiffsform der Insel mit ihrer langen Geschichte als Heilort. | E18: Schiffsbug erkennen und die Tempelgeschichte in einem kurzen Rätsel deuten. | F18: FORMERKENNUNG|MEDIZINGESCHICHTE|DIALOG | G18: Richtige Deutung gewährt einen kleinen Heilbonus. | H18: Ein medizinisches Symbol kann einen Zusatzdialog öffnen. | I18: Fallback: allgemeine Inselform und sichtbare Brückenbeziehung.
A19: D1-Q15 | B19: DAY_1 | C19: Cecilias Stimmen | D19: Folgt der Erinnerung an Cecilia bis zum großen Mosaik von Santa Maria in Trastevere. | E19: Außenhinweise lesen und im Dialog entscheiden, wie Legende und belegte Geschichte getrennt erzählt werden. | F19: NAMENHINWEIS|FASSADENMOSAIK|SYMBOLDEUTUNG | G19: Sorgfältige Quellenwahl erhöht Glauben/Wissen statt bloßer Denare. | H19: Ein Musikbezug kann eine kurze klassenspezifische Nebenfrage öffnen. | I19: Wenn Santa Cecilia außen nicht eindeutig ist, startet die Quest auf der Piazza Santa Maria. | J19: Verbindlicher Klassenanker Kleriker; kein Innenraum.
A20: D1-Q16 | B20: DAY_1 | C20: Republik auf dem Gianicolo | D20: Steigt von den Mauern über das Ossarium und die Wasserfassade zu Garibaldi und Anita auf. | E20: Ereignisse und Denkmäler ordnen; am Ende Kampf gegen den Garibaldino der Mauern. | F20: GPS_ROUTE|DENKMAELER|WASSER|REIHENFOLGE | G20: Jede korrekt geordnete Station gibt dem Team einen gemeinsamen Buff. | H20: Ein Detail an Anitas Reitergruppe kann eine kurze Mutprobe öffnen. | I20: Die Quest kann auf vier Stationen gekürzt werden; Fontana Acqua Paola bleibt als Revive-Punkt erhalten.
A21: D2-Q01 | B21: DAY_2 | C21: Stern des Kapitols | D21: Lest Sternmuster und Caesarfigur als zwei bewusst gesetzte politische Zeichen. | E21: Muster und Attribut finden und den Aussagen Macht, Erinnerung oder Orientierung zuordnen. | F21: BODENMUSTER|FIGURENATTRIBUT|DIALOG | G21: Die Zuordnung verändert den folgenden Dialog. | H21: Keine Hidden-Komponente notwendig. | I21: Fallback: nur das robuste Stern-im-Oval-Muster des Platzes verwenden.
A22: D2-Q02 | B22: DAY_2 | C22: Quadrigen der Einheit | D22: Erkennt die zwei Quadrigen als monumentale Krönung des Nationaldenkmals. | E22: Großformen zählen und die Epoche des Denkmals zuordnen. | F22: SILHOUETTENZAEHLUNG|MULTIPLE_CHOICE | G22: Schneller Ruhmbonus. | H22: Keine Hidden-Komponente empfohlen. | I22: Fallback: zentrale Reiterfigur statt Dachdetails.
A23: D2-Q03 | B23: DAY_2 | C23: Arena und Triumph | D23: Verbindet Triumphbogen, Amphitheater und Trainingsarena zu einem Kampfkreislauf. | E23: Durchgänge und Arenaform lesen; daraus eine Taktik gegen den Gladiator ableiten. | F23: BOGENZAEHLUNG|ARENAFORM|TAKTIK | G23: Richtige Taktik beeinflusst Startinitiative und Beute. | H23: Ein Detail am Ludus kann einen optionalen Trainerdialog öffnen. | I23: Bei Überfüllung wird die Quest auf Konstantinsbogen und Ludus Magnus reduziert.
A24: D2-Q04 | B24: DAY_2 | C24: Handel, Götter und Wahrheit | D24: Lest vier eng benachbarte Monumente als Knoten von Handel, Kult und späterer Legende. | E24: Großformen vergleichen und am Ende entscheiden, welche Erklärung historisch, später oder legendär ist. | F24: GESICHTSDETAIL|BAUFORM|FORMVERGLEICH|RUNDGANG | G24: Saubere Trennung von Fakt und Legende erhöht Wissensbelohnung. | H24: Der Janusbogen kann einen optionalen Vier-Seiten-Wächter öffnen. | I24: Bei Warteschlange wird die Bocca nur aus Distanz genutzt oder durch die Tempelform ersetzt.
A25: D2-Q05 | B25: DAY_2 | C25: Masken über dem Circus | D25: Verbindet zwei Brunnenwesen mit dem Panorama über den Circus Maximus. | E25: Tritonen und Maske vergleichen und anschließend Palatin und Aventin richtig zuordnen. | F25: FIGURENVERGLEICH|MASKENDETAIL|PANORAMA | G25: Richtige Zuordnung gibt Bonus für die Streitwagen-Medienquest. | H25: Die Maske kann einen optionalen kurzen Gegnerkampf öffnen. | I25: Bei gesperrtem Brunnenbereich bleibt der Belvedere-Panoramafallback.
A26: D2-Q06 | B26: DAY_2 | C26: Das steinerne Schiff | D26: Deutet die Navicella als sichtbares Schiffssymbol vor dem Kirchenraum. | E26: Objektform erfassen und eine kurze Deutung auswählen oder eingeben. | F26: OBJEKTFORM|SYMBOLDEUTUNG | G26: Kleiner Navigations- oder Wissensbonus. | H26: Keine Hidden-Komponente empfohlen. | I26: Fallback: Ausrichtung des Schiffs statt kleiner Details.
A27: D2-Q07 | B27: DAY_2 | C27: Sitz der Kirche | D27: Verknüpft Kathedralfassade, Obelisk und Stadttor als geistliches und städtisches Machtzentrum. | E27: Drei Großhinweise erfassen und im Dialog geistliche, imperiale und städtische Funktion trennen. | F27: FASSADENSILHOUETTE|SCHRIFT|TORFORM | G27: Die Schlusswahl beeinflusst Glauben, Wissen oder Schutz. | H27: Eine klassenspezifische Klerikeroption ist sinnvoll, aber kein zusätzlicher Pflichtanker. | I27: Bei Verkehrssperre bleibt die Quest auf Basilika-Außenfassade und Obelisk.
A28: D2-Q08 | B28: DAY_2 | C28: Tore der Aurelianischen Mauer | D28: Vergleicht ein monumentales Tor mit einem vermauerten historischen Durchlass. | E28: Türme und Öffnungszustand erkennen; die beiden Orte nach Wehr- und Verkehrslogik zuordnen. | F28: GPS_ROUTE|ALT_NEU_VERGLEICH|TORFORM | G28: Richtige Zuordnung reduziert die Verteidigung des Mauerskorpions. | H28: Ein Mauerzeichen kann einen kurzen Nebenfund öffnen. | I28: Wenn Porta Metronia nicht sicher anspielbar ist, wird nur Porta Latina als Kurzquest aktiviert.
A29: D2-Q09 | B29: DAY_2 | C29: Schichten des Esquilino | D29: Lest drei sichtbare Schichten Roms vom Obelisken über die Basilika bis zur Ziegelruine. | E29: Großformen und Material erkennen; Schichten zeitlich ordnen; optionaler Dampfgegner. | F29: FASSADE|OBELISK|MATERIAL|OPTIONALER_KAMPF | G29: Richtige Chronologie gibt Widerstand gegen den späteren Boss. | H29: Der Thermendampf kann einen kurzen Kampf öffnen. | I29: Bei Parkschließung endet die Quest am Esquilino-Obelisken.
A30: D2-Q10 | B30: DAY_2 | C30: Wasser über dem Tor | D30: Erkennt den Doppelbogen als Tor und Träger zweier Wasserleitungen. | E30: Bögen und Aquäduktfunktion verbinden; danach kurzer Kampf gegen die Wasserhydra. | F30: DOPPELBOGEN|INFRASTRUKTUR|TAKTIK | G30: Korrekte Infrastrukturerklärung entfernt einen Hydrakopf. | H30: Keine zusätzliche Hidden Quest notwendig. | I30: Bei ungeeignetem Gehwegpunkt wird die Quest vollständig deaktiviert.

Sheet Mechanikbewertung
A1: Via Romae – Mechanikbewertung
A2: Eignung jeder Questkombination auf einer Skala von 0 bis 5. Null bedeutet irrelevant, fünf bedeutet ideal.
A4: Quest-ID | B4: Typ | C4: Tag | D4: Titel | E4: Orte | F4: Hauptmechanik | G4: GPS / Gehen | H4: Beobachtung / Suche | I4: Zählen / MC | J4: Zuordnen / Reihenfolge | K4: Kurze Texteingabe / Rätsel | L4: Dialog / Entscheidung | M4: Kampf | N4: Medien | O4: Max | P4: Stärkste Eignung | Q4: Warum funktioniert es? | R4: Schwäche / Bedingung
A5: D1-Q01 | B5: REGULAER | C5: DAY_1 | D5: Der Fluchtkorridor | E5: Petersplatz → Passetto di Borgo → Engelsburg | F5: DIALOG_ENTSCHEIDUNG | G5: 5 | H5: 4 | I5: 3 | J5: 3 | K5: 2 | L5: 5 | M5: 4 | N5: 0 | O5: =MAX(H5:N5) -> 5 | P5: =INDEX($H$4:$N$4,1,MATCH(O5,H5:N5,0)) -> Dialog / Entscheidung | Q5: An jedem Ort einen dauerhaften Hinweis identifizieren; am Ende entscheiden, wie die Nachhut den Rückzug deckt. | R5: Petersplatz: Menschenmenge und aktuelle Sicht der Bodenmarkierung.
A6: D1-Q02 | B6: REGULAER | C6: DAY_1 | D6: Tore des Borgo | E6: St.-Pellegrino-Tor → Porta Cavalleggeri → Porta Santo Spirito | F6: KAMPF | G6: 5 | H6: 4 | I6: 3 | J6: 3 | K6: 1 | L6: 4 | M6: 5 | N6: 0 | O6: =MAX(H6:N6) -> 5 | P6: =INDEX($H$4:$N$4,1,MATCH(O6,H6:N6,0)) -> Kampf | Q6: Torformen und Wappen zuordnen; taktische Entscheidung; Kampf gegen den päpstlichen Reiter. | R6: Zwei Hinweise sind relativ klein; Cavalleggeri ist nur als Mauerrest erhalten.
A7: D1-Q03 | B7: REGULAER | C7: DAY_1 | D7: Der Dreizack | E7: Piazza del Popolo → Obelisco Flaminio → Porta del Popolo | F7: BEOBACHTUNG_SUCHE | G7: 5 | H7: 5 | I7: 4 | J7: 2 | K7: 1 | L7: 2 | M7: 1 | N7: 0 | O7: =MAX(H7:N7) -> 5 | P7: =INDEX($H$4:$N$4,1,MATCH(O7,H7:N7,0)) -> Beobachtung / Suche | Q7: Dreizack erkennen, Löwen zählen und die Toröffnungen in die richtige historische Reihenfolge bringen. | R7: Hohe Besucherzahl, aber alle Hinweise sind groß.
A8: D1-Q04 | B8: REGULAER | C8: DAY_1 | D8: Antinoos über Rom | E8: Obelisco di Antinoo → Fontana della Dea di Roma → Balconata del Pincio | F8: KAMPF | G8: 5 | H8: 4 | I8: 3 | J8: 3 | K8: 1 | L8: 3 | M8: 5 | N8: 0 | O8: =MAX(H8:N8) -> 5 | P8: =INDEX($H$4:$N$4,1,MATCH(O8,H8:N8,0)) -> Kampf | Q8: Zeichen und Figuren zuordnen; die korrekte Deutung schwächt den Schatten des Antinoos. | R8: Parkzugang und Tageszeit beachten.
A9: D1-Q05 | B9: REGULAER | C9: DAY_1 | D9: Die steinerne Barke | E9: Spanischer Platz | F9: BEOBACHTUNG_SUCHE | G9: 3 | H9: 5 | I9: 4 | J9: 2 | K9: 1 | L9: 2 | M9: 1 | N9: 0 | O9: =MAX(H9:N9) -> 5 | P9: =INDEX($H$4:$N$4,1,MATCH(O9,H9:N9,0)) -> Beobachtung / Suche | Q9: Ort erreichen, Großform bestimmen und zwischen vier Objektformen wählen. | R9: Extreme Menschenmenge; nur die große Bootsform ist robust.
A10: D1-Q06 | B10: REGULAER | C10: DAY_1 | D10: Berninis Werkstatt | E10: Piazza Navona → Neptunsbrunnen → Mohrenbrunnen | F10: ZUORDNUNG_REIHENFOLGE | G10: 5 | H10: 4 | I10: 3 | J10: 5 | K10: 2 | L10: 4 | M10: 2 | N10: 0 | O10: =MAX(H10:N10) -> 5 | P10: =INDEX($H$4:$N$4,1,MATCH(O10,H10:N10,0)) -> Zuordnen / Reihenfolge | Q10: Brunnen ablaufen, Figurenattribute zuordnen und eine Werkstattentscheidung treffen. | R10: Menschenmenge; nur große Figurenattribute verwenden.
A11: D1-Q07 | B11: REGULAER | C11: DAY_1 | D11: Agrippas Zeichen | E11: Pantheon → Obelisco Macuteo | F11: KURZTEXT_RAETSEL | G11: 3 | H11: 4 | I11: 3 | J11: 3 | K11: 5 | L11: 3 | M11: 4 | N11: 0 | O11: =MAX(H11:N11) -> 5 | P11: =INDEX($H$4:$N$4,1,MATCH(O11,H11:N11,0)) -> Kurze Texteingabe / Rätsel | Q11: AGRIPPA als normalisierte Texteingabe erfassen und den Obelisken seinem heutigen Träger zuordnen. | R11: Pantheon-Außenpunkt und Besucherdichte müssen aktuell bestätigt werden.
A12: D1-Q08 | B12: REGULAER | C12: DAY_1 | D12: Kaiserbotschaften | E12: Obelisco di Montecitorio → Mark-Aurel-Säule | F12: ZUORDNUNG_REIHENFOLGE | G12: 4 | H12: 4 | I12: 3 | J12: 5 | K12: 2 | L12: 3 | M12: 2 | N12: 0 | O12: =MAX(H12:N12) -> 5 | P12: =INDEX($H$4:$N$4,1,MATCH(O12,H12:N12,0)) -> Zuordnen / Reihenfolge | Q12: Hieroglyphen und Spiralrelief erkennen; Zweck und Bildsprache zuordnen. | R12: Verkehr und Menschenmenge, Hinweise selbst sind groß.
A13: D1-Q09 | B13: REGULAER | C13: DAY_1 | D13: Das gebändigte Wasser | E13: Trevi-Brunnen → Acquedotto Vergine → Tritonenbrunnen | F13: KAMPF | G13: 5 | H13: 4 | I13: 3 | J13: 3 | K13: 1 | L13: 3 | M13: 5 | N13: 0 | O13: =MAX(H13:N13) -> 5 | P13: =INDEX($H$4:$N$4,1,MATCH(O13,H13:N13,0)) -> Kampf | Q13: Wasserweg nachvollziehen, große Figuren zählen und den Kanalratten-Gegner stellen. | R13: Trevi ist extrem voll; die antiken Arkaden sind teilweise verdeckt.
A14: D1-Q10 | B14: REGULAER | C14: DAY_1 | D14: Macht auf dem Quirinal | E14: Piazza Scanderbeg → Obelisco del Quirinale → Quirinalspalast | F14: DIALOG_ENTSCHEIDUNG | G14: 5 | H14: 4 | I14: 3 | J14: 3 | K14: 2 | L14: 5 | M14: 4 | N14: 0 | O14: =MAX(H14:N14) -> 5 | P14: =INDEX($H$4:$N$4,1,MATCH(O14,H14:N14,0)) -> Dialog / Entscheidung | Q14: Name, Pferdegruppe und heutige Institution erfassen; anschließend Loyalität wählen. | R14: Scanderbeg-Inschrift ist klein; am Palast Sicherheitsabstand einhalten.
A15: D1-Q11 | B15: REGULAER | C15: DAY_1 | D15: Zeichen der Unbefleckten | E15: Colonna dell'Immacolata | F15: KURZTEXT_RAETSEL | G15: 3 | H15: 4 | I15: 3 | J15: 3 | K15: 5 | L15: 3 | M15: 1 | N15: 0 | O15: =MAX(H15:N15) -> 5 | P15: =INDEX($H$4:$N$4,1,MATCH(O15,H15:N15,0)) -> Kurze Texteingabe / Rätsel | Q15: Spitzenfigur identifizieren und ihre Bedeutung in einer kurzen Auswahlfrage deuten. | R15: Menschenmenge, aber klare Silhouette.
A16: D1-Q12 | B16: REGULAER | C16: DAY_1 | D16: Stimmen der Republik | E16: Ponte Sisto → Palazzo Farnese → Campo de' Fiori → Largo di Torre Argentina | F16: DIALOG_ENTSCHEIDUNG | G16: 5 | H16: 4 | I16: 3 | J16: 3 | K16: 2 | L16: 5 | M16: 2 | N16: 0 | O16: =MAX(H16:N16) -> 5 | P16: =INDEX($H$4:$N$4,1,MATCH(O16,H16:N16,0)) -> Dialog / Entscheidung | Q16: Vier große Hinweise sammeln und am Ende entscheiden, wessen Stimme im Stadtbild dominiert. | R16: Campo-Marktzeiten, Palazzo-Sicherheitsbereich und Überblick am Largo.
... A44: B-D2-01 | B44: WORLD_BOSS | C44: DAY_2 | D44: Custode della Neve | E44: Basilika Groß Sankt Marien | F44: KAMPF | G44: 3 | H44: 3 | I44: 1 | J44: 1 | K44: 0 | L44: 4 | M44: 5 | N44: 1 | O44: =MAX(H44:N44) -> 5 | P44: =INDEX($H$4:$N$4,1,MATCH(O44,H44:N44,0)) -> Kampf | Q44: Tag-2-Finale vor Santa Maria Maggiore; Schneemotiv ausdrücklich als Legende erzählen. | R44: Sehr hohe Besucherzahl; sichere Bossfläche muss remote aktuell geprüft werden.

Sheet Ortszuordnung
A1: Via Romae – Ortszuordnung
A2: Jede Station mit Reihenfolge, Koordinate, Ortsfrage, Quelle und nachvollziehbarer Distanzschätzung.
A4: Quest-ID | B4: Questtyp | C4: Tag | D4: Sequenz | E4: Kandidaten-ID | F4: Ort | G4: Rolle in der Quest | H4: Cluster | I4: Breite | J4: Länge | K4: Ampel | L4: Research-Status | M4: Sichtbarer Hinweis | N4: Ortsfrage | O4: Sollantwort | P4: Primärquelle | Q4: Google Maps | R4: Segment Luftlinie (m) | S4: Gehstrecke geschätzt (m) | T4: Zugangs-/Fallbacknotiz | U4: Gegnerbezug
A5: D1-Q01 | B5: REGULAER | C5: DAY_1 | D5: 1 | E5: place_day_1_piazza_san_pietro | F5: Petersplatz | G5: START / ERSTER HINWEIS | H5: D1_VATICANO_PRATI_BORGO | I5: 41.902229 | J5: 12.457358 | K5: GELB | L5: GELB_MENSCHENMENGE | M5: Runde Marmor-Brennpunktmarkierung im Pflaster zwischen Obelisk und Kolonnade; danach Blick auf die großen Säulen. | N5: Stellt euch auf eine der runden Marmorplatten auf der Querachse des Obelisken und blickt zur Kolonnade. Wie viele Säulenreihen scheinen übrig zu bleiben? | O5: Eine | P5: https://www.turismoroma.it/it/luoghi/piazza-san-pietro | Q5: https://www.google.com/maps/search/?api=1&query=41.9022286,12.4573576 | R5: =IF(A5=A4,ROUND(SQRT(POWER((I5-I4)*111000,2)+POWER((J5-J4)*111000*COS(RADIANS((I5+I4)/2)),2)),0),0) -> 0 | S5: =ROUND(R5*Kriterien!$B$6,0) -> 0 | T5: V03-Punkt; Die Bodenmarkierung muss vor Veröffentlichung auf einem aktuellen Bild eindeutig lokalisiert werden. | U5: Schatten des Passetto
A6: D1-Q01 | B6: REGULAER | C6: DAY_1 | D6: 2 | E6: place_day_1_passetto_di_borgo | F6: Passetto di Borgo | G6: ZWISCHENSTATION | H6: D1_VATICANO_PRATI_BORGO | I6: 41.903273 | J6: 12.461072 | K6: GRUEN | L6: GRUEN_MIT_BLICKPUNKT | M6: Langer, geschlossener Maueraufbau mit kleinen Öffnungen; vom öffentlichen Straßenraum sichtbar. | N6: Wo verläuft der befestigte Verbindungsgang des Passetto? | O6: Auf der Mauer | P6: https://www.turismoroma.it/en/places/passetto-di-borgo | Q6: https://www.google.com/maps/search/?api=1&query=41.9032733,12.4610723 | R6: =IF(A6=A5,ROUND(SQRT(POWER((I6-I5)*111000,2)+POWER((J6-J5)*111000*COS(RADIANS((I6+I5)/2)),2)),0),0) -> 328 | S6: =ROUND(R6*Kriterien!$B$6,0) -> 410 | T6: V03-Punkt; Exakten Gehsteig-Blickpunkt im Dossier verwenden; der begehbare Passetto selbst ist nicht erforderlich. | U6: Schatten des Passetto
A7: D1-Q01 | B7: REGULAER | C7: DAY_1 | D7: 3 | E7: place_day_1_castel_sant_angelo | F7: Engelsburg | G7: ABSCHLUSS | H7: D1_VATICANO_PRATI_BORGO | I7: 41.90262 | J7: 12.46686 | K7: GRUEN | L7: GRUEN_AUSSENPUNKT | M7: Große geflügelte Bronzefigur auf dem höchsten Punkt, vom öffentlichen Vorplatz sichtbar. | N7: Welche geflügelte Figur bekrönt die Engelsburg? | O7: Der Erzengel Michael | P7: https://www.turismoroma.it/en/places/santangelo-castle | Q7: https://www.google.com/maps/search/?api=1&query=41.90262,12.46686 | R7: =IF(A7=A6,ROUND(SQRT(POWER((I7-I6)*111000,2)+POWER((J7-J6)*111000*COS(RADIANS((I7+I6)/2)),2)),0),0) -> 484 | S7: =ROUND(R7*Kriterien!$B$6,0) -> 605 | T7: Moved from the monument centroid to the public exterior forecourt at the bridge/castle approach. No ticket or castle entry may be required.; Nur der öffentliche Vorplatz darf als Trigger dienen; kein Eintritt in die Burg. | U7: Schatten des Passetto
A8: D1-Q02 | B8: REGULAER | C8: DAY_1 | D8: 1 | E8: place_day_1_porta_san_pellegrino | F8: St.-Pellegrino-Tor | G8: START / ERSTER HINWEIS | H8: D1_VATICANO_PRATI_BORGO | I8: 41.903386 | J8: 12.457148 | K8: GELB | L8: GELB_DETAIL_HOCH | M8: Großer Torbogen und hoch angebrachtes päpstliches Wappen mit Stiermotiv. | N8: Welches Tier erkennt ihr im Wappen über dem Torbogen? | O8: Einen Stier | P8: https://it.wikipedia.org/wiki/Porta_San_Pellegrino | Q8: https://www.google.com/maps/search/?api=1&query=41.903386,12.4571483 | R8: =IF(A8=A7,ROUND(SQRT(POWER((I8-I7)*111000,2)+POWER((J8-J7)*111000*COS(RADIANS((I8+I7)/2)),2)),0),0) -> 0 | S8: =ROUND(R8*Kriterien!$B$6,0) -> 0 | T8: V03-Punkt; Der Stier ist relativ hoch angebracht; Antwortgröße auf aktuellen Bildern prüfen. | U8: Cavalleggero Pontificio
A9: D1-Q02 | B9: REGULAER | C9: DAY_1 | D9: 2 | E9: place_day_1_porta_cavalleggeri | F9: Porta Cavalleggeri | G9: ZWISCHENSTATION | H9: D1_VATICANO_PRATI_BORGO | I9: 41.900388 | J9: 12.456315 | K9: GELB | L9: GELB_KLEINER_MAUERREST | M9: Ein einzelner erhaltener Mauerbogen mit päpstlichen Zeichen nahe dem Vatikan. | N9: Wie viele historische Hauptbögen sind als Torrest sichtbar? | O9: Einer | P9: https://www.openstreetmap.org/node/6205478926 | Q9: https://www.google.com/maps/search/?api=1&query=41.9003883,12.4563148 | R9: =IF(A9=A8,ROUND(SQRT(POWER((I9-I8)*111000,2)+POWER((J9-J8)*111000*COS(RADIANS((I9+I8)/2)),2)),0),0) -> 340 | S9: =ROUND(R9*Kriterien!$B$6,0) -> 425 | T9: V03-Punkt; Als Ersatz für einen zu vollen Petersplatz geeignet; Sichtbarkeit zwischen Verkehr und parkenden Fahrzeugen prüfen. | U9: Cavalleggero Pontificio
A10: D1-Q02 | B10: REGULAER | C10: DAY_1 | D10: 3 | E10: place_day_1_porta_santo_spirito | F10: Porta Santo Spirito | G10: ABSCHLUSS | H10: D1_VATICANO_PRATI_BORGO | I10: 41.900304 | J10: 12.461587 | K10: GRUEN | L10: GRUEN_MIT_BLICKPUNKT | M10: Großer Mittelbogen, paarweise Säulen und deutlich erkennbare leere Nischen. | N10: Welche Kombination flankiert den großen mittleren Bogen? | O10: Dorische Säulen und leere Nischen | P10: https://www.turismoroma.it/it/luoghi/porta-santo-spirito | Q10: https://www.google.com/maps/search/?api=1&query=41.9003045,12.4615874 | R10: =IF(A10=A9,ROUND(SQRT(POWER((I10-I9)*111000,2)+POWER((J10-J9)*111000*COS(RADIANS((I10+I9)/2)),2)),0),0) -> 436 | S10: =ROUND(R10*Kriterien!$B$6,0) -> 545 | T10: V03-Punkt; VISUAL_EVIDENCE_NOT_YET_VERIFIED | U10: Cavalleggero Pontificio
A11: D1-Q03 | B11: REGULAER | C11: DAY_1 | D11: 1 | E11: place_day_1_piazza_del_popolo | F11: Piazza del Popolo | G11: START / ERSTER HINWEIS | H11: D1_POPOLO_PINCIO_SPAGNA | I11: 41.910749 | J11: 12.476345 | K11: GRUEN | L11: GRUEN_KONZEPTREIF | M11: Zwei große Kuppelkirchen am südlichen Platzende und drei radial ausgehende Straßen. | N11: Wie viele nahezu spiegelbildliche Kuppelkirchen flankieren den Beginn der Via del Corso? | O11: Zwei | P11: https://en.wikipedia.org/wiki/Piazza_del_Popolo | Q11: https://www.google.com/maps/search/?api=1&query=41.9107491,12.4763454 | R11: =IF(A11=A10,ROUND(SQRT(POWER((I11-I10)*111000,2)+POWER((J11-J10)*111000*COS(RADIANS((I11+I10)/2)),2)),0),0) -> 0 | S11: =ROUND(R11*Kriterien!$B$6,0) -> 0 | T11: V03-Punkt; VISUAL_EVIDENCE_NOT_YET_VERIFIED|CROWDING_RISK
A12: D1-Q03 | B12: REGULAER | C12: DAY_1 | D12: 2 | E12: place_day_1_obelisco_flaminio | F12: Obelisco Flaminio | G12: ZWISCHENSTATION | H12: D1_POPOLO_PINCIO_SPAGNA | I12: 41.910708 | J12: 12.476343 | K12: GRUEN | L12: GRUEN_KONZEPTREIF | M12: Vier monumentale Löwenbrunnen unmittelbar um den Sockel. | N12: Wie viele Löwenbrunnen stehen rund um den Sockel des Obelisken? | O12: Vier | P12: https://en.wikipedia.org/wiki/Flaminio_Obelisk | Q12: https://www.google.com/maps/search/?api=1&query=41.9107077,12.4763431 | R12: =IF(A12=A11,ROUND(SQRT(POWER((I12-I11)*111000,2)+POWER((J12-J11)*111000*COS(RADIANS((I12+I11)/2)),2)),0),0) -> 5 | S12: =ROUND(R12*Kriterien!$B$6,0) -> 6 | T12: V03-Punkt; VISUAL_EVIDENCE_NOT_YET_VERIFIED|CROWDING_RISK
A13: D1-Q03 | B13: REGULAER | C13: DAY_1 | D13: 3 | E13: place_day_1_porta_del_popolo | F13: Porta del Popolo | G13: ABSCHLUSS | H13: D1_POPOLO_PINCIO_SPAGNA | I13: 41.911525 | J13: 12.475994 | K13: GRUEN | L13: GRUEN_KONZEPTREIF | M13: Drei große heutige Öffnungen, davon ein höherer Mittelbogen. | N13: Wie viele große Durchgänge besitzt die Porta del Popolo heute? | O13: Drei | P13: https://en.wikipedia.org/wiki/Porta_del_Popolo | Q13: https://www.google.com/maps/search/?api=1&query=41.9115252,12.4759941 | R13: =IF(A13=A12,ROUND(SQRT(POWER((I13-I12)*111000,2)+POWER((J13-J12)*111000*COS(RADIANS((I13+I12)/2)),2)),0),0) -> 95 | S13: =ROUND(R13*Kriterien!$B$6,0) -> 119 | T13: V03-Punkt; VISUAL_EVIDENCE_NOT_YET_VERIFIED
A14: D1-Q04 | B14: REGULAER | C14: DAY_1 | D14: 1 | E14: place_day_1_obelisco_di_antinoo | F14: Obelisco di Antinoo | G14: START / ERSTER HINWEIS | H14: D1_POPOLO_PINCIO_SPAGNA | I14: 41.910809 | J14: 12.479749 | K14: GRUEN | L14: GRUEN_PARKZUGANG | M14: Hieroglyphen auf allen Schaftseiten und deutliche Obeliskform. | N14: Welche Art von Schriftzeichen bedeckt den Schaft? | O14: Hieroglyphen | P14: https://it.wikipedia.org/wiki/Obelisco_del_Pincio | Q14: https://www.google.com/maps/search/?api=1&query=41.9108092,12.479749 | R14: =IF(A14=A13,ROUND(SQRT(POWER((I14-I13)*111000,2)+POWER((J14-J13)*111000*COS(RADIANS((I14+I13)/2)),2)),0),0) -> 0 | S14: =ROUND(R14*Kriterien!$B$6,0) -> 0 | T14: V03-Punkt; VISUAL_EVIDENCE_NOT_YET_VERIFIED|CROWDING_RISK | U14: Ombra di Antinoo
A15: D1-Q04 | B15: REGULAER | C15: DAY_1 | D15: 2 | E15: place_day_1_fontana_della_dea_di_roma | F15: Fontana della Dea di Roma | G15: ZWISCHENSTATION | H15: D1_POPOLO_PINCIO_SPAGNA | I15: 41.910917 | J15: 12.477178 | K15: GRUEN | L15: GRUEN_PARKZUGANG | M15: Zentrale sitzende Göttin und gut erkennbare Wölfin mit Zwillingen im unteren Bereich. | N15: Welches Tier ist zusammen mit den Zwillingen Romulus und Remus dargestellt? | O15: Eine Wölfin | P15: https://www.openstreetmap.org/relation/11496554 | Q15: https://www.google.com/maps/search/?api=1&query=41.9109167,12.4771784 | R15: =IF(A15=A14,ROUND(SQRT(POWER((I15-I14)*111000,2)+POWER((J15-J14)*111000*COS(RADIANS((I15+I14)/2)),2)),0),0) -> 213 | S15: =ROUND(R15*Kriterien!$B$6,0) -> 266 | T15: V03-Punkt; VISUAL_EVIDENCE_NOT_YET_VERIFIED | U15: Ombra di Antinoo
A16: D1-Q04 | B16: REGULAER | C16: DAY_1 | D16: 3 | E16: place_day_1_balconata_del_pincio | F16: Balconata del Pincio | G16: ABSCHLUSS | H16: D1_POPOLO_PINCIO_SPAGNA | I16: 41.911091 | J16: 12.477935 | K16: GRUEN | L16: GRUEN_PARKZUGANG | M16: Große Balustrade mit unmittelbarem Überblick auf Piazza del Popolo. | N16: Welcher große Platz liegt direkt unter der Aussichtsterrasse? | O16: Piazza del Popolo | P16: https://www.openstreetmap.org/node/649529694 | Q16: https://www.google.com/maps/search/?api=1&query=41.9110905,12.4779346 | R16: =IF(A16=A15,ROUND(SQRT(POWER((I16-I15)*111000,2)+POWER((J16-J15)*111000*COS(RADIANS((I16+I15)/2)),2)),0),0) -> 65 | S16: =ROUND(R16*Kriterien!$B$6,0) -> 81 | T16: V03-Punkt; VISUAL_EVIDENCE_NOT_YET_VERIFIED | U16: Ombra di Antinoo
A17: D1-Q05 | B17: REGULAER | C17: DAY_1 | D17: 1 | E17: place_day_1_piazza_di_spagna | F17: Spanischer Platz | G17: START / ERSTER HINWEIS | H17: D1_POPOLO_PINCIO_SPAGNA | I17: 41.905666 | J17: 12.482277 | K17: GRUEN | L17: GRUEN_MENSCHENMENGE | M17: Bootsförmiger Brunnen am Fuß der großen Freitreppe. | N17: Welche Form hat der Brunnen am Fuß der Spanischen Treppe? | O17: Ein Boot | P17: https://it.wikipedia.org/wiki/Piazza_di_Spagna | Q17: https://www.google.com/maps/search/?api=1&query=41.9056657,12.4822771 | R17: =IF(A17=A16,ROUND(SQRT(POWER((I17-I16)*111000,2)+POWER((J17-J16)*111000*COS(RADIANS((I17+I16)/2)),2)),0),0) -> 0 | S17: =ROUND(R17*Kriterien!$B$6,0) -> 0 | T17: V03-Punkt; Die sehr hohe Besucherzahl kann Zähl- und Bodenaufgaben stören; nur Großform verwenden.
A18: D1-Q06 | B18: REGULAER | C18: DAY_1 | D18: 1 | E18: place_day_1_piazza_navona | F18: Piazza Navona | G18: START / ERSTER HINWEIS | H18: D1_NAVONA_PANTHEON | I18: 41.898926 | J18: 12.473099 | K18: GRUEN | L18: GRUEN_MENSCHENMENGE | M18: Drei weit auseinanderliegende Großbrunnen entlang der Platzachse. | N18: Wie viele große Brunnen liegen entlang der Längsachse der Piazza Navona? | O18: Drei | P18: https://it.wikipedia.org/wiki/Piazza_Navona | Q18: https://www.google.com/maps/search/?api=1&query=41.8989256,12.4730991 | R18: =IF(A18=A17,ROUND(SQRT(POWER((I18-I17)*111000,2)+POWER((J18-J17)*111000*COS(RADIANS((I18+I17)/2)),2)),0),0) -> 0 | S18: =ROUND(R18*Kriterien!$B$6,0) -> 0 | T18: V03-Punkt; Für die Medienquest sind alle drei Brunnen als separate Fotostationen zu markieren.
A19: D1-Q06 | B19: REGULAER | C19: DAY_1 | D19: 2 | E19: place_day_1_fontana_del_nettuno | F19: Neptunsbrunnen | G19: ZWISCHENSTATION | H19: D1_NAVONA_PANTHEON | I19: 41.899798 | J19: 12.473021 | K19: GRUEN | L19: GRUEN_KONZEPTREIF | M19: Große zentrale Neptunfigur im Ringkampf mit einem vielarmigen Meerestier. | N19: Mit welchem Meerestier ringt Neptun in der zentralen Skulptur? | O19: Mit einem Oktopus | P19: https://it.wikipedia.org/wiki/Fontana_del_Nettuno_(Roma) | Q19: https://www.google.com/maps/search/?api=1&query=41.8997976,12.4730207 | R19: =IF(A19=A18,ROUND(SQRT(POWER((I19-I18)*111000,2)+POWER((J19-J18)*111000*COS(RADIANS((I19+I18)/2)),2)),0),0) -> 97 | S19: =ROUND(R19*Kriterien!$B$6,0) -> 121 | T19: V03-Punkt; VISUAL_EVIDENCE_NOT_YET_VERIFIED|CROWDING_RISK
A20: D1-Q06 | B20: REGULAER | C20: DAY_1 | D20: 3 | E20: place_day_1_fontana_del_moro | F20: Mohrenbrunnen | G20: ABSCHLUSS | H20: D1_NAVONA_PANTHEON | I20: 41.898111 | J20: 12.473153 | K20: GRUEN | L20: GRUEN_KONZEPTREIF | M20: Zentrale männliche Figur mit Delfin; vier Tritonen im unteren Becken. | N20: Welches Tier hält die zentrale Figur des Mohrenbrunnens fest? | O20: Einen Delfin | P20: https://it.wikipedia.org/wiki/Fontana_del_Moro | Q20: https://www.google.com/maps/search/?api=1&query=41.8981115,12.4731529 | R20: =IF(A20=A19,ROUND(SQRT(POWER((I20-I19)*111000,2)+POWER((J20-J19)*111000*COS(RADIANS((I20+I19)/2)),2)),0),0) -> 187 | S20: =ROUND(R20*Kriterien!$B$6,0) -> 234 | T20: V03-Punkt; VISUAL_EVIDENCE_NOT_YET_VERIFIED|CROWDING_RISK
A21: D1-Q07 | B21: REGULAER | C21: DAY_1 | D21: 1 | E21: place_day_1_pantheon | F21: Pantheon | G21: START / ERSTER HINWEIS | H21: D1_NAVONA_PANTHEON | I21: 41.898626 | J21: 12.476833 | K21: GRUEN | L21: GRUEN_AUSSENPUNKT | M21: Sehr große lateinische Inschrift über dem Portikus; vollständig vom öffentlichen Platz lesbar. | N21: Welcher Name steht in der obersten Zeile der großen Inschrift über dem Eingang? | O21: AGRIPPA | P21: https://www.turismoroma.it/it/luoghi/pantheon | Q21: https://www.google.com/maps/search/?api=1&query=41.8986261,12.4768335 | R21: =IF(A21=A20,ROUND(SQRT(POWER((I21-I20)*111000,2)+POWER((J21-J20)*111000*COS(RADIANS((I21+I20)/2)),2)),0),0) -> 0 | S21: =ROUND(R21*Kriterien!$B$6,0) -> 0 | T21: V03-Punkt; Trigger auf Piazza della Rotonda legen; kein Eintritt und keine Innenfrage. | U21: Mummia dell’Iseo
A22: D1-Q07 | B22: REGULAER | C22: DAY_1 | D22: 2 | E22: place_day_1_obelisco_macuteo | F22: Obelisco Macuteo | G22: ABSCHLUSS | H22: D1_NAVONA_PANTHEON | I22: 41.899312 | J22: 12.47674 | K22: GRUEN | L22: GRUEN_MENSCHENMENGE | M22: Obelisk mit Hieroglyphen, der sichtbar aus der Brunnenanlage der Piazza della Rotonda aufragt. | N22: Auf welchem Bauwerk steht der Obelisco Macuteo heute? | O22: Auf einem Brunnen | P22: https://it.wikipedia.org/wiki/Obelisco_del_Pantheon | Q22: https://www.google.com/maps/search/?api=1&query=41.8993124,12.4767399 | R22: =IF(A22=A21,ROUND(SQRT(POWER((I22-I21)*111000,2)+POWER((J22-J21)*111000*COS(RADIANS((I22+I21)/2)),2)),0),0) -> 77 | S22: =ROUND(R22*Kriterien!$B$6,0) -> 96 | T22: V03-Punkt; VISUAL_EVIDENCE_NOT_YET_VERIFIED | U22: Mummia dell’Iseo
A23: D1-Q08 | B23: REGULAER | C23: DAY_1 | D23: 1 | E23: place_day_1_obelisco_di_montecitorio | F23: Obelisco di Montecitorio | G23: START / ERSTER HINWEIS | H23: D1_NAVONA_PANTHEON | I23: 41.900679 | J23: 12.478665 | K23: GRUEN | L23: GRUEN_KONZEPTREIF | M23: Monumentaler Schaft mit Hieroglyphen und einer Metallkugel an der Spitze. | N23: Welche Schriftzeichen bedecken den Schaft des Obelisken? | O23: Ägyptische Hieroglyphen | P23: https://it.wikipedia.org/wiki/Obelisco_di_Montecitorio | Q23: https://www.google.com/maps/search/?api=1&query=41.9006787,12.4786653 | R23: =IF(A23=A22,ROUND(SQRT(POWER((I23-I22)*111000,2)+POWER((J23-J22)*111000*COS(RADIANS((I23+I22)/2)),2)),0),0) -> 0 | S23: =ROUND(R23*Kriterien!$B$6,0) -> 0 | T23: V03-Punkt; VISUAL_EVIDENCE_NOT_YET_VERIFIED|CROWDING_RISK
A24: D1-Q08 | B24: REGULAER | C24: DAY_1 | D24: 2 | E24: place_day_1_colonna_di_marco_aurelio | F24: Mark-Aurel-Säule | G24: ABSCHLUSS | H24: D1_NAVONA_PANTHEON | I24: 41.900848 | J24: 12.479987 | K24: GRUEN | L24: GRUEN_KONZEPTREIF | M24: Breites spiralförmiges Reliefband und große Figur auf der Spitze. | N24: In welchem Muster läuft das Reliefband um die Säule? | O24: Spiralförmig | P24: https://it.wikipedia.org/wiki/Colonna_di_Marco_Aurelio | Q24: https://www.google.com/maps/search/?api=1&query=41.9008477,12.4799871 | R24: =IF(A24=A23,ROUND(SQRT(POWER((I24-I23)*111000,2)+POWER((J24-J23)*111000*COS(RADIANS((I24+I23)/2)),2)),0),0) -> 111 | S24: =ROUND(R24*Kriterien!$B$6,0) -> 139 | T24: V03-Punkt; VISUAL_EVIDENCE_NOT_YET_VERIFIED
A25: D1-Q09 | B25: REGULAER | C25: DAY_1 | D25: 1 | E25: place_day_1_fontana_di_trevi | F25: Trevi-Brunnen | G25: START / ERSTER HINWEIS | H25: D1_TREVI_QUIRINALE | I25: 41.900965 | J25: 12.483282 | K25: GELB | L25: GELB_EXTREME_MENSCHENMENGE | M25: Zwei große Seepferde vor dem muschelförmigen Wagen der Zentralfigur. | N25: Wie viele Seepferde ziehen den Wagen der zentralen Figur? | O25: Zwei | P25: https://it.wikipedia.org/wiki/Fontana_di_Trevi | Q25: https://www.google.com/maps/search/?api=1&query=41.9009648,12.4832817 | R25: =IF(A25=A24,ROUND(SQRT(POWER((I25-I24)*111000,2)+POWER((J25-J24)*111000*COS(RADIANS((I25+I24)/2)),2)),0),0) -> 0 | S25: =ROUND(R25*Kriterien!$B$6,0) -> 0 | T25: V03-Punkt; Nur von mehreren Positionen erkennbare Großdetails verwenden; keine Boden- oder Randdetails. | U25: Ratto dell’Acqua Virgo
A26: D1-Q09 | B26: REGULAER | C26: DAY_1 | D26: 2 | E26: place_day_1_acquedotto_vergine | F26: Acquedotto Vergine | G26: ZWISCHENSTATION | H26: D1_TREVI_QUIRINALE | I26: 41.902611 | J26: 12.483711 | K26: GELB | L26: GELB_TEILWEISE_VERDECKT | M26: Drei teilweise im heutigen Bodenniveau versunkene Travertinarkaden hinter einer Absperrung. | N26: Wie viele kleinere antike Arkaden sind in der Via del Nazareno nebeneinander erhalten? | O26: Drei | P26: https://www.sovraintendenzaroma.it/i_luoghi/roma_antica/monumenti/acquedotto_vergine | Q26: https://www.google.com/maps/search/?api=1&query=41.9026109,12.4837108 | R26: =IF(A26=A25,ROUND(SQRT(POWER((I26-I25)*111000,2)+POWER((J26-J25)*111000*COS(RADIANS((I26+I25)/2)),2)),0),0) -> 186 | S26: =ROUND(R26*Kriterien!$B$6,0) -> 233 | T26: V03-Punkt; Die Arkaden sind teilweise eingetieft und durch Gitter verdeckt; nur nach aktuellem Sichttest als Pflichtfrage einsetzen. | U26: Ratto dell’Acqua Virgo
A27: D1-Q09 | B27: REGULAER | C27: DAY_1 | D27: 3 | E27: place_day_1_fontana_del_tritone | F27: Tritonenbrunnen | G27: ABSCHLUSS | H27: D1_TREVI_QUIRINALE | I27: 41.903662 | J27: 12.488479 | K27: GRUEN | L27: GRUEN_KONZEPTREIF | M27: Vier große Delfine, Muschelschale, Triton mit Schneckenhorn. | N27: Wie viele Delfine tragen die große Muschel? | O27: Vier | P27: https://it.wikipedia.org/wiki/Fontana_del_Tritone | Q27: https://www.google.com/maps/search/?api=1&query=41.903662,12.4884786 | R27: =IF(A27=A26,ROUND(SQRT(POWER((I27-I26)*111000,2)+POWER((J27-J26)*111000*COS(RADIANS((I27+I26)/2)),2)),0),0) -> 411 | S27: =ROUND(R27*Kriterien!$B$6,0) -> 514 | T27: V03-Punkt; VISUAL_EVIDENCE_NOT_YET_VERIFIED|CROWDING_RISK | U27: Ratto dell’Acqua Virgo
A28: D1-Q10 | B28: REGULAER | C28: DAY_1 | D28: 1 | E28: place_day_1_piazza_scanderbeg | F28: Piazza Scanderbeg | G28: START / ERSTER HINWEIS | H28: D1_TREVI_QUIRINALE | I28: 41.900664 | J28: 12.484829 | K28: GELB | L28: GELB_KLEINES_FASSADENDETAIL | M28: Steinernes Porträtrelief mit lesbarem Namen an der Hausfassade. | N28: Welcher Name steht beim Porträtrelief am Palazzo Scanderbeg? | O28: Scanderbeg | P28: https://en.wikipedia.org/wiki/Piazza_Scanderbeg | Q28: https://www.google.com/maps/search/?api=1&query=41.9006643,12.4848288 | R28: =IF(A28=A27,ROUND(SQRT(POWER((I28-I27)*111000,2)+POWER((J28-J27)*111000*COS(RADIANS((I28+I27)/2)),2)),0),0) -> 0 | S28: =ROUND(R28*Kriterien!$B$6,0) -> 0 | T28: V03-Punkt; VISUAL_EVIDENCE_NOT_YET_VERIFIED | U28: Corazziere del Colle
A29: D1-Q10 | B29: REGULAER | C29: DAY_1 | D29: 2 | E29: place_day_1_obelisco_del_quirinale | F29: Obelisco del Quirinale | G29: ZWISCHENSTATION | H29: D1_TREVI_QUIRINALE | I29: 41.899064 | J29: 12.486643 | K29: GRUEN | L29: GRUEN_KONZEPTREIF | M29: Zwei monumentale Pferdegruppen flankieren den Obelisken. | N29: Wie viele monumentale Pferde flankieren den Obelisken? | O29: Zwei | P29: https://it.wikipedia.org/wiki/Obelisco_del_Quirinale | Q29: https://www.google.com/maps/search/?api=1&query=41.899064,12.4866425 | R29: =IF(A29=A28,ROUND(SQRT(POWER((I29-I28)*111000,2)+POWER((J29-J28)*111000*COS(RADIANS((I29+I28)/2)),2)),0),0) -> 232 | S29: =ROUND(R29*Kriterien!$B$6,0) -> 290 | T29: V03-Punkt; VISUAL_EVIDENCE_NOT_YET_VERIFIED | U29: Corazziere del Colle
A30: D1-Q10 | B30: REGULAER | C30: DAY_1 | D30: 3 | E30: place_day_1_palazzo_del_quirinale | F30: Quirinalspalast | G30: ABSCHLUSS | H30: D1_TREVI_QUIRINALE | I30: 41.900663 | J30: 12.487614 | K30: GRUEN | L30: GRUEN_SICHERHEITSABSTAND | M30: Monumentale lange Palastfassade und Hauptportal an der öffentlich zugänglichen Piazza del Quirinale. | N30: Welche heutige staatliche Institution nutzt den Quirinalspalast? | O30: Der Präsident der Italienischen Republik | P30: https://palazzo.quirinale.it/palazzo_en.html | Q30: https://www.google.com/maps/search/?api=1&query=41.9006627,12.4876143 | R30: =IF(A30=A29,ROUND(SQRT(POWER((I30-I29)*111000,2)+POWER((J30-J29)*111000*COS(RADIANS((I30+I29)/2)),2)),0),0) -> 195 | S30: =ROUND(R30*Kriterien!$B$6,0) -> 244 | T30: V03-Punkt; Keine Annäherung an Wachen oder Eingang verlangen; Trigger auf der freien Platzfläche. | U30: Corazziere del Colle
A31: D1-Q11 | B31: REGULAER | C31: DAY_1 | D31: 1 | E31: place_day_1_colonna_dell_immacolata | F31: Colonna dell'Immacolata | G31: START / ERSTER HINWEIS | H31: D1_TREVI_QUIRINALE | I31: 41.904994 | J31: 12.482962 | K31: GRUEN | L31: GRUEN_KONZEPTREIF | M31: Große Marienstatue auf der Spitze und vier sitzende Sockelfiguren. | N31: Welche religiöse Figur steht auf der Spitze der Säule? | O31: Maria | P31: https://it.wikipedia.org/wiki/Colonna_dell'Immacolata_(Roma) | Q31: https://www.google.com/maps/search/?api=1&query=41.9049939,12.482962 | R31: =IF(A31=A30,ROUND(SQRT(POWER((I31-I30)*111000,2)+POWER((J31-J30)*111000*COS(RADIANS((I31+I30)/2)),2)),0),0) -> 0 | S31: =ROUND(R31*Kriterien!$B$6,0) -> 0 | T31: V03-Punkt; VISUAL_EVIDENCE_NOT_YET_VERIFIED
A32: D1-Q12 | B32: REGULAER | C32: DAY_1 | D32: 1 | E32: place_day_1_ponte_sisto | F32: Ponte Sisto | G32: START / ERSTER HINWEIS | H32: D1_CAMPO_REGOLA_GHETTO | I32: 41.892346 | J32: 12.47077 | K32: GRUEN | L32: GRUEN_MIT_BLICKPUNKT | M32: Große kreisrunde Öffnung zwischen den beiden mittleren Brückenbögen. | N32: Welche geometrische Form hat die Öffnung zwischen den beiden mittleren Brückenbögen? | O32: Einen Kreis | P32: https://www.turismoroma.it/it/luoghi/ponte-sisto | Q32: https://www.google.com/maps/search/?api=1&query=41.8923463,12.4707703 | R32: =IF(A32=A31,ROUND(SQRT(POWER((I32-I31)*111000,2)+POWER((J32-J31)*111000*COS(RADIANS((I32+I31)/2)),2)),0),0) -> 0 | S32: =ROUND(R32*Kriterien!$B$6,0) -> 0 | T32: V03-Punkt; VISUAL_EVIDENCE_NOT_YET_VERIFIED
A33: D1-Q12 | B33: REGULAER | C33: DAY_1 | D33: 2 | E33: place_day_1_palazzo_farnese | F33: Palazzo Farnese | G33: ZWISCHENSTATION | H33: D1_CAMPO_REGOLA_GHETTO | I33: 41.894653 | J33: 12.470682 | K33: GELB | L33: GELB_SICHERHEITSBEREICH | M33: Großes päpstliches Wappen über dem Mittelportal und wiederkehrende Lilienmotive. | N33: Welches heraldische Symbol wiederholt sich im Farnese-Wappen? | O33: Die Lilie | P33: https://it.wikipedia.org/wiki/Palazzo_Farnese_(Roma) | Q33: https://www.google.com/maps/search/?api=1&query=41.8946528,12.4706818 | R33: =IF(A33=A32,ROUND(SQRT(POWER((I33-I32)*111000,2)+POWER((J33-J32)*111000*COS(RADIANS((I33+I32)/2)),2)),0),0) -> 256 | S33: =ROUND(R33*Kriterien!$B$6,0) -> 320 | T33: V03-Punkt; Botschaftsgebäude: keine längere Gruppenblockade direkt vor dem Eingang; gegenüberstehenden Blickpunkt wählen.
A34: D1-Q12 | B34: REGULAER | C34: DAY_1 | D34: 3 | E34: place_day_1_campo_de_fiori | F34: Campo de' Fiori | G34: ZWISCHENSTATION | H34: D1_CAMPO_REGOLA_GHETTO | I34: 41.895573 | J34: 12.472122 | K34: GRUEN | L34: GRUEN_MIT_MARKTRISIKO | M34: Monumentale dunkle Bronzefigur; geschlossenes Buch direkt unter den gekreuzten Händen. | N34: Welchen Gegenstand hält Giordano Bruno unter seinen gekreuzten Händen? | O34: Ein geschlossenes Buch | P34: https://www.sovraintendenzaroma.it/i_luoghi/roma_medioevale_e_moderna/monumenti/monumento_a_giordano_bruno | Q34: https://www.google.com/maps/search/?api=1&query=41.8955725,12.4721223 | R34: =IF(A34=A33,ROUND(SQRT(POWER((I34-I33)*111000,2)+POWER((J34-J33)*111000*COS(RADIANS((I34+I33)/2)),2)),0),0) -> 157 | S34: =ROUND(R34*Kriterien!$B$6,0) -> 196 | T34: V03-Punkt; Am Vormittag kann der Markt die Sockelsicht einschränken; Aufgabe auf die große Figur beschränken.
A35: D1-Q12 | B35: REGULAER | C35: DAY_1 | D35: 4 | E35: place_day_1_largo_di_torre_argentina | F35: Largo di Torre Argentina | G35: ABSCHLUSS | H35: D1_CAMPO_REGOLA_GHETTO | I35: 41.895397 | J35: 12.476886 | K35: GELB | L35: GELB_ZAEHLPERSPEKTIVE | M35: Vier klar getrennte Tempelkomplexe im tiefer liegenden Areal. | N35: Wie viele republikanische Tempel sind im Areal zusammengefasst? | O35: Vier | P35: https://it.wikipedia.org/wiki/Largo_di_Torre_Argentina | Q35: https://www.google.com/maps/search/?api=1&query=41.8953968,12.4768864 | R35: =IF(A35=A34,ROUND(SQRT(POWER((I35-I34)*111000,2)+POWER((J35-J34)*111000*COS(RADIANS((I35+I34)/2)),2)),0),0) -> 394 | S35: =ROUND(R35*Kriterien!$B$6,0) -> 493 | T35: V03-Punkt; Trigger auf öffentlichen Gehweg legen; kein Betreten des inzwischen zugänglichen, aber zeitgebundenen Areals.
A36: D1-Q13 | B36: REGULAER | C36: DAY_1 | D36: 1 | E36: place_day_1_basilica_di_sant_andrea_della_valle | F36: Basilica di Sant'Andrea della Valle | G36: START / ERSTER HINWEIS | H36: D1_CAMPO_REGOLA_GHETTO | I36: 41.896003 | J36: 12.474333 | K36: GELB | L36: GELB_FASSADENSICHT | M36: Einzelne große Engelsfigur auf der linken Fassadenseite, wenn man vor der Kirche steht. | N36: Auf welcher Seite der Fassade sitzt die einzelne große Engelsfigur? | O36: Links | P36: https://it.wikipedia.org/wiki/Basilica_di_Sant'Andrea_della_Valle | Q36: https://www.google.com/maps/search/?api=1&query=41.8960034,12.4743329 | R36: =IF(A36=A35,ROUND(SQRT(POWER((I36-I35)*111000,2)+POWER((J36-J35)*111000*COS(RADIANS((I36+I35)/2)),2)),0),0) -> 0 | S36: =ROUND(R36*Kriterien!$B$6,0) -> 0 | T36: V03-Punkt; Nur Außenfassade; die Kuppelfresken und Innenkunst dürfen nicht Teil der Pflichtaufgabe sein. | U36: Custode delle Tartarughe
A37: D1-Q13 | B37: REGULAER | C37: DAY_1 | D37: 2 | E37: place_day_1_fontana_delle_tartarughe | F37: Fontana delle Tartarughe | G37: ZWISCHENSTATION | H37: D1_TREVI_QUIRINALE | I37: 41.893782 | J37: 12.477456 | K37: GRUEN | L37: GRUEN_KONZEPTREIF | M37: Vier deutlich sichtbare Schildkröten am Rand des oberen Beckens. | N37: Wie viele Schildkröten klettern zum oberen Becken? | O37: Vier | P37: https://www.turismoroma.it/it/luoghi/fontana-delle-tartarughe | Q37: https://www.google.com/maps/search/?api=1&query=41.893782,12.477456 | R37: =IF(A37=A36,ROUND(SQRT(POWER((I37-I36)*111000,2)+POWER((J37-J36)*111000*COS(RADIANS((I37+I36)/2)),2)),0),0) -> 357 | S37: =ROUND(R37*Kriterien!$B$6,0) -> 446 | T37: Corrected an erroneous OSM-derived point to the official Turismo Roma coordinate in Piazza Mattei.; VISUAL_EVIDENCE_NOT_YET_VERIFIED | U37: Custode delle Tartarughe
A38: D1-Q13 | B38: REGULAER | C38: DAY_1 | D38: 3 | E38: place_day_1_teatro_di_marcello | F38: Marcellustheater | G38: ABSCHLUSS | H38: D1_CAMPO_REGOLA_GHETTO | I38: 41.892202 | J38: 12.479938 | K38: GRUEN | L38: GRUEN_AUSSENPUNKT | M38: Zwei übereinanderliegende antike Arkadenebenen unter einem späteren Wohnpalast. | N38: Wie viele übereinanderliegende antike Arkadengeschosse sind von außen klar sichtbar? | O38: Zwei | P38: https://www.turismoroma.it/it/luoghi/teatro-di-marcello | Q38: https://www.google.com/maps/search/?api=1&query=41.892202,12.479938 | R38: =IF(A38=A37,ROUND(SQRT(POWER((I38-I37)*111000,2)+POWER((J38-J37)*111000*COS(RADIANS((I38+I37)/2)),2)),0),0) -> 270 | S38: =ROUND(R38*Kriterien!$B$6,0) -> 338 | T38: V03-Punkt; Offizieller Fußweg erlaubt Außenbesichtigung; Medienquest-Pickup ohne Zugang zu Innenräumen. | U38: Custode delle Tartarughe
A39: D1-Q14 | B39: REGULAER | C39: DAY_1 | D39: 1 | E39: place_day_1_isola_tiberina | F39: Isola Tiberina | G39: START / ERSTER HINWEIS | H39: D1_CAMPO_REGOLA_GHETTO | I39: 41.889637 | J39: 12.479234 | K39: GELB | L39: GELB_SICHTWINKEL | M39: Travertinreste einer Schiffsspitze und Asklepios-Relief am östlichen Inselende. | N39: Welche Form ahmt die antike Travertinverkleidung an der Inselspitze nach? | O39: Den Bug eines Schiffes | P39: https://www.openstreetmap.org/node/4798313727 | Q39: https://www.google.com/maps/search/?api=1&query=41.8896365,12.4792342 | R39: =IF(A39=A38,ROUND(SQRT(POWER((I39-I38)*111000,2)+POWER((J39-J38)*111000*COS(RADIANS((I39+I38)/2)),2)),0),0) -> 0 | S39: =ROUND(R39*Kriterien!$B$6,0) -> 0 | T39: V03-Punkt; Nur verwenden, wenn der genaue öffentliche Blickpunkt und die freie Sicht auf die Travertinreste bestätigt sind.
A40: D1-Q15 | B40: REGULAER | C40: DAY_1 | D40: 1 | E40: place_day_1_basilica_di_santa_cecilia_in_trastevere | F40: Basilica di Santa Cecilia in Trastevere | G40: START / ERSTER HINWEIS | H40: D1_TRASTEVERE_TIBER_ISLAND | I40: 41.887561 | J40: 12.475857 | K40: GELB | L40: GELB_KLASSENANKER_OHNE_INNENHOF | M40: Kirchenname und Widmung am äußeren Zugang; Innenhofbrunnen nur optional, weil der Hof zeitabhängig sein kann. | N40: Welche Kunst wird traditionell von der hier verehrten heiligen Cecilia beschützt? | O40: Die Musik | P40: https://it.wikipedia.org/wiki/Basilica_di_Santa_Cecilia_in_Trastevere | Q40: https://www.google.com/maps/search/?api=1&query=41.8875608,12.4758567 | R40: =IF(A40=A39,ROUND(SQRT(POWER((I40-I39)*111000,2)+POWER((J40-J39)*111000*COS(RADIANS((I40+I39)/2)),2)),0),0) -> 0 | S40: =ROUND(R40*Kriterien!$B$6,0) -> 0 | T40: V03-Punkt; Für die Kleriker-Klassengeschichte nur Außenpunkt vor dem Tor nutzen; der vorhandene Punkt im Hof ist zu versetzen.
A41: D1-Q15 | B41: REGULAER | C41: DAY_1 | D41: 2 | E41: place_day_1_basilica_di_santa_maria_in_trastevere | F41: Santa Maria in Trastevere | G41: ABSCHLUSS | H41: D1_TRASTEVERE_TIBER_ISLAND | I41: 41.889426 | J41: 12.469494 | K41: GRUEN | L41: GRUEN_AUSSENPUNKT | M41: Großes goldenes Mosaik hoch an der Fassade; vom Platz sichtbar. | N41: Welche zwei Hauptfiguren sitzen im Zentrum des großen Fassadenmosaiks? | O41: Maria und Christus | P41: https://it.wikipedia.org/wiki/Basilica_di_Santa_Maria_in_Trastevere | Q41: https://www.google.com/maps/search/?api=1&query=41.8894264,12.4694941 | R41: =IF(A41=A40,ROUND(SQRT(POWER((I41-I40)*111000,2)+POWER((J41-J40)*111000*COS(RADIANS((I41+I40)/2)),2)),0),0) -> 565 | S41: =ROUND(R41*Kriterien!$B$6,0) -> 706 | T41: V03-Punkt; VISUAL_EVIDENCE_NOT_YET_VERIFIED|EXTERIOR_VANTAGE_POINT_REQUIRED|INTERIOR_AND_OPENING_HOURS_MUST_NOT_BE_REQUIRED|CROWDING_RISK
A42: D1-Q16 | B42: REGULAER | C42: DAY_1 | D42: 1 | E42: place_day_1_mura_gianicolensi_2 | F42: Gianicolense-Mauern | G42: START / ERSTER HINWEIS | H42: D1_GIANICOLO | I42: 41.886977 | J42: 12.46163 | K42: GRUEN | L42: GRUEN_MIT_GEWEGPUNKT | M42: Langer massiver Mauerabschnitt mit Schieß- und Verteidigungsformen. | N42: Aus welchem Material besteht der sichtbare Hauptkörper der Mauer überwiegend? | O42: Aus Ziegelmauerwerk | P42: https://turismoroma.it/es/node/31555 | Q42: https://www.google.com/maps/search/?api=1&query=41.8869765,12.4616301 | R42: =IF(A42=A41,ROUND(SQRT(POWER((I42-I41)*111000,2)+POWER((J42-J41)*111000*COS(RADIANS((I42+I41)/2)),2)),0),0) -> 0 | S42: =ROUND(R42*Kriterien!$B$6,0) -> 0 | T42: V03-Punkt; VISUAL_EVIDENCE_NOT_YET_VERIFIED | U42: Garibaldino delle Mura
A43: D1-Q16 | B43: REGULAER | C43: DAY_1 | D43: 2 | E43: place_day_1_mausoleo_ossario_garibaldino | F43: Mausoleo Ossario Garibaldino | G43: ZWISCHENSTATION | H43: D1_TRASTEVERE_TIBER_ISLAND | I43: 41.888193 | J43: 12.465613 | K43: GRUEN | L43: GRUEN_KONZEPTREIF | M43: Symmetrischer Zentralbau mit vier großen offenen Bögen. | N43: Wie viele offene Bogenfronten umgeben den zentralen Teil des Ossariums? | O43: Vier | P43: https://it.wikipedia.org/wiki/Mausoleo_Ossario_Garibaldino | Q43: https://www.google.com/maps/search/?api=1&query=41.8881928,12.4656132 | R43: =IF(A43=A42,ROUND(SQRT(POWER((I43-I42)*111000,2)+POWER((J43-J42)*111000*COS(RADIANS((I43+I42)/2)),2)),0),0) -> 356 | S43: =ROUND(R43*Kriterien!$B$6,0) -> 445 | T43: V03-Punkt; VISUAL_EVIDENCE_NOT_YET_VERIFIED | U43: Garibaldino delle Mura
A44: D1-Q16 | B44: REGULAER | C44: DAY_1 | D44: 3 | E44: place_day_1_fontana_dell_acqua_paola | F44: Fontana Dell'Acqua Paola | G44: ZWISCHENSTATION | H44: D1_GIANICOLO | I44: 41.888819 | J44: 12.464242 | K44: GRUEN | L44: GRUEN_KONZEPTREIF | M44: Fünf weithin sichtbare Bogenfelder in der Hauptfassade. | N44: Wie viele große Bogenöffnungen gliedern die Hauptfassade? | O44: Fünf | P44: https://it.wikipedia.org/wiki/Fontana_dell'Acqua_Paola | Q44: https://www.google.com/maps/search/?api=1&query=41.8888192,12.4642423 | R44: =IF(A44=A43,ROUND(SQRT(POWER((I44-I43)*111000,2)+POWER((J44-J43)*111000*COS(RADIANS((I44+I43)/2)),2)),0),0) -> 133 | S44: =ROUND(R44*Kriterien!$B$6,0) -> 166 | T44: V03-Punkt; VISUAL_EVIDENCE_NOT_YET_VERIFIED|CROWDING_RISK | U44: Garibaldino delle Mura
A45: D1-Q16 | B45: REGULAER | C45: DAY_1 | D45: 4 | E45: place_day_1_monumento_a_garibaldi | F45: Monumento a Garibaldi | G45: ZWISCHENSTATION | H45: D1_GIANICOLO | I45: 41.891464 | J45: 12.460769 | K45: GRUEN | L45: GRUEN_KONZEPTREIF | M45: Große Reiterfigur auf hohem Sockel. | N45: Auf welchem Tier sitzt Giuseppe Garibaldi? | O45: Auf einem Pferd | P45: https://it.wikipedia.org/wiki/Monumento_a_Giuseppe_Garibaldi_(Roma) | Q45: https://www.google.com/maps/search/?api=1&query=41.8914637,12.4607686 | R45: =IF(A45=A44,ROUND(SQRT(POWER((I45-I44)*111000,2)+POWER((J45-J44)*111000*COS(RADIANS((I45+I44)/2)),2)),0),0) -> 411 | S45: =ROUND(R45*Kriterien!$B$6,0) -> 514 | T45: V03-Punkt; VISUAL_EVIDENCE_NOT_YET_VERIFIED | U45: Garibaldino delle Mura
A46: D1-Q16 | B46: REGULAER | C46: DAY_1 | D46: 5 | E46: place_day_1_monumento_ad_anita_garibaldi | F46: Monumento ad Anita Garibaldi | G46: ABSCHLUSS | H46: D1_GIANICOLO | I46: 41.893411 | J46: 12.460117 | K46: GRUEN | L46: GRUEN_KONZEPTREIF | M46: Große Reiterfigur mit deutlich erhobener Handwaffe. | N46: Welche Waffe hält Anita Garibaldi in der erhobenen Hand? | O46: Eine Pistole | P46: https://it.wikipedia.org/wiki/Monumento_ad_Anita_Garibaldi | Q46: https://www.google.com/maps/search/?api=1&query=41.8934109,12.460117 | R46: =IF(A46=A45,ROUND(SQRT(POWER((I46-I45)*111000,2)+POWER((J46-J45)*111000*COS(RADIANS((I46+I45)/2)),2)),0),0) -> 223 | S46: =ROUND(R46*Kriterien!$B$6,0) -> 279 | T46: V03-Punkt; VISUAL_EVIDENCE_NOT_YET_VERIFIED | U46: Garibaldino delle Mura
A47: D2-Q01 | B47: REGULAER | C47: DAY_2 | D47: 1 | E47: place_day_2_piazza_del_campidoglio | F47: Kapitolsplatz | G47: START / ERSTER HINWEIS | H47: D2_CAMPIDOGLIO_FORI_TRAIANEI | I47: 41.893229 | J47: 12.482965 | K47: GRUEN | L47: GRUEN_KONZEPTREIF | M47: Großes hell-dunkles Sternoval im Pflaster um die Reiterstatue. | N47: Welches geometrische Motiv prägt das Pflaster rund um die Reiterstatue? | O47: Ein Stern in einem Oval | P47: https://it.wikipedia.org/wiki/Piazza_del_Campidoglio | Q47: https://www.google.com/maps/search/?api=1&query=41.8932288,12.4829654 | R47: =IF(A47=A46,ROUND(SQRT(POWER((I47-I46)*111000,2)+POWER((J47-J46)*111000*COS(RADIANS((I47+I46)/2)),2)),0),0) -> 0 | S47: =ROUND(R47*Kriterien!$B$6,0) -> 0 | T47: V03-Punkt; VISUAL_EVIDENCE_NOT_YET_VERIFIED|CROWDING_RISK
A48: D2-Q01 | B48: REGULAER | C48: DAY_2 | D48: 2 | E48: place_day_2_giulio_cesare | F48: Giulio Cesare | G48: ABSCHLUSS | H48: D2_CAMPIDOGLIO_FORI_TRAIANEI | I48: 41.893997 | J48: 12.485383 | K48: GELB | L48: GELB_QUELLENLAGE | M48: Lebensgroße Bronze mit deutlich sichtbarer Schriftrolle in der linken Hand. | N48: Welchen Gegenstand hält Caesar in der linken Hand? | O48: Eine Schriftrolle | P48: https://www.openstreetmap.org/node/7239169954 | Q48: https://www.google.com/maps/search/?api=1&query=41.8939965,12.4853829 | R48: =IF(A48=A47,ROUND(SQRT(POWER((I48-I47)*111000,2)+POWER((J48-J47)*111000*COS(RADIANS((I48+I47)/2)),2)),0),0) -> 217 | S48: =ROUND(R48*Kriterien!$B$6,0) -> 271 | T48: V03-Punkt; Für die konkrete moderne Statue ist zusätzlich ein kommunaler Inventareintrag wünschenswert.
A49: D2-Q02 | B49: REGULAER | C49: DAY_2 | D49: 1 | E49: place_day_2_altare_della_patria | F49: Nationaldenkmal für Viktor Emanuel II. | G49: START / ERSTER HINWEIS | H49: D2_CAMPIDOGLIO_FORI_TRAIANEI | I49: 41.894705 | J49: 12.483184 | K49: GRUEN | L49: GRUEN_MENSCHENMENGE | M49: Zwei monumentale Quadrigen auf den oberen Enden des Bauwerks. | N49: Wie viele große Quadrigen stehen auf den beiden oberen Enden des Nationaldenkmals? | O49: Zwei | P49: https://vive.cultura.gov.it/ | Q49: https://www.google.com/maps/search/?api=1&query=41.8947045,12.4831835 | R49: =IF(A49=A48,ROUND(SQRT(POWER((I49-I48)*111000,2)+POWER((J49-J48)*111000*COS(RADIANS((I49+I48)/2)),2)),0),0) -> 0 | S49: =ROUND(R49*Kriterien!$B$6,0) -> 0 | T49: V03-Punkt; Nur Außenansicht; keine Terrasse oder Museumseintritt verlangen.
A50: D2-Q03 | B50: REGULAER | C50: DAY_2 | D50: 1 | E50: place_day_2_arco_di_costantino | F50: Konstantinsbogen | G50: START / ERSTER HINWEIS | H50: D2_FORUM_COLOSSEO | I50: 41.889762 | J50: 12.490667 | K50: GRUEN | L50: GRUEN_AUSSENPUNKT | M50: Drei monumentale Durchgänge, vom öffentlichen Bereich beim Kolosseum sichtbar. | N50: Wie viele Durchgänge besitzt der Konstantinsbogen? | O50: Drei | P50: https://en.wikipedia.org/wiki/Arch_of_Constantine | Q50: https://www.google.com/maps/search/?api=1&query=41.8897623,12.4906668 | R50: =IF(A50=A49,ROUND(SQRT(POWER((I50-I49)*111000,2)+POWER((J50-J49)*111000*COS(RADIANS((I50+I49)/2)),2)),0),0) -> 0 | S50: =ROUND(R50*Kriterien!$B$6,0) -> 0 | T50: V03-Punkt; VISUAL_EVIDENCE_NOT_YET_VERIFIED|CROWDING_RISK | U50: Gladiator des Ludus
A51: D2-Q03 | B51: REGULAER | C51: DAY_2 | D51: 2 | E51: place_day_2_colosseo | F51: Kolosseum | G51: ZWISCHENSTATION | H51: D2_FORUM_COLOSSEO | I51: 41.88989 | J51: 12.49337 | K51: GRUEN | L51: GRUEN_AUSSENPUNKT | M51: Drei große Reihen offener Arkaden an der hohen erhaltenen Außenwand. | N51: Wie viele übereinanderliegende Reihen offener Arkaden sind an der hohen Außenwand sichtbar? | O51: Drei | P51: https://it.wikipedia.org/wiki/Colosseo | Q51: https://www.google.com/maps/search/?api=1&query=41.88989,12.49337 | R51: =IF(A51=A50,ROUND(SQRT(POWER((I51-I50)*111000,2)+POWER((J51-J50)*111000*COS(RADIANS((I51+I50)/2)),2)),0),0) -> 224 | S51: =ROUND(R51*Kriterien!$B$6,0) -> 280 | T51: Moved from the monument centroid to Piazza del Colosseo for the exterior photoquest. No ticket, queue or archaeological-area entry may be required.; Außenkoordinate verwenden; weder Eintritt noch Sicherheitskontrolle dürfen erforderlich sein. | U51: Gladiator des Ludus
A52: D2-Q03 | B52: REGULAER | C52: DAY_2 | D52: 3 | E52: place_day_2_ludus_magnus | F52: Ludus Magnus | G52: ABSCHLUSS | H52: D2_FORUM_COLOSSEO | I52: 41.890113 | J52: 12.494955 | K52: GRUEN | L52: GRUEN_AUSSENPUNKT | M52: Halb freigelegte ovale Arena unter dem heutigen Straßenniveau. | N52: Welche Grundform hat die sichtbare Trainingsarena? | O52: Oval | P52: https://de.wikipedia.org/wiki/Ludus_Magnus | Q52: https://www.google.com/maps/search/?api=1&query=41.8901133,12.494955 | R52: =IF(A52=A51,ROUND(SQRT(POWER((I52-I51)*111000,2)+POWER((J52-J51)*111000*COS(RADIANS((I52+I51)/2)),2)),0),0) -> 133 | S52: =ROUND(R52*Kriterien!$B$6,0) -> 166 | T52: V03-Punkt; VISUAL_EVIDENCE_NOT_YET_VERIFIED|EXTERIOR_VANTAGE_POINT_REQUIRED|PAID_INTERIOR_OR_SITE_RISK_USE_EXTERIOR_ONLY|CROWDING_RISK | U52: Gladiator des Ludus
A53: D2-Q04 | B53: REGULAER | C53: DAY_2 | D53: 1 | E53: place_day_2_bocca_della_verita | F53: Mund der Wahrheit | G53: START / ERSTER HINWEIS | H53: D2_AVENTINO_FORUM_BOARIUM | I53: 41.888257 | J53: 12.481544 | K53: GELB | L53: GELB_WARTESCHLANGE | M53: Großes rundes Steingesicht im äußeren Portikus von Santa Maria in Cosmedin. | N53: Welcher Gesichtsteil bildet die große zentrale Öffnung? | O53: Der Mund | P53: https://it.wikipedia.org/wiki/Bocca_della_Verit%C3%A0 | Q53: https://www.google.com/maps/search/?api=1&query=41.8882567,12.4815441 | R53: =IF(A53=A52,ROUND(SQRT(POWER((I53-I52)*111000,2)+POWER((J53-J52)*111000*COS(RADIANS((I53+I52)/2)),2)),0),0) -> 0 | S53: =ROUND(R53*Kriterien!$B$6,0) -> 0 | T53: V03-Punkt; Nicht verlangen, die Hand hineinzulegen oder die Warteschlange zu betreten; Sicht vom öffentlichen Bereich prüfen. | U53: Custode di Giano
A54: D2-Q04 | B54: REGULAER | C54: DAY_2 | D54: 2 | E54: place_day_2_tempio_di_ercole_vincitore | F54: Tempel des Hercules Victor | G54: ZWISCHENSTATION | H54: D2_AVENTINO_FORUM_BOARIUM | I54: 41.888741 | J54: 12.480768 | K54: GRUEN | L54: GRUEN_AUSSENPUNKT | M54: Klar erkennbare runde Cella mit umlaufendem Säulenkranz. | N54: Welche Grundform hat der Tempel? | O54: Rund | P54: https://it.wikipedia.org/wiki/Tempio_di_Ercole_Vincitore | Q54: https://www.google.com/maps/search/?api=1&query=41.8887407,12.4807681 | R54: =IF(A54=A53,ROUND(SQRT(POWER((I54-I53)*111000,2)+POWER((J54-J53)*111000*COS(RADIANS((I54+I53)/2)),2)),0),0) -> 84 | S54: =ROUND(R54*Kriterien!$B$6,0) -> 105 | T54: V03-Punkt; VISUAL_EVIDENCE_NOT_YET_VERIFIED|EXTERIOR_VANTAGE_POINT_REQUIRED|PAID_INTERIOR_OR_SITE_RISK_USE_EXTERIOR_ONLY|CROWDING_RISK | U54: Custode di Giano
A55: D2-Q04 | B55: REGULAER | C55: DAY_2 | D55: 3 | E55: place_day_2_arco_degli_argentari | F55: Arco degli Argentari | G55: ZWISCHENSTATION | H55: D2_AVENTINO_FORUM_BOARIUM | I55: 41.889491 | J55: 12.483003 | K55: GRUEN | L55: GRUEN_KONZEPTREIF | M55: Gerader oberer Abschluss über engem Durchgang; reiche Reliefs an den Pfeilern. | N55: Wie ist der obere Abschluss des Durchgangs geformt? | O55: Gerade, als Architrav | P55: https://en.wikipedia.org/wiki/Arcus_Argentariorum | Q55: https://www.google.com/maps/search/?api=1&query=41.8894907,12.4830029 | R55: =IF(A55=A54,ROUND(SQRT(POWER((I55-I54)*111000,2)+POWER((J55-J54)*111000*COS(RADIANS((I55+I54)/2)),2)),0),0) -> 203 | S55: =ROUND(R55*Kriterien!$B$6,0) -> 254 | T55: V03-Punkt; VISUAL_EVIDENCE_NOT_YET_VERIFIED | U55: Custode di Giano
A56: D2-Q04 | B56: REGULAER | C56: DAY_2 | D56: 4 | E56: place_day_2_arco_di_giano | F56: Janusbogen | G56: ABSCHLUSS | H56: D2_AVENTINO_FORUM_BOARIUM | I56: 41.889353 | J56: 12.482768 | K56: GRUEN | L56: GRUEN_KONZEPTREIF | M56: Vier weithin sichtbare Bogenöffnungen auf vier Seiten. | N56: Nach wie vielen Seiten öffnet sich das Monument mit großen Durchgängen? | O56: Vier | P56: https://it.wikipedia.org/wiki/Arco_di_Giano | Q56: https://www.google.com/maps/search/?api=1&query=41.889353,12.4827682 | R56: =IF(A56=A55,ROUND(SQRT(POWER((I56-I55)*111000,2)+POWER((J56-J55)*111000*COS(RADIANS((I56+I55)/2)),2)),0),0) -> 25 | S56: =ROUND(R56*Kriterien!$B$6,0) -> 31 | T56: V03-Punkt; VISUAL_EVIDENCE_NOT_YET_VERIFIED|CROWDING_RISK | U56: Custode di Giano
A57: D2-Q05 | B57: REGULAER | C57: DAY_2 | D57: 1 | E57: place_day_2_fontana_dei_tritoni | F57: Tritonenbrunnen | G57: START / ERSTER HINWEIS | H57: D2_AVENTINO_FORUM_BOARIUM | I57: 41.888524 | J57: 12.481225 | K57: GRUEN | L57: GRUEN_KONZEPTREIF | M57: Zwei große Tritonen als Träger einer Muschelschale. | N57: Wie viele Tritonen tragen die obere Schale? | O57: Zwei | P57: https://it.wikipedia.org/wiki/Fontana_dei_Tritoni | Q57: https://www.google.com/maps/search/?api=1&query=41.8885236,12.4812253 | R57: =IF(A57=A56,ROUND(SQRT(POWER((I57-I56)*111000,2)+POWER((J57-J56)*111000*COS(RADIANS((I57+I56)/2)),2)),0),0) -> 0 | S57: =ROUND(R57*Kriterien!$B$6,0) -> 0 | T57: V03-Punkt; VISUAL_EVIDENCE_NOT_YET_VERIFIED|CROWDING_RISK | U57: Mascherone dell’Aventino
A58: D2-Q05 | B58: REGULAER | C58: DAY_2 | D58: 2 | E58: place_day_2_belvedere_romolo_e_remo | F58: Belvedere Romolo E Remo | G58: ZWISCHENSTATION | H58: D2_AVENTINO_FORUM_BOARIUM | I58: 41.885697 | J58: 12.484964 | K58: GRUEN | L58: GRUEN_AUSSICHTSPUNKT | M58: Freier Panoramablick über die langgestreckte Circus-Senke zum Palatin. | N58: Welcher Hügel liegt auf der gegenüberliegenden Seite des Circus Maximus? | O58: Der Palatin | P58: https://www.rerumromanarum.com/2024/04/belvedere-romolo-e-remo.html | Q58: https://www.google.com/maps/search/?api=1&query=41.8856975,12.484964 | R58: =IF(A58=A57,ROUND(SQRT(POWER((I58-I57)*111000,2)+POWER((J58-J57)*111000*COS(RADIANS((I58+I57)/2)),2)),0),0) -> 440 | S58: =ROUND(R58*Kriterien!$B$6,0) -> 550 | T58: V03-Punkt; VISUAL_EVIDENCE_NOT_YET_VERIFIED | U58: Mascherone dell’Aventino
A59: D2-Q05 | B59: REGULAER | C59: DAY_2 | D59: 3 | E59: place_day_2_fontana_del_mascherone_di_santa_sabina | F59: Maskenbrunnen bei Santa Sabina | G59: ABSCHLUSS | H59: D2_AVENTINO_FORUM_BOARIUM | I59: 41.88441 | J59: 12.480147 | K59: GRUEN | L59: GRUEN_KONZEPTREIF | M59: Großes steinernes Maskengesicht mit Wasserauslass im Mund. | N59: Aus welchem Gesichtsteil tritt das Wasser? | O59: Aus dem Mund | P59: https://turismoroma.it/it/luoghi/fontana-piazza-pietro-d%E2%80%99illiria | Q59: https://www.google.com/maps/search/?api=1&query=41.88441,12.480147 | R59: =IF(A59=A58,ROUND(SQRT(POWER((I59-I58)*111000,2)+POWER((J59-J58)*111000*COS(RADIANS((I59+I58)/2)),2)),0),0) -> 423 | S59: =ROUND(R59*Kriterien!$B$6,0) -> 529 | T59: V03-Punkt; VISUAL_EVIDENCE_NOT_YET_VERIFIED|CROWDING_RISK | U59: Mascherone dell’Aventino
A60: D2-Q06 | B60: REGULAER | C60: DAY_2 | D60: 1 | E60: place_day_2_fontana_della_navicella | F60: Fontana della Navicella | G60: START / ERSTER HINWEIS | H60: D2_FORUM_COLOSSEO | I60: 41.884759 | J60: 12.495864 | K60: GRUEN | L60: GRUEN_KONZEPTREIF | M60: Großes steinernes Schiff als zentrales Brunnenobjekt. | N60: Welche Objektform besitzt die zentrale Skulptur? | O60: Ein Schiff | P60: https://it.wikipedia.org/wiki/Fontana_della_Navicella | Q60: https://www.google.com/maps/search/?api=1&query=41.8847586,12.4958638 | R60: =IF(A60=A59,ROUND(SQRT(POWER((I60-I59)*111000,2)+POWER((J60-J59)*111000*COS(RADIANS((I60+I59)/2)),2)),0),0) -> 0 | S60: =ROUND(R60*Kriterien!$B$6,0) -> 0 | T60: V03-Punkt; VISUAL_EVIDENCE_NOT_YET_VERIFIED
A61: D2-Q07 | B61: REGULAER | C61: DAY_2 | D61: 1 | E61: place_day_2_basilica_di_san_giovanni_in_laterano | F61: Lateranbasilika | G61: START / ERSTER HINWEIS | H61: D2_CELIO_SAN_GIOVANNI | I61: 41.885762 | J61: 12.505586 | K61: GRUEN | L61: GRUEN_AUSSENPUNKT | M61: Sehr große Statuengruppe auf der Dachlinie mit Christus in der Mitte. | N61: Welche Figur steht im Zentrum der Statuengruppe auf der Hauptfassade? | O61: Christus | P61: https://it.wikipedia.org/wiki/Basilica_di_San_Giovanni_in_Laterano | Q61: https://www.google.com/maps/search/?api=1&query=41.8857617,12.5055858 | R61: =IF(A61=A60,ROUND(SQRT(POWER((I61-I60)*111000,2)+POWER((J61-J60)*111000*COS(RADIANS((I61+I60)/2)),2)),0),0) -> 0 | S61: =ROUND(R61*Kriterien!$B$6,0) -> 0 | T61: V03-Punkt; Nur die Piazza und Außenfassade verwenden; kein Kirchenbesuch.
A62: D2-Q07 | B62: REGULAER | C62: DAY_2 | D62: 2 | E62: place_day_2_obelisco_lateranense | F62: Lateranischer Obelisk | G62: ZWISCHENSTATION | H62: D2_CELIO_SAN_GIOVANNI | I62: 41.886844 | J62: 12.504798 | K62: GRUEN | L62: GRUEN_KONZEPTREIF | M62: Sehr hoher Schaft mit deutlich sichtbaren Hieroglyphen. | N62: Welche Art von Schriftzeichen ist auf dem Obelisken zu sehen? | O62: Ägyptische Hieroglyphen | P62: https://it.wikipedia.org/wiki/Obelisco_Lateranense | Q62: https://www.google.com/maps/search/?api=1&query=41.886844,12.5047983 | R62: =IF(A62=A61,ROUND(SQRT(POWER((I62-I61)*111000,2)+POWER((J62-J61)*111000*COS(RADIANS((I62+I61)/2)),2)),0),0) -> 137 | S62: =ROUND(R62*Kriterien!$B$6,0) -> 171 | T62: V03-Punkt; VISUAL_EVIDENCE_NOT_YET_VERIFIED
A63: D2-Q07 | B63: REGULAER | C63: DAY_2 | D63: 3 | E63: place_day_2_porta_san_giovanni | F63: Porta San Giovanni | G63: ABSCHLUSS | H63: D2_CELIO_SAN_GIOVANNI | I63: 41.885905 | J63: 12.509334 | K63: GRUEN | L63: GRUEN_VERKEHRSABSTAND | M63: Drei große Öffnungen nebeneinander. | N63: Wie viele große Durchgänge besitzt die Porta San Giovanni? | O63: Drei | P63: https://en.wikipedia.org/wiki/Porta_San_Giovanni_(Rome) | Q63: https://www.google.com/maps/search/?api=1&query=41.8859055,12.5093343 | R63: =IF(A63=A62,ROUND(SQRT(POWER((I63-I62)*111000,2)+POWER((J63-J62)*111000*COS(RADIANS((I63+I62)/2)),2)),0),0) -> 389 | S63: =ROUND(R63*Kriterien!$B$6,0) -> 486 | T63: V03-Punkt; Blickpunkt auf sicherem Gehweg; keine Straßenquerung für die Antwort verlangen.
A64: D2-Q08 | B64: REGULAER | C64: DAY_2 | D64: 1 | E64: place_day_2_porta_latina | F64: Porta Latina | G64: START / ERSTER HINWEIS | H64: D2_CELIO_SAN_GIOVANNI | I64: 41.876519 | J64: 12.502488 | K64: GRUEN | L64: GRUEN_KONZEPTREIF | M64: Ein Torbogen zwischen zwei deutlich runden Türmen. | N64: Wie viele runde Türme flankieren den Durchgang? | O64: Zwei | P64: https://en.wikipedia.org/wiki/Porta_Latina | Q64: https://www.google.com/maps/search/?api=1&query=41.8765186,12.5024875 | R64: =IF(A64=A63,ROUND(SQRT(POWER((I64-I63)*111000,2)+POWER((J64-J63)*111000*COS(RADIANS((I64+I63)/2)),2)),0),0) -> 0 | S64: =ROUND(R64*Kriterien!$B$6,0) -> 0 | T64: V03-Punkt; VISUAL_EVIDENCE_NOT_YET_VERIFIED | U64: Scorpione delle Mura
A65: D2-Q08 | B65: REGULAER | C65: DAY_2 | D65: 2 | E65: place_day_2_porta_metronia | F65: Porta Metronia | G65: ABSCHLUSS | H65: D2_CELIO_SAN_GIOVANNI | I65: 41.882323 | J65: 12.498639 | K65: GELB | L65: GELB_VERKEHRSUMFELD | M65: Vermauerter antiker Bogen im massiven Ziegelmauerwerk. | N65: Ist der historische Torbogen offen oder zugemauert? | O65: Zugemauert | P65: https://en.wikipedia.org/wiki/Porta_Metronia | Q65: https://www.google.com/maps/search/?api=1&query=41.8823233,12.4986395 | R65: =IF(A65=A64,ROUND(SQRT(POWER((I65-I64)*111000,2)+POWER((J65-J64)*111000*COS(RADIANS((I65+I64)/2)),2)),0),0) -> 719 | S65: =ROUND(R65*Kriterien!$B$6,0) -> 899 | T65: V03-Punkt; Frage muss den antiken Bogen eindeutig von modernen Durchbrüchen abgrenzen. | U65: Scorpione delle Mura
A66: D2-Q09 | B66: REGULAER | C66: DAY_2 | D66: 1 | E66: place_day_2_basilica_di_santa_maria_maggiore | F66: Basilika Groß Sankt Marien | G66: START / ERSTER HINWEIS | H66: D2_SANTA_MARIA_MAGGIORE | I66: 41.897129 | J66: 12.499146 | K66: GELB | L66: GELB_BOSS_MENSCHENMENGE | M66: Monumentale Fassade mit zentraler oberer Loggia und Marienbezug; großer öffentlicher Platz davor. | N66: Wie viele große Öffnungen besitzt die zentrale obere Loggia der Hauptfassade? | O66: Drei | P66: https://www.turismoroma.it/en/places/piazza-di-santa-maria-maggiore | Q66: https://www.google.com/maps/search/?api=1&query=41.89712887126836,12.499145861948264 | R66: =IF(A66=A65,ROUND(SQRT(POWER((I66-I65)*111000,2)+POWER((J66-J65)*111000*COS(RADIANS((I66+I65)/2)),2)),0),0) -> 0 | S66: =ROUND(R66*Kriterien!$B$6,0) -> 0 | T66: World-boss staging point placed on Piazza di Santa Maria Maggiore, outside the basilica. No interior access may be required.; Primär Boss-Staging auf dem öffentlichen Platz. Die Loggiazahl muss auf aktuellem Frontalbild nochmals bestätigt werden. | U66: Vapore delle Terme
A67: D2-Q09 | B67: REGULAER | C67: DAY_2 | D67: 2 | E67: place_day_2_obelisco_esquilino | F67: Obelisco Esquilino | G67: ZWISCHENSTATION | H67: D2_SANTA_MARIA_MAGGIORE | I67: 41.898177 | J67: 12.497503 | K67: GRUEN | L67: GRUEN_KONZEPTREIF | M67: Schlichter Obelisk ohne Hieroglyphen, oben mit Kreuz. | N67: Welches Symbol krönt die Spitze des Obelisken? | O67: Ein Kreuz | P67: https://it.wikipedia.org/wiki/Obelisco_Esquilino | Q67: https://www.google.com/maps/search/?api=1&query=41.8981766,12.4975028 | R67: =IF(A67=A66,ROUND(SQRT(POWER((I67-I66)*111000,2)+POWER((J67-J66)*111000*COS(RADIANS((I67+I66)/2)),2)),0),0) -> 179 | S67: =ROUND(R67*Kriterien!$B$6,0) -> 224 | T67: V03-Punkt; VISUAL_EVIDENCE_NOT_YET_VERIFIED | U67: Vapore delle Terme
A68: D2-Q09 | B68: REGULAER | C68: DAY_2 | D68: 3 | E68: place_day_2_thermae_traianae | F68: Thermae Traianae | G68: ABSCHLUSS | H68: D2_MONTI_ESQUILINO | I68: 41.892398 | J68: 12.497297 | K68: GRUEN | L68: GRUEN_PARKZUGANG | M68: Sehr hohe antike Ziegelmauerreste im öffentlichen Park. | N68: Welches Baumaterial dominiert die sichtbaren Thermenruinen? | O68: Ziegel | P68: https://it.wikipedia.org/wiki/Terme_di_Traiano | Q68: https://www.google.com/maps/search/?api=1&query=41.8923984,12.4972974 | R68: =IF(A68=A67,ROUND(SQRT(POWER((I68-I67)*111000,2)+POWER((J68-J67)*111000*COS(RADIANS((I68+I67)/2)),2)),0),0) -> 642 | S68: =ROUND(R68*Kriterien!$B$6,0) -> 803 | T68: V03-Punkt; VISUAL_EVIDENCE_NOT_YET_VERIFIED|EXTERIOR_VANTAGE_POINT_REQUIRED|PAID_INTERIOR_OR_SITE_RISK_USE_EXTERIOR_ONLY | U68: Vapore delle Terme
A69: D2-Q10 | B69: REGULAER | C69: DAY_2 | D69: 1 | E69: place_day_2_porta_maggiore_aqua_claudia | F69: Porta Maggiore und Aqua Claudia | G69: START / ERSTER HINWEIS | H69: D2_SANTA_MARIA_MAGGIORE | I69: 41.89118 | J69: 12.51572 | K69: GRUEN | L69: GRUEN_VERKEHRSABSTAND | M69: Zwei große Durchgänge, darüber mehrere gemauerte Aquäduktkanäle und monumentale Inschriften. | N69: Wie viele große Durchgänge besitzt der antike Doppelbogen? | O69: Zwei | P69: https://www.sovraintendenzaroma.it/i_luoghi/roma_antica/monumenti/porta_maggiore | Q69: https://www.google.com/maps/search/?api=1&query=41.89118,12.51572 | R69: =IF(A69=A68,ROUND(SQRT(POWER((I69-I68)*111000,2)+POWER((J69-J68)*111000*COS(RADIANS((I69+I68)/2)),2)),0),0) -> 0 | S69: =ROUND(R69*Kriterien!$B$6,0) -> 0 | T69: V03-Punkt; Sicheren Gehwegpunkt festlegen; keine Überquerung des Verkehrsknotens verlangen. | U69: Idra dell’Aqua Claudia
A70: M-D1-01 | B70: MEDIA_LOCAL | C70: DAY_1 | D70: 1 | E70: place_day_1_piazza_san_pietro | F70: Petersplatz | G70: START / ERSTER HINWEIS | H70: D1_VATICANO_PRATI_BORGO | I70: 41.902229 | J70: 12.457358 | K70: GELB | L70: GELB_MENSCHENMENGE | M70: Runde Marmor-Brennpunktmarkierung im Pflaster zwischen Obelisk und Kolonnade; danach Blick auf die großen Säulen. | N70: Stellt euch auf eine der runden Marmorplatten auf der Querachse des Obelisken und blickt zur Kolonnade. Wie viele Säulenreihen scheinen übrig zu bleiben? | O70: Eine | P70: https://www.turismoroma.it/it/luoghi/piazza-san-pietro | Q70: https://www.google.com/maps/search/?api=1&query=41.9022286,12.4573576 | R70: =IF(A70=A69,ROUND(SQRT(POWER((I70-I69)*111000,2)+POWER((J70-J69)*111000*COS(RADIANS((I70+I69)/2)),2)),0),0) -> 0 | S70: =ROUND(R70*Kriterien!$B$6,0) -> 0 | T70: V03-Punkt; Die Bodenmarkierung muss vor Veröffentlichung auf einem aktuellen Bild eindeutig lokalisiert werden.
A71: M-D1-02 | B71: MEDIA_LOCAL | C71: DAY_1 | D71: 1 | E71: place_day_1_ponte_sant_angelo | F71: Engelsbrücke | G71: START / ERSTER HINWEIS | H71: D1_VATICANO_PRATI_BORGO | I71: 41.901893 | J71: 12.466427 | K71: GRUEN | L71: GRUEN_KONZEPTREIF | M71: Zehn große Engelsfiguren auf beiden Balustraden; Petrus und Paulus stehen getrennt an den Brückenköpfen. | N71: Wie viele Engel auf der Brücke tragen Symbole der Passion Christi? Zählt Petrus und Paulus an den Brückenköpfen nicht mit. | O71: 10 | P71: https://www.turismoroma.it/en/places/terrace-castel-santangelo | Q71: https://www.google.com/maps/search/?api=1&query=41.9018932,12.4664274 | R71: =IF(A71=A70,ROUND(SQRT(POWER((I71-I70)*111000,2)+POWER((J71-J70)*111000*COS(RADIANS((I71+I70)/2)),2)),0),0) -> 0 | S71: =ROUND(R71*Kriterien!$B$6,0) -> 0 | T71: V03-Punkt; VISUAL_EVIDENCE_NOT_YET_VERIFIED|CROWDING_RISK
A72: M-D1-03 | B72: MEDIA_LOCAL | C72: DAY_1 | D72: 1 | E72: place_day_1_piazza_navona | F72: Piazza Navona | G72: START / ERSTER HINWEIS | H72: D1_NAVONA_PANTHEON | I72: 41.898926 | J72: 12.473099 | K72: GRUEN | L72: GRUEN_MENSCHENMENGE | M72: Drei weit auseinanderliegende Großbrunnen entlang der Platzachse. | N72: Wie viele große Brunnen liegen entlang der Längsachse der Piazza Navona? | O72: Drei | P72: https://it.wikipedia.org/wiki/Piazza_Navona | Q72: https://www.google.com/maps/search/?api=1&query=41.8989256,12.4730991 | R72: =IF(A72=A71,ROUND(SQRT(POWER((I72-I71)*111000,2)+POWER((J72-J71)*111000*COS(RADIANS((I72+I71)/2)),2)),0),0) -> 0 | S72: =ROUND(R72*Kriterien!$B$6,0) -> 0 | T72: V03-Punkt; Für die Medienquest sind alle drei Brunnen als separate Fotostationen zu markieren.
A73: M-D1-03 | B73: MEDIA_LOCAL | C73: DAY_1 | D73: 2 | E73: place_day_1_fontana_del_nettuno | F73: Neptunsbrunnen | G73: ZWISCHENSTATION | H73: D1_NAVONA_PANTHEON | I73: 41.899798 | J73: 12.473021 | K73: GRUEN | L73: GRUEN_KONZEPTREIF | M73: Große zentrale Neptunfigur im Ringkampf mit einem vielarmigen Meerestier. | N73: Mit welchem Meerestier ringt Neptun in der zentralen Skulptur? | O73: Mit einem Oktopus | P73: https://it.wikipedia.org/wiki/Fontana_del_Nettuno_(Roma) | Q73: https://www.google.com/maps/search/?api=1&query=41.8997976,12.4730207 | R73: =IF(A73=A72,ROUND(SQRT(POWER((I73-I72)*111000,2)+POWER((J73-J72)*111000*COS(RADIANS((I73+I72)/2)),2)),0),0) -> 97 | S73: =ROUND(R73*Kriterien!$B$6,0) -> 121 | T73: V03-Punkt; VISUAL_EVIDENCE_NOT_YET_VERIFIED|CROWDING_RISK
A74: M-D1-03 | B74: MEDIA_LOCAL | C74: DAY_1 | D74: 3 | E74: place_day_1_fontana_del_moro | F74: Mohrenbrunnen | G74: ABSCHLUSS | H74: D1_NAVONA_PANTHEON | I74: 41.898111 | J74: 12.473153 | K74: GRUEN | L74: GRUEN_KONZEPTREIF | M74: Zentrale männliche Figur mit Delfin; vier Tritonen im unteren Becken. | N74: Welches Tier hält die zentrale Figur des Mohrenbrunnens fest? | O74: Einen Delfin | P74: https://it.wikipedia.org/wiki/Fontana_del_Moro | Q74: https://www.google.com/maps/search/?api=1&query=41.8981115,12.4731529 | R74: =IF(A74=A73,ROUND(SQRT(POWER((I74-I73)*111000,2)+POWER((J74-J73)*111000*COS(RADIANS((I74+I73)/2)),2)),0),0) -> 187 | S74: =ROUND(R74*Kriterien!$B$6,0) -> 234 | T74: V03-Punkt; VISUAL_EVIDENCE_NOT_YET_VERIFIED|CROWDING_RISK
A75: M-LT-01 | B75: MEDIA_LANGZEIT | C75: BOTH_DAYS | D75: 1 | E75: place_day_1_teatro_di_marcello | F75: Marcellustheater | G75: START / ERSTER HINWEIS | H75: D1_CAMPO_REGOLA_GHETTO | I75: 41.892202 | J75: 12.479938 | K75: GRUEN | L75: GRUEN_AUSSENPUNKT | M75: Zwei übereinanderliegende antike Arkadenebenen unter einem späteren Wohnpalast. | N75: Wie viele übereinanderliegende antike Arkadengeschosse sind von außen klar sichtbar? | O75: Zwei | P75: https://www.turismoroma.it/it/luoghi/teatro-di-marcello | Q75: https://www.google.com/maps/search/?api=1&query=41.892202,12.479938 | R75: =IF(A75=A74,ROUND(SQRT(POWER((I75-I74)*111000,2)+POWER((J75-J74)*111000*COS(RADIANS((I75+I74)/2)),2)),0),0) -> 0 | S75: =ROUND(R75*Kriterien!$B$6,0) -> 0 | T75: V03-Punkt; Offizieller Fußweg erlaubt Außenbesichtigung; Medienquest-Pickup ohne Zugang zu Innenräumen. | U75: Maschera del Dramma
A76: M-D2-01 | B76: MEDIA_LOCAL | C76: DAY_2 | D76: 1 | E76: place_day_2_circo_massimo | F76: Circus Maximus | G76: START / ERSTER HINWEIS | H76: D2_AVENTINO_FORUM_BOARIUM | I76: 41.886651 | J76: 12.484509 | K76: GRUEN | L76: GRUEN_MEDIENQUEST | M76: Sehr große langgestreckte Senke der Rennbahn zwischen zwei Hügeln. | N76: Zwischen welchen zwei Hügeln liegt der Circus Maximus? | O76: Palatin und Aventin | P76: https://www.turismoroma.it/en/places/circus-maximus | Q76: https://www.google.com/maps/search/?api=1&query=41.886650681433466,12.484508661426391 | R76: =IF(A76=A75,ROUND(SQRT(POWER((I76-I75)*111000,2)+POWER((J76-J75)*111000*COS(RADIANS((I76+I75)/2)),2)),0),0) -> 0 | S76: =ROUND(R76*Kriterien!$B$6,0) -> 0 | T76: Official Turismo Roma coordinate; page states that the site is always open. The photoquest must remain in the freely accessible open area.; Fotoquest Streitwagenrennen: exakt fünf Bilder; Pickup und Upload am selben Außenpunkt im 15-m-Radius. | U76: Rasender Kutschergeist
A77: M-D2-02 | B77: MEDIA_LOCAL | C77: DAY_2 | D77: 1 | E77: place_day_2_colosseo | F77: Kolosseum | G77: START / ERSTER HINWEIS | H77: D2_FORUM_COLOSSEO | I77: 41.88989 | J77: 12.49337 | K77: GRUEN | L77: GRUEN_AUSSENPUNKT | M77: Drei große Reihen offener Arkaden an der hohen erhaltenen Außenwand. | N77: Wie viele übereinanderliegende Reihen offener Arkaden sind an der hohen Außenwand sichtbar? | O77: Drei | P77: https://it.wikipedia.org/wiki/Colosseo | Q77: https://www.google.com/maps/search/?api=1&query=41.88989,12.49337 | R77: =IF(A77=A76,ROUND(SQRT(POWER((I77-I76)*111000,2)+POWER((J77-J76)*111000*COS(RADIANS((I77+I76)/2)),2)),0),0) -> 0 | S77: =ROUND(R77*Kriterien!$B$6,0) -> 0 | T77: Moved from the monument centroid to Piazza del Colosseo for the exterior photoquest. No ticket, queue or archaeological-area entry may be required.; Außenkoordinate verwenden; weder Eintritt noch Sicherheitskontrolle dürfen erforderlich sein. | U77: Gladiator
A78: M-D2-03 | B78: MEDIA_LOCAL | C78: DAY_2 | D78: 1 | E78: place_day_2_mercati_di_traiano | F78: Trajansmärkte | G78: START / ERSTER HINWEIS | H78: D2_CAMPIDOGLIO_FORI_TRAIANEI | I78: 41.896251 | J78: 12.486098 | K78: GRUEN | L78: GRUEN_AUSSENPUNKT | M78: Mehrgeschossiger Ziegel-Halbkreis mit vielen Bogenöffnungen, vom öffentlichen Bereich Via IV Novembre sichtbar. | N78: Welche Form beschreibt die große Außenfassade am besten? | O78: Halbkreisförmig | P78: https://www.mercatiditraiano.it/en/museo/sede/mercati_di_traiano_storia | Q78: https://www.google.com/maps/search/?api=1&query=41.8962514,12.4860984 | R78: =IF(A78=A77,ROUND(SQRT(POWER((I78-I77)*111000,2)+POWER((J78-J77)*111000*COS(RADIANS((I78+I77)/2)),2)),0),0) -> 0 | S78: =ROUND(R78*Kriterien!$B$6,0) -> 0 | T78: Videoquest point uses the official Via Quattro Novembre 94 address outside the paid museum. Verify an unobstructed public pavement position before release.; Videoquest ausschließlich am öffentlichen Außenpunkt; Museumseintritt ist nicht Bestandteil. | U78: Spettro della Taberna
A79: H-D1-01 | B79: HIDDEN | C79: DAY_1 | D79: 1 | E79: place_day_1_fontana_delle_tartarughe | F79: Fontana delle Tartarughe | G79: START / ERSTER HINWEIS | H79: D1_TREVI_QUIRINALE | I79: 41.893782 | J79: 12.477456 | K79: GRUEN | L79: GRUEN_KONZEPTREIF | M79: Vier deutlich sichtbare Schildkröten am Rand des oberen Beckens. | N79: Wie viele Schildkröten klettern zum oberen Becken? | O79: Vier | P79: https://www.turismoroma.it/it/luoghi/fontana-delle-tartarughe | Q79: https://www.google.com/maps/search/?api=1&query=41.893782,12.477456 | R79: =IF(A79=A78,ROUND(SQRT(POWER((I79-I78)*111000,2)+POWER((J79-J78)*111000*COS(RADIANS((I79+I78)/2)),2)),0),0) -> 0 | S79: =ROUND(R79*Kriterien!$B$6,0) -> 0 | T79: Corrected an erroneous OSM-derived point to the official Turismo Roma coordinate in Piazza Mattei.; VISUAL_EVIDENCE_NOT_YET_VERIFIED | U79: Custode delle Tartarughe
A80: H-D1-02 | B80: HIDDEN | C80: DAY_1 | D80: 1 | E80: place_day_1_acquedotto_vergine | F80: Acquedotto Vergine | G80: START / ERSTER HINWEIS | H80: D1_TREVI_QUIRINALE | I80: 41.902611 | J80: 12.483711 | K80: GELB | L80: GELB_TEILWEISE_VERDECKT | M80: Drei teilweise im heutigen Bodenniveau versunkene Travertinarkaden hinter einer Absperrung. | N80: Wie viele kleinere antike Arkaden sind in der Via del Nazareno nebeneinander erhalten? | O80: Drei | P80: https://www.sovraintendenzaroma.it/i_luoghi/roma_antica/monumenti/acquedotto_vergine | Q80: https://www.google.com/maps/search/?api=1&query=41.9026109,12.4837108 | R80: =IF(A80=A79,ROUND(SQRT(POWER((I80-I79)*111000,2)+POWER((J80-J79)*111000*COS(RADIANS((I80+I79)/2)),2)),0),0) -> 0 | S80: =ROUND(R80*Kriterien!$B$6,0) -> 0 | T80: V03-Punkt; Die Arkaden sind teilweise eingetieft und durch Gitter verdeckt; nur nach aktuellem Sichttest als Pflichtfrage einsetzen. | U80: Ratto dell’Acqua Virgo
A81: H-D1-03 | B81: HIDDEN | C81: DAY_1 | D81: 1 | E81: place_day_1_fontana_dei_satirelli | F81: Fontana dei Satirelli | G81: START / ERSTER HINWEIS | H81: D1_TRASTEVERE_TIBER_ISLAND | I81: 41.884724 | J81: 12.463599 | K81: GELB | L81: GELB_PARKOEFFNUNG | M81: Figürliche Gruppe kleiner Satyrwesen auf einer Felsinszenierung. | N81: Welche mythologischen Wesen bilden die zentrale Figurengruppe? | O81: Satyrn | P81: https://www.comune.roma.it/web/it/attivita-progetto.page?contentId=PRG1072554 | Q81: https://www.google.com/maps/search/?api=1&query=41.8847241,12.4635989 | R81: =IF(A81=A80,ROUND(SQRT(POWER((I81-I80)*111000,2)+POWER((J81-J80)*111000*COS(RADIANS((I81+I80)/2)),2)),0),0) -> 0 | S81: =ROUND(R81*Kriterien!$B$6,0) -> 0 | T81: V03-Punkt; Nur nutzen, wenn Villa Sciarra zu den Spielzeiten sicher geöffnet ist; sonst als Hidden/Reserve. | U81: I Satirelli Gemelli
A82: H-D2-01 | B82: HIDDEN | C82: DAY_2 | D82: 1 | E82: place_day_2_piazza_vittorio_emanuele_secondo | F82: Piazza Vittorio Emanuele Secondo | G82: START / ERSTER HINWEIS | H82: D2_MONTI_ESQUILINO | I82: 41.894623 | J82: 12.504308 | K82: GELB | L82: GELB_PARKOEFFNUNG | M82: Porta Magica mit alchemistischen Inschriften und zwei massiven Wächterfiguren. | N82: Wie viele steinerne Wächterfiguren flankieren die Porta Magica? | O82: Zwei | P82: https://it.wikipedia.org/wiki/Piazza_Vittorio_Emanuele_II_(Roma) | Q82: https://www.google.com/maps/search/?api=1&query=41.8946228,12.5043081 | R82: =IF(A82=A81,ROUND(SQRT(POWER((I82-I81)*111000,2)+POWER((J82-J81)*111000*COS(RADIANS((I82+I81)/2)),2)),0),0) -> 0 | S82: =ROUND(R82*Kriterien!$B$6,0) -> 0 | T82: V03-Punkt; Nur innerhalb der sicheren Tagesöffnung des Gartens einplanen; bei Sperre gleichörtige Platzaufgabe bereitstellen. | U82: Alchemist der Porta Magica
A83: H-D2-02 | B83: HIDDEN | C83: DAY_2 | D83: 1 | E83: place_day_2_piazza_dante | F83: Piazza Dante | G83: START / ERSTER HINWEIS | H83: D2_MONTI_ESQUILINO | I83: 41.891977 | J83: 12.503991 | K83: GELB | L83: GELB_PARKOEFFNUNG | M83: Große Rose der Winde aus Ziegel und Travertin im Gartenpflaster. | N83: Welches Navigationssymbol bildet das Pflaster im Garten? | O83: Eine Windrose | P83: https://www.turismoroma.it/it/luoghi/giardino-di-piazza-dante | Q83: https://www.google.com/maps/search/?api=1&query=41.8919766,12.5039912 | R83: =IF(A83=A82,ROUND(SQRT(POWER((I83-I82)*111000,2)+POWER((J83-J82)*111000*COS(RADIANS((I83+I82)/2)),2)),0),0) -> 0 | S83: =ROUND(R83*Kriterien!$B$6,0) -> 0 | T83: V03-Punkt; Der Garten ist offiziell von Morgendämmerung bis Abenddämmerung geöffnet; für Tag 2 zeitlich voraussichtlich passend, aber Fallback vorsehen. | U83: Custode dell’Inferno
A84: B-D1-01 | B84: WORLD_BOSS | C84: DAY_1 | D84: 1 | E84: place_day_1_terrazza_del_gianicolo | F84: Terrazza del Gianicolo | G84: START / ERSTER HINWEIS | H84: D1_GIANICOLO | I84: 41.891477 | J84: 12.461388 | K84: GRUEN | L84: GRUEN_SONDERROLLE | M84: Weite, offene Aussichtsterrasse beim Garibaldi-Denkmal; geeignet als sichere Bossbühne, nicht als kleines Suchobjekt. | N84: Gehört der Gianicolo zu den klassischen sieben Hügeln des antiken Rom? | O84: Nein | P84: https://www.openstreetmap.org/node/1001130475 | Q84: https://www.google.com/maps/search/?api=1&query=41.8914773,12.4613885 | R84: =IF(A84=A83,ROUND(SQRT(POWER((I84-I83)*111000,2)+POWER((J84-J83)*111000*COS(RADIANS((I84+I83)/2)),2)),0),0) -> 0 | S84: =ROUND(R84*Kriterien!$B$6,0) -> 0 | T84: V03-Punkt; Primär Weltboss-Ort. Kampftrigger großzügig setzen und vom Straßenverkehr abwenden. | U84: Il Cannoniere del Gianicolo
A85: B-D2-01 | B85: WORLD_BOSS | C85: DAY_2 | D85: 1 | E85: place_day_2_basilica_di_santa_maria_maggiore | F85: Basilika Groß Sankt Marien | G85: START / ERSTER HINWEIS | H85: D2_SANTA_MARIA_MAGGIORE | I85: 41.897129 | J85: 12.499146 | K85: GELB | L85: GELB_BOSS_MENSCHENMENGE | M85: Monumentale Fassade mit zentraler oberer Loggia und Marienbezug; großer öffentlicher Platz davor. | N85: Wie viele große Öffnungen besitzt die zentrale obere Loggia der Hauptfassade? | O85: Drei | P85: https://www.turismoroma.it/en/places/piazza-di-santa-maria-maggiore | Q85: https://www.google.com/maps/search/?api=1&query=41.89712887126836,12.499145861948264 | R85: =IF(A85=A84,ROUND(SQRT(POWER((I85-I84)*111000,2)+POWER((J85-J84)*111000*COS(RADIANS((I85+I84)/2)),2)),0),0) -> 0 | S85: =ROUND(R85*Kriterien!$B$6,0) -> 0 | T85: World-boss staging point placed on Piazza di Santa Maria Maggiore, outside the basilica. No interior access may be required.; Primär Boss-Staging auf dem öffentlichen Platz. Die Loggiazahl muss auf aktuellem Frontalbild nochmals bestätigt werden. | U85: Custode della Neve

Sheet Sonderquests
A1: Via Romae – Sonderquests und Events v0.9
A2: Sieben Medienquests, fünf Hidden Quests und zwei World-Boss-Events mit Reward-Profilen aus GDD v0.16 Kapitel 28.
A4: Nr. | B4: Quest-ID | C4: Typ | D4: Tag | E4: Titel | F4: Orte | G4: Zeitrahmen | H4: Briefing / Hook | I4: Hauptmechanik | J4: Sekundärmechaniken | K4: Gegner / Boss | L4: Limitwirkung | M4: Pickup / Abgabe | N4: Status | O4: Hauptrisiko | P4: Empfehlung | Q4: Reward-Profil | R4: Basis-Ruhm / Denare | S4: Item-/Loot-Regel
A5: 1 | B5: M-D1-01 | C5: MEDIA_LOCAL | D5: DAY_1 | E5: Foto mit Schweizer Gardist | F5: Petersplatz | G5: 5–15 | H5: Teamfoto mit einem Schweizer Gardisten am Petersplatz. | I5: MEDIEN | J5: GPS|DIALOG | L5: SEPARAT | M5: Pickup und Upload am Petersplatz, 15-m-Radius. | N5: BESTAETIGT | O5: Gardist ist nicht garantiert verfügbar; respektvolle Distanz und Menschenmenge. | P5: Fallbackbriefing mit sichtbarer Garde im Hintergrund vorbereiten. | Q5: MEDIA_RANK_TABLE | R5: 50 / 25 | S5: LOOT_ROLL:MEDIA_EVENT_PROFILE
A6: 2 | B6: M-D1-02 | C6: MEDIA_LOCAL | D6: DAY_1 | E6: Wie ein Engel | F6: Engelsbrücke | G6: 5–15 | H6: Bewusst offene kreative Fotoaufgabe auf der Engelsbrücke. | I6: MEDIEN | J6: GPS|KREATIVITAET | L6: SEPARAT | M6: Pickup und Upload an der Engelsbrücke, 15-m-Radius. | N6: BESTAETIGT | O6: Hohe Besucherzahl und schmale Bewegungsflächen. | P6: Offenes Briefing beibehalten; keine exakte Pose verlangen. | Q6: MEDIA_RANK_TABLE | R6: 50 / 25 | S6: LOOT_ROLL:MEDIA_EVENT_PROFILE
A7: 3 | B7: M-D1-03 | C7: MEDIA_LOCAL | D7: DAY_1 | E7: Drei Brunnen, drei Figuren | F7: Piazza Navona → Neptunsbrunnen → Mohrenbrunnen | G7: 15–25 | H7: Je eine Figurenpose aus jedem der drei Brunnen der Piazza Navona nachstellen. | I7: MEDIEN | J7: GPS|BEOBACHTUNG|ZUORDNUNG | L7: SEPARAT | M7: Pickup und Upload im Zentrum der Piazza Navona, 15-m-Radius. | N7: BESTAETIGT | O7: Menschenmenge; nur große Figuren als Vorbild verwenden. | P7: Sehr gute Medienquest; klare Dreiteilung beibehalten. | Q7: MEDIA_RANK_TABLE | R7: 50 / 25 | S7: LOOT_ROLL:MEDIA_EVENT_PROFILE
A8: 4 | B8: M-LT-01 | C8: MEDIA_LANGZEIT | D8: BOTH_DAYS | E8: Roma in zwölf Bildern | F8: Marcellustheater | G8: BEIDE_TAGE | H8: Maximal zwölf Bilder erzählen eine erkennbare Kurzgeschichte mit sichtbaren Klassenrollen. | I8: MEDIEN | J8: DIALOG|ENTSCHEIDUNG|GPS | K8: Maschera del Dramma | L8: CHRONIKSLOT | M8: Pickup am Marcellustheater; Abgabe nach separater Langzeitregel. | N8: BESTAETIGT | O8: Bewertung benötigt klare Rubrik; darf reguläre Questslots nicht blockieren. | P8: Als einzige bestätigte Langzeitquest umsetzen. | Q8: MEDIA_RANK_TABLE | R8: 120 / 50 | S8: LOOT_ROLL:MEDIA_EVENT_PROFILE
A9: 5 | B9: M-D2-01 | C9: MEDIA_LOCAL | D9: DAY_2 | E9: Streitwagenrennen | F9: Circus Maximus | G9: 15–25 | H9: Ein Streitwagenrennen als zusammenhängender Akt in exakt fünf Bildern. | I9: MEDIEN | J9: GPS|ROLLENSPIEL|REIHENFOLGE | K9: Rasender Kutschergeist | L9: SEPARAT | M9: Pickup und Upload am Circus Maximus, 15-m-Radius. | N9: BESTAETIGT | O9: Große offene Fläche; sichere Laufrichtung im Briefing festlegen. | P9: Sehr starke Orts- und Medienpassung. | Q9: MEDIA_RANK_TABLE | R9: 50 / 25 | S9: LOOT_ROLL:MEDIA_EVENT_PROFILE
A10: 6 | B10: M-D2-02 | C10: MEDIA_LOCAL | D10: DAY_2 | E10: Gladiatorenkampf | F10: Kolosseum | G10: 5–15 | H10: Kurze inszenierte Bildserie eines Gladiatorenkampfs vor dem Kolosseum. | I10: MEDIEN | J10: ROLLENSPIEL|KAMPFINSZENIERUNG | K10: Gladiator | L10: SEPARAT | M10: Pickup und Upload am öffentlichen Kolosseum-Außenpunkt, 15-m-Radius. | N10: BESTAETIGT | O10: Sehr hohe Besucherzahl; keine reale Kampfbewegung in Engstellen. | P10: Posen statt dynamischer Aktionen verlangen. | Q10: MEDIA_RANK_TABLE | R10: 50 / 25 | S10: LOOT_ROLL:MEDIA_EVENT_PROFILE
A11: 7 | B11: M-D2-03 | C11: MEDIA_LOCAL | D11: DAY_2 | E11: Souvenirreview | F11: Trajansmärkte | G11: 15–25 | H11: 30–60 Sekunden Review eines Souvenirs bis maximal 5 EUR; Kauf kann anderswo erfolgen. | I11: MEDIEN | J11: KURZTEXT|ROLLENSPIEL | K11: Spettro della Taberna | L11: SEPARAT | M11: Pickup und Upload am öffentlichen Außenpunkt der Trajansmärkte, 15-m-Radius. | N11: BESTAETIGT | O11: Kauf darf nicht am Ort vorausgesetzt werden; Außenpunkt eindeutig festlegen. | P11: Sehr gute Verbindung von Alltagsleben, Handel und Performance. | Q11: MEDIA_RANK_TABLE | R11: 50 / 25 | S11: LOOT_ROLL:MEDIA_EVENT_PROFILE
A12: 8 | B12: H-D1-01 | C12: HIDDEN | D12: DAY_1 | E12: Die Schildkröten wachen | F12: Fontana delle Tartarughe | G12: 5–10 | H12: Eine zusätzliche Beobachtung an den vier Schildkröten löst einen kurzen Wächterkampf aus. | I12: BEOBACHTUNG_SUCHE | J12: KAMPF | K12: Custode delle Tartarughe | L12: ZAEHLT_NICHT | M12: Automatischer Näherungstrigger; kein eigener aktiver Slot. | N12: OPTIONAL | O12: Aktuelle Sicht der Schildkröten prüfen. | P12: Guter versteckter Zusatz zu D1-Q13. | Q12: HIDDEN_BASE_PLUS_LOOT | R12: 30 / 20 | S12: LOOT_ROLL:HIDDEN_PROFILE
A13: 9 | B13: H-D1-02 | C13: HIDDEN | D13: DAY_1 | E13: Ratte des Aquädukts | F13: Acquedotto Vergine | G13: 5–10 | H13: Wer die verdeckten Arkaden findet, entdeckt die Kanalratte der Aqua Virgo. | I13: BEOBACHTUNG_SUCHE | J13: KAMPF | K13: Ratto dell’Acqua Virgo | L13: ZAEHLT_NICHT | M13: Nähe und vorherige Beobachtung lösen den Auftrag aus. | N13: OPTIONAL | O13: Arkaden sind teilweise verdeckt. | P13: Nur aktivieren, wenn aktueller Sichtbeleg genügt. | Q13: HIDDEN_BASE_PLUS_LOOT | R13: 30 / 20 | S13: LOOT_ROLL:HIDDEN_PROFILE
A14: 10 | B14: H-D1-03 | C14: HIDDEN | D14: DAY_1 | E14: Die Satirelli | F14: Fontana dei Satirelli | G14: 5–10 | H14: Die beiden Satyrn öffnen einen kurzen Zuordnungs- oder Begegnungsauftrag. | I14: BEOBACHTUNG_SUCHE | J14: ZUORDNUNG|KAMPF | K14: I Satirelli Gemelli | L14: ZAEHLT_NICHT | M14: Näherungstrigger im Park; kein aktiver Slot. | N14: OPTIONAL | O14: Parköffnungszeiten. | P14: Nur tagsüber aktivieren; sonst automatisch deaktiviert. | Q14: HIDDEN_BASE_PLUS_LOOT | R14: 30 / 20 | S14: LOOT_ROLL:HIDDEN_PROFILE
A15: 11 | B15: H-D2-01 | C15: HIDDEN | D15: DAY_2 | E15: Wächter der Porta Magica | F15: Piazza Vittorio Emanuele Secondo | G15: 5–10 | H15: Zwei steinerne Wächter führen zu einer kurzen alchemistischen Zuordnung. | I15: BEOBACHTUNG_SUCHE | J15: ZUORDNUNG|KURZTEXT | K15: Alchemist der Porta Magica | L15: ZAEHLT_NICHT | M15: Näherungstrigger im Park; kein aktiver Slot. | N15: OPTIONAL | O15: Parkzugang und Sicht der Wächterfiguren. | P15: Starker Geheimtipp, wenn aktueller Sichtbeleg vorliegt. | Q15: HIDDEN_BASE_PLUS_LOOT | R15: 30 / 20 | S15: LOOT_ROLL:HIDDEN_PROFILE
A16: 12 | B16: H-D2-02 | C16: HIDDEN | D16: DAY_2 | E16: Dantes Windrose | F16: Piazza Dante | G16: 5–10 | H16: Die große Windrose öffnet eine kurze Richtungs- und Textaufgabe. | I16: BEOBACHTUNG_SUCHE | J16: KURZTEXT|RICHTUNG | K16: Custode dell’Inferno | L16: ZAEHLT_NICHT | M16: Näherungstrigger im Garten; kein aktiver Slot. | N16: OPTIONAL | O16: Parköffnungszeiten. | P16: Als Hidden Quest gut; nicht als Pflichtstation. | Q16: HIDDEN_BASE_PLUS_LOOT | R16: 30 / 20 | S16: LOOT_ROLL:HIDDEN_PROFILE
A17: 13 | B17: B-D1-01 | C17: WORLD_BOSS | D17: DAY_1 | E17: Il Cannoniere del Gianicolo | F17: Terrazza del Gianicolo | G17: EVENT | H17: Tag-1-Finale auf der öffentlichen Terrasse des Gianicolo. | I17: KAMPF | J17: DIALOG|TEAMKOORDINATION | K17: Il Cannoniere del Gianicolo | L17: ZAEHLT_NICHT | M17: Separater Eventtrigger in der ausgewiesenen sicheren Zone. | N17: EMPFOHLEN | O17: Menschenmenge und sichere Aufstellfläche aktuell prüfen. | P17: Starke thematische und räumliche Schlussposition für Tag 1. | Q17: WORLD_BOSS_CONTRIBUTION_RANK | R17: 0 / 0 | S17: LOOT_ROLL:WORLD_BOSS_RANKED
A18: 14 | B18: B-D2-01 | C18: WORLD_BOSS | D18: DAY_2 | E18: Custode della Neve | F18: Basilika Groß Sankt Marien | G18: EVENT | H18: Tag-2-Finale vor Santa Maria Maggiore; Schneemotiv ausdrücklich als Legende erzählen. | I18: KAMPF | J18: DIALOG|TEAMKOORDINATION | K18: Custode della Neve | L18: ZAEHLT_NICHT | M18: Separater Eventtrigger ausschließlich auf dem öffentlichen Außenplatz. | N18: BEDINGT | O18: Sehr hohe Besucherzahl; sichere Bossfläche muss remote aktuell geprüft werden. | P18: Inhaltlich stark, operativ riskanter als Gianicolo. | Q18: WORLD_BOSS_CONTRIBUTION_RANK | R18: 0 / 0 | S18: LOOT_ROLL:WORLD_BOSS_RANKED

Sheet Supportpunkte
A1: Via Romae – Supportpunkte
A2: Revive Points, Stores und Boss-Sicherheitszonen bleiben von den regulären Questzahlen getrennt.
L3: Store-ID | M3: Sichtbarkeit | N3: Interaktion | O3: Katalog
A4: Tag | B4: Kandidaten-ID | C4: Ort | D4: Supportrollen | E4: Reguläre Nutzungen | F4: Sondernutzungen | G4: Research-Ampel | H4: Funktion | I4: Hauptrisiko | J4: Google Maps | K4: Empfehlung
A5: DAY_1 | B5: place_day_1_castel_sant_angelo | C5: Engelsburg | D5: STORE_LOCATION_CANDIDATE|CLASS_HISTORY_QUEST_ANCHOR | E5: =COUNTIFS(Ortszuordnung!$E$5:$E$85,B5,Ortszuordnung!$B$5:$B$85,"REGULAER") -> 1 | F5: =COUNTIF(Ortszuordnung!$E$5:$E$85,B5)-E5 -> 0 | G5: GRUEN | H5: Store | I5: Nur der öffentliche Vorplatz darf als Trigger dienen; kein Eintritt in die Burg. | J5: https://www.google.com/maps/search/?api=1&query=41.90262,12.46686 | K5: ALS_SEPARATEN_SUPPORTPUNKT_BEHALTEN | L5: STORE-D1-01 | M5: 500 m | N5: 15 m | O5: Stores!A5:I5
A6: DAY_1 | B6: place_day_1_piazza_del_popolo | C6: Piazza del Popolo | D6: REVIVE_POINT_CANDIDATE | E6: =COUNTIFS(Ortszuordnung!$E$5:$E$85,B6,Ortszuordnung!$B$5:$B$85,"REGULAER") -> 1 | F6: =COUNTIF(Ortszuordnung!$E$5:$E$85,B6)-E6 -> 0 | G6: GRUEN | H6: Wiederbelebung / Sammelpunkt | I6: VISUAL_EVIDENCE_NOT_YET_VERIFIED|CROWDING_RISK | J6: https://www.google.com/maps/search/?api=1&query=41.9107491,12.4763454 | K6: ALS_SEPARATEN_SUPPORTPUNKT_BEHALTEN
A7: DAY_1 | B7: place_day_1_piazza_navona | C7: Piazza Navona | D7: MEDIA_QUEST_LOCATION|LOCAL_MEDIA_QUEST|REVIVE_POINT_CANDIDATE|STORE_LOCATION_CANDIDATE|CLASS_HISTORY_QUEST_ANCHOR | E7: =COUNTIFS(Ortszuordnung!$E$5:$E$85,B7,Ortszuordnung!$B$5:$B$85,"REGULAER") -> 1 | F7: =COUNTIF(Ortszuordnung!$E$5:$E$85,B7)-E7 -> 1 | G7: GRUEN | H7: Wiederbelebung / Sammelpunkt | I7: Für die Medienquest sind alle drei Brunnen als separate Fotostationen zu markieren. | J7: https://www.google.com/maps/search/?api=1&query=41.8989256,12.4730991 | K7: ALS_SEPARATEN_SUPPORTPUNKT_BEHALTEN | L7: STORE-D1-02 | M7: 500 m | N7: 15 m | O7: Stores!A6:I6
A8: DAY_1 | B8: place_day_1_campo_de_fiori | C8: Campo de' Fiori | D8: STORE_LOCATION_CANDIDATE | E8: =COUNTIFS(Ortszuordnung!$E$5:$E$85,B8,Ortszuordnung!$B$5:$B$85,"REGULAER") -> 1 | F8: =COUNTIF(Ortszuordnung!$E$5:$E$85,B8)-E8 -> 0 | G8: GRUEN | H8: Store | I8: Am Vormittag kann der Markt die Sockelsicht einschränken; Aufgabe auf die große Figur beschränken. | J8: https://www.google.com/maps/search/?api=1&query=41.8955725,12.4721223 | K8: ALS_SEPARATEN_SUPPORTPUNKT_BEHALTEN | L8: STORE-D1-03 | M8: 500 m | N8: 15 m | O8: Stores!A7:I7
A9: DAY_1 | B9: place_day_1_fontana_dell_acqua_paola | C9: Fontana Dell'Acqua Paola | D9: REVIVE_POINT_CANDIDATE | E9: =COUNTIFS(Ortszuordnung!$E$5:$E$85,B9,Ortszuordnung!$B$5:$B$85,"REGULAER") -> 1 | F9: =COUNTIF(Ortszuordnung!$E$5:$E$85,B9)-E9 -> 0 | G9: GRUEN | H9: Wiederbelebung / Sammelpunkt | I9: VISUAL_EVIDENCE_NOT_YET_VERIFIED|CROWDING_RISK | J9: https://www.google.com/maps/search/?api=1&query=41.8888192,12.4642423 | K9: ALS_SEPARATEN_SUPPORTPUNKT_BEHALTEN
A10: DAY_1 | B10: place_day_1_terrazza_del_gianicolo | C10: Terrazza del Gianicolo | D10: WORLD_BOSS_LOCATION|BOSS_STAGING_SAFE_ZONE | E10: =COUNTIFS(Ortszuordnung!$E$5:$E$85,B10,Ortszuordnung!$B$5:$B$85,"REGULAER") -> 0 | F10: =COUNTIF(Ortszuordnung!$E$5:$E$85,B10)-E10 -> 1 | G10: GRUEN | H10: Boss-Sicherheitszone | I10: Primär Weltboss-Ort. Kampftrigger großzügig setzen und vom Straßenverkehr abwenden. | J10: https://www.google.com/maps/search/?api=1&query=41.8914773,12.4613885 | K10: ALS_SEPARATEN_SUPPORTPUNKT_BEHALTEN
A11: DAY_1 | B11: place_day_1_piazza_di_santa_maria_in_trastevere | C11: Piazza di Santa Maria in Trastevere | D11: REVIVE_POINT_CANDIDATE | E11: =COUNTIFS(Ortszuordnung!$E$5:$E$85,B11,Ortszuordnung!$B$5:$B$85,"REGULAER") -> 0 | F11: =COUNTIF(Ortszuordnung!$E$5:$E$85,B11)-E11 -> 0 | G11: GRUEN | H11: Wiederbelebung / Sammelpunkt | I11: VISUAL_EVIDENCE_NOT_YET_VERIFIED | J11: https://www.google.com/maps/search/?api=1&query=41.8895605,12.4703092 | K11: ALS_SEPARATEN_SUPPORTPUNKT_BEHALTEN
A12: DAY_2 | B12: place_day_2_piazza_del_campidoglio | C12: Kapitolsplatz | D12: REVIVE_POINT_CANDIDATE | E12: =COUNTIFS(Ortszuordnung!$E$5:$E$85,B12,Ortszuordnung!$B$5:$B$85,"REGULAER") -> 1 | F12: =COUNTIF(Ortszuordnung!$E$5:$E$85,B12)-E12 -> 0 | G12: GRUEN | H12: Wiederbelebung / Sammelpunkt | I12: VISUAL_EVIDENCE_NOT_YET_VERIFIED|CROWDING_RISK | J12: https://www.google.com/maps/search/?api=1&query=41.8932288,12.4829654 | K12: ALS_SEPARATEN_SUPPORTPUNKT_BEHALTEN
A13: DAY_2 | B13: place_day_2_colosseo | C13: Kolosseum | D13: MEDIA_QUEST_LOCATION|LOCAL_MEDIA_QUEST|STORE_LOCATION_CANDIDATE | E13: =COUNTIFS(Ortszuordnung!$E$5:$E$85,B13,Ortszuordnung!$B$5:$B$85,"REGULAER") -> 1 | F13: =COUNTIF(Ortszuordnung!$E$5:$E$85,B13)-E13 -> 1 | G13: GRUEN | H13: Store | I13: Außenkoordinate verwenden; weder Eintritt noch Sicherheitskontrolle dürfen erforderlich sein. | J13: https://www.google.com/maps/search/?api=1&query=41.88989,12.49337 | K13: ALS_SEPARATEN_SUPPORTPUNKT_BEHALTEN | L13: STORE-D2-01 | M13: 500 m | N13: 15 m | O13: Stores!A8:I8
A14: DAY_2 | B14: place_day_2_piazza_vittorio_emanuele_secondo | C14: Piazza Vittorio Emanuele Secondo | D14: REVIVE_POINT_CANDIDATE|STORE_LOCATION_CANDIDATE | E14: =COUNTIFS(Ortszuordnung!$E$5:$E$85,B14,Ortszuordnung!$B$5:$B$85,"REGULAER") -> 0 | F14: =COUNTIF(Ortszuordnung!$E$5:$E$85,B14)-E14 -> 1 | G14: GELB | H14: Wiederbelebung / Sammelpunkt | I14: Nur innerhalb der sicheren Tagesöffnung des Gartens einplanen; bei Sperre gleichörtige Platzaufgabe bereitstellen. | J14: https://www.google.com/maps/search/?api=1&query=41.8946228,12.5043081 | K14: ALS_SEPARATEN_SUPPORTPUNKT_BEHALTEN | L14: STORE-D2-02 | M14: 500 m | N14: 15 m | O14: Stores!A9:I9
A15: DAY_2 | B15: place_day_2_basilica_di_santa_maria_maggiore | C15: Basilika Groß Sankt Marien | D15: REVIVE_POINT_CANDIDATE|WORLD_BOSS_LOCATION|BOSS_STAGING_SAFE_ZONE | E15: =COUNTIFS(Ortszuordnung!$E$5:$E$85,B15,Ortszuordnung!$B$5:$B$85,"REGULAER") -> 1 | F15: =COUNTIF(Ortszuordnung!$E$5:$E$85,B15)-E15 -> 1 | G15: GELB | H15: Wiederbelebung / Sammelpunkt | I15: Primär Boss-Staging auf dem öffentlichen Platz. Die Loggiazahl muss auf aktuellem Frontalbild nochmals bestätigt werden. | J15: https://www.google.com/maps/search/?api=1&query=41.89712887126836,12.499145861948264 | K15: ALS_SEPARATEN_SUPPORTPUNKT_BEHALTEN
A16: DAY_2 | B16: place_day_2_circo_massimo | C16: Circus Maximus | D16: MEDIA_QUEST_LOCATION|LOCAL_MEDIA_QUEST|REVIVE_POINT_CANDIDATE | E16: =COUNTIFS(Ortszuordnung!$E$5:$E$85,B16,Ortszuordnung!$B$5:$B$85,"REGULAER") -> 0 | F16: =COUNTIF(Ortszuordnung!$E$5:$E$85,B16)-E16 -> 1 | G16: GRUEN | H16: Wiederbelebung / Sammelpunkt | I16: Fotoquest Streitwagenrennen: exakt fünf Bilder; Pickup und Upload am selben Außenpunkt im 15-m-Radius. | J16: https://www.google.com/maps/search/?api=1&query=41.886650681433466,12.484508661426391 | K16: ALS_SEPARATEN_SUPPORTPUNKT_BEHALTEN

Sheet Kandidatenstatus
A1: Via Romae – Kandidatenstatus nach Gruppierung
A2: Alle 90 Orte: Kernquest, Sonderquest, Support, Reserve oder Ausschluss. Reserve ist bewusst und kein Recherchefehler.
A4: Kandidaten-ID | B4: Tag | C4: Cluster | D4: Ort | E4: Ampel | F4: Research-Status | G4: Supportrollen | H4: Kernnutzungen | I4: Sondernutzungen | J4: Entscheidung | K4: Score v0.3 | L4: Gegnerhook | M4: Begründung / nächste Verwendung
A5: place_day_1_piazza_san_pietro | B5: DAY_1 | C5: D1_VATICANO_PRATI_BORGO | D5: Petersplatz | E5: GELB | F5: GELB_MENSCHENMENGE | H5: =COUNTIFS(Ortszuordnung!$E$5:$E$85,A5,Ortszuordnung!$B$5:$B$85,"REGULAER") -> 1 | I5: =COUNTIF(Ortszuordnung!$E$5:$E$85,A5)-H5 -> 1 | J5: =IF(E5="ROT","AUSSCHLUSS",IF(H5>0,"KERNQUEST",IF(I5>0,"SONDERQUEST",IF(G5<>"","SUPPORT","RESERVE")))) -> KERNQUEST | K5: 93 | M5: =IF(J5="AUSSCHLUSS","Nicht als Pflichtort; nur nach neuer Evidenz neu bewerten.",IF(J5="KERNQUEST","In regulärer Quest gruppiert; aktuelle Sicht und blinden Test vor Release abschließen.",IF(J5="SONDERQUEST","Für Medien-, Hidden- oder Bossinhalt vorgesehen; separate Slot- oder Eventregel.",IF(J5="SUPPORT","Nur als Supportpunkt behalten; keine zusätzliche Pflichtquest.","Als Ersatz- oder späterer Questkandidat erhalten.")))) -> In regulärer Quest gruppiert; aktuelle Sicht und blinden Test vor Release abschließen.
A6: place_day_1_ponte_sant_angelo | B6: DAY_1 | C6: D1_VATICANO_PRATI_BORGO | D6: Engelsbrücke | E6: GRUEN | F6: GRUEN_KONZEPTREIF | H6: =COUNTIFS(Ortszuordnung!$E$5:$E$85,A6,Ortszuordnung!$B$5:$B$85,"REGULAER") -> 0 | I6: =COUNTIF(Ortszuordnung!$E$5:$E$85,A6)-H6 -> 1 | J6: =IF(E6="ROT","AUSSCHLUSS",IF(H6>0,"KERNQUEST",IF(I6>0,"SONDERQUEST",IF(G6<>"","SUPPORT","RESERVE")))) -> SONDERQUEST | K6: 89 | L6: Angelo della Passione | M6: =IF(J6="AUSSCHLUSS","Nicht als Pflichtort; nur nach neuer Evidenz neu bewerten.",IF(J6="KERNQUEST","In regulärer Quest gruppiert; aktuelle Sicht und blinden Test vor Release abschließen.",IF(J6="SONDERQUEST","Für Medien-, Hidden- oder Bossinhalt vorgesehen; separate Slot- oder Eventregel.",IF(J6="SUPPORT","Nur als Supportpunkt behalten; keine zusätzliche Pflichtquest.","Als Ersatz- oder späterer Questkandidat erhalten.")))) -> Für Medien-, Hidden- oder Bossinhalt vorgesehen; separate Slot- oder Eventregel.
A7: place_day_1_castel_sant_angelo | B7: DAY_1 | C7: D1_VATICANO_PRATI_BORGO | D7: Engelsburg | E7: GRUEN | F7: GRUEN_AUSSENPUNKT | G7: STORE_LOCATION_CANDIDATE|CLASS_HISTORY_QUEST_ANCHOR | H7: =COUNTIFS(Ortszuordnung!$E$5:$E$85,A7,Ortszuordnung!$B$5:$B$85,"REGULAER") -> 1 | I7: =COUNTIF(Ortszuordnung!$E$5:$E$85,A7)-H7 -> 0 | J7: =IF(E7="ROT","AUSSCHLUSS",IF(H7>0,"KERNQUEST",IF(I7>0,"SONDERQUEST",IF(G7<>"","SUPPORT","RESERVE")))) -> KERNQUEST | K7: 86 | M7: =IF(J7="AUSSCHLUSS","Nicht als Pflichtort; nur nach neuer Evidenz neu bewerten.",IF(J7="KERNQUEST","In regulärer Quest gruppiert; aktuelle Sicht und blinden Test vor Release abschließen.",IF(J7="SONDERQUEST","Für Medien-, Hidden- oder Bossinhalt vorgesehen; separate Slot- oder Eventregel.",IF(J7="SUPPORT","Nur als Supportpunkt behalten; keine zusätzliche Pflichtquest.","Als Ersatz- oder späterer Questkandidat erhalten.")))) -> In regulärer Quest gruppiert; aktuelle Sicht und blinden Test vor Release abschließen.
A8: place_day_1_porta_san_pellegrino | B8: DAY_1 | C8: D1_VATICANO_PRATI_BORGO | D8: St.-Pellegrino-Tor | E8: GELB | F8: GELB_DETAIL_HOCH | H8: =COUNTIFS(Ortszuordnung!$E$5:$E$85,A8,Ortszuordnung!$B$5:$B$85,"REGULAER") -> 1 | I8: =COUNTIF(Ortszuordnung!$E$5:$E$85,A8)-H8 -> 0 | J8: =IF(E8="ROT","AUSSCHLUSS",IF(H8>0,"KERNQUEST",IF(I8>0,"SONDERQUEST",IF(G8<>"","SUPPORT","RESERVE")))) -> KERNQUEST | K8: 91 | M8: =IF(J8="AUSSCHLUSS","Nicht als Pflichtort; nur nach neuer Evidenz neu bewerten.",IF(J8="KERNQUEST","In regulärer Quest gruppiert; aktuelle Sicht und blinden Test vor Release abschließen.",IF(J8="SONDERQUEST","Für Medien-, Hidden- oder Bossinhalt vorgesehen; separate Slot- oder Eventregel.",IF(J8="SUPPORT","Nur als Supportpunkt behalten; keine zusätzliche Pflichtquest.","Als Ersatz- oder späterer Questkandidat erhalten.")))) -> In regulärer Quest gruppiert; aktuelle Sicht und blinden Test vor Release abschließen.
A9: place_day_1_passetto_di_borgo | B9: DAY_1 | C9: D1_VATICANO_PRATI_BORGO | D9: Passetto di Borgo | E9: GRUEN | F9: GRUEN_MIT_BLICKPUNKT | H9: =COUNTIFS(Ortszuordnung!$E$5:$E$85,A9,Ortszuordnung!$B$5:$B$85,"REGULAER") -> 1 | I9: =COUNTIF(Ortszuordnung!$E$5:$E$85,A9)-H9 -> 0 | J9: =IF(E9="ROT","AUSSCHLUSS",IF(H9>0,"KERNQUEST",IF(I9>0,"SONDERQUEST",IF(G9<>"","SUPPORT","RESERVE")))) -> KERNQUEST | K9: 90 | M9: =IF(J9="AUSSCHLUSS","Nicht als Pflichtort; nur nach neuer Evidenz neu bewerten.",IF(J9="KERNQUEST","In regulärer Quest gruppiert; aktuelle Sicht und blinden Test vor Release abschließen.",IF(J9="SONDERQUEST","Für Medien-, Hidden- oder Bossinhalt vorgesehen; separate Slot- oder Eventregel.",IF(J9="SUPPORT","Nur als Supportpunkt behalten; keine zusätzliche Pflichtquest.","Als Ersatz- oder späterer Questkandidat erhalten.")))) -> In regulärer Quest gruppiert; aktuelle Sicht und blinden Test vor Release abschließen.
A10: place_day_1_porta_santo_spirito | B10: DAY_1 | C10: D1_VATICANO_PRATI_BORGO | D10: Porta Santo Spirito | E10: GRUEN | F10: GRUEN_MIT_BLICKPUNKT | H10: =COUNTIFS(Ortszuordnung!$E$5:$E$85,A10,Ortszuordnung!$B$5:$B$85,"REGULAER") -> 1 | I10: =COUNTIF(Ortszuordnung!$E$5:$E$85,A10)-H10 -> 0 | J10: =IF(E10="ROT","AUSSCHLUSS",IF(H10>0,"KERNQUEST",IF(I10>0,"SONDERQUEST",IF(G10<>"","SUPPORT","RESERVE")))) -> KERNQUEST | K10: 89 | M10: =IF(J10="AUSSCHLUSS","Nicht als Pflichtort; nur nach neuer Evidenz neu bewerten.",IF(J10="KERNQUEST","In regulärer Quest gruppiert; aktuelle Sicht und blinden Test vor Release abschließen.",IF(J10="SONDERQUEST","Für Medien-, Hidden- oder Bossinhalt vorgesehen; separate Slot- oder Eventregel.",IF(J10="SUPPORT","Nur als Supportpunkt behalten; keine zusätzliche Pflichtquest.","Als Ersatz- oder späterer Questkandidat erhalten.")))) -> In regulärer Quest gruppiert; aktuelle Sicht und blinden Test vor Release abschließen.
A11: place_day_1_piazza_del_popolo | B11: DAY_1 | C11: D1_POPOLO_PINCIO_SPAGNA | D11: Piazza del Popolo | E11: GRUEN | F11: GRUEN_KONZEPTREIF | G11: REVIVE_POINT_CANDIDATE | H11: =COUNTIFS(Ortszuordnung!$E$5:$E$85,A11,Ortszuordnung!$B$5:$B$85,"REGULAER") -> 1 | I11: =COUNTIF(Ortszuordnung!$E$5:$E$85,A11)-H11 -> 0 | J11: =IF(E11="ROT","AUSSCHLUSS",IF(H11>0,"KERNQUEST",IF(I11>0,"SONDERQUEST",IF(G11<>"","SUPPORT","RESERVE")))) -> KERNQUEST | K11: 89 | M11: =IF(J11="AUSSCHLUSS","Nicht als Pflichtort; nur nach neuer Evidenz neu bewerten.",IF(J11="KERNQUEST","In regulärer Quest gruppiert; aktuelle Sicht und blinden Test vor Release abschließen.",IF(J11="SONDERQUEST","Für Medien-, Hidden- oder Bossinhalt vorgesehen; separate Slot- oder Eventregel.",IF(J11="SUPPORT","Nur als Supportpunkt behalten; keine zusätzliche Pflichtquest.","Als Ersatz- oder späterer Questkandidat erhalten.")))) -> In regulärer Quest gruppiert; aktuelle Sicht und blinden Test vor Release abschließen.
A12: place_day_1_piazza_di_spagna | B12: DAY_1 | C12: D1_POPOLO_PINCIO_SPAGNA | D12: Spanischer Platz | E12: GRUEN | F12: GRUEN_MENSCHENMENGE | H12: =COUNTIFS(Ortszuordnung!$E$5:$E$85,A12,Ortszuordnung!$B$5:$B$85,"REGULAER") -> 1 | I12: =COUNTIF(Ortszuordnung!$E$5:$E$85,A12)-H12 -> 0 | J12: =IF(E12="ROT","AUSSCHLUSS",IF(H12>0,"KERNQUEST",IF(I12>0,"SONDERQUEST",IF(G12<>"","SUPPORT","RESERVE")))) -> KERNQUEST | K12: 89 | M12: =IF(J12="AUSSCHLUSS","Nicht als Pflichtort; nur nach neuer Evidenz neu bewerten.",IF(J12="KERNQUEST","In regulärer Quest gruppiert; aktuelle Sicht und blinden Test vor Release abschließen.",IF(J12="SONDERQUEST","Für Medien-, Hidden- oder Bossinhalt vorgesehen; separate Slot- oder Eventregel.",IF(J12="SUPPORT","Nur als Supportpunkt behalten; keine zusätzliche Pflichtquest.","Als Ersatz- oder späterer Questkandidat erhalten.")))) -> In regulärer Quest gruppiert; aktuelle Sicht und blinden Test vor Release abschließen.
A13: place_day_1_obelisco_flaminio | B13: DAY_1 | C13: D1_POPOLO_PINCIO_SPAGNA | D13: Obelisco Flaminio | E13: GRUEN | F13: GRUEN_KONZEPTREIF | H13: =COUNTIFS(Ortszuordnung!$E$5:$E$85,A13,Ortszuordnung!$B$5:$B$85,"REGULAER") -> 1 | I13: =COUNTIF(Ortszuordnung!$E$5:$E$85,A13)-H13 -> 0 | J13: =IF(E13="ROT","AUSSCHLUSS",IF(H13>0,"KERNQUEST",IF(I13>0,"SONDERQUEST",IF(G13<>"","SUPPORT","RESERVE")))) -> KERNQUEST | K13: 87 | L13: Leone del Flaminio | M13: =IF(J13="AUSSCHLUSS","Nicht als Pflichtort; nur nach neuer Evidenz neu bewerten.",IF(J13="KERNQUEST","In regulärer Quest gruppiert; aktuelle Sicht und blinden Test vor Release abschließen.",IF(J13="SONDERQUEST","Für Medien-, Hidden- oder Bossinhalt vorgesehen; separate Slot- oder Eventregel.",IF(J13="SUPPORT","Nur als Supportpunkt behalten; keine zusätzliche Pflichtquest.","Als Ersatz- oder späterer Questkandidat erhalten.")))) -> In regulärer Quest gruppiert; aktuelle Sicht und blinden Test vor Release abschließen.
A14: place_day_1_porta_del_popolo | B14: DAY_1 | C14: D1_POPOLO_PINCIO_SPAGNA | D14: Porta del Popolo | E14: GRUEN | F14: GRUEN_KONZEPTREIF | H14: =COUNTIFS(Ortszuordnung!$E$5:$E$85,A14,Ortszuordnung!$B$5:$B$85,"REGULAER") -> 1 | I14: =COUNTIF(Ortszuordnung!$E$5:$E$85,A14)-H14 -> 0 | J14: =IF(E14="ROT","AUSSCHLUSS",IF(H14>0,"KERNQUEST",IF(I14>0,"SONDERQUEST",IF(G14<>"","SUPPORT","RESERVE")))) -> KERNQUEST | K14: 89 | M14: =IF(J14="AUSSCHLUSS","Nicht als Pflichtort; nur nach neuer Evidenz neu bewerten.",IF(J14="KERNQUEST","In regulärer Quest gruppiert; aktuelle Sicht und blinden Test vor Release abschließen.",IF(J14="SONDERQUEST","Für Medien-, Hidden- oder Bossinhalt vorgesehen; separate Slot- oder Eventregel.",IF(J14="SUPPORT","Nur als Supportpunkt behalten; keine zusätzliche Pflichtquest.","Als Ersatz- oder späterer Questkandidat erhalten.")))) -> In regulärer Quest gruppiert; aktuelle Sicht und blinden Test vor Release abschließen.
A15: place_day_1_monumento_ai_fratelli_cairoli | B15: DAY_1 | C15: D1_POPOLO_PINCIO_SPAGNA | D15: Monumento ai Fratelli Cairoli | E15: GRUEN | F15: GRUEN_KONZEPTREIF | H15: =COUNTIFS(Ortszuordnung!$E$5:$E$85,A15,Ortszuordnung!$B$5:$B$85,"REGULAER") -> 0 | I15: =COUNTIF(Ortszuordnung!$E$5:$E$85,A15)-H15 -> 0 | J15: =IF(E15="ROT","AUSSCHLUSS",IF(H15>0,"KERNQUEST",IF(I15>0,"SONDERQUEST",IF(G15<>"","SUPPORT","RESERVE")))) -> RESERVE | K15: 88 | M15: =IF(J15="AUSSCHLUSS","Nicht als Pflichtort; nur nach neuer Evidenz neu bewerten.",IF(J15="KERNQUEST","In regulärer Quest gruppiert; aktuelle Sicht und blinden Test vor Release abschließen.",IF(J15="SONDERQUEST","Für Medien-, Hidden- oder Bossinhalt vorgesehen; separate Slot- oder Eventregel.",IF(J15="SUPPORT","Nur als Supportpunkt behalten; keine zusätzliche Pflichtquest.","Als Ersatz- oder späterer Questkandidat erhalten.")))) -> Als Ersatz- oder späterer Questkandidat erhalten.
A16: place_day_1_piazza_navona | B16: DAY_1 | C16: D1_NAVONA_PANTHEON | D16: Piazza Navona | E16: GRUEN | F16: GRUEN_MENSCHENMENGE | G16: MEDIA_QUEST_LOCATION|LOCAL_MEDIA_QUEST|REVIVE_POINT_CANDIDATE|STORE_LOCATION_CANDIDATE|CLASS_HISTORY_QUEST_ANCHOR | H16: =COUNTIFS(Ortszuordnung!$E$5:$E$85,A16,Ortszuordnung!$B$5:$B$85,"REGULAER") -> 1 | I16: =COUNTIF(Ortszuordnung!$E$5:$E$85,A16)-H16 -> 1 | J16: =IF(E16="ROT","AUSSCHLUSS",IF(H16>0,"KERNQUEST",IF(I16>0,"SONDERQUEST",IF(G16<>"","SUPPORT","RESERVE")))) -> KERNQUEST | K16: 93 | M16: =IF(J16="AUSSCHLUSS","Nicht als Pflichtort; nur nach neuer Evidenz neu bewerten.",IF(J16="KERNQUEST","In regulärer Quest gruppiert; aktuelle Sicht und blinden Test vor Release abschließen.",IF(J16="SONDERQUEST","Für Medien-, Hidden- oder Bossinhalt vorgesehen; separate Slot- oder Eventregel.",IF(J16="SUPPORT","Nur als Supportpunkt behalten; keine zusätzliche Pflichtquest.","Als Ersatz- oder späterer Questkandidat erhalten.")))) -> In regulärer Quest gruppiert; aktuelle Sicht und blinden Test vor Release abschließen.
A17: place_day_1_obelisco_di_montecitorio | B17: DAY_1 | C17: D1_NAVONA_PANTHEON | D17: Obelisco di Montecitorio | E17: GRUEN | F17: GRUEN_KONZEPTREIF | H17: =COUNTIFS(Ortszuordnung!$E$5:$E$85,A17,Ortszuordnung!$B$5:$B$85,"REGULAER") -> 1 | I17: =COUNTIF(Ortszuordnung!$E$5:$E$85,A17)-H17 -> 0 | J17: =IF(E17="ROT","AUSSCHLUSS",IF(H17>0,"KERNQUEST",IF(I17>0,"SONDERQUEST",IF(G17<>"","SUPPORT","RESERVE")))) -> KERNQUEST | K17: 91 | L17: Ombra dell’Horologium | M17: =IF(J17="AUSSCHLUSS","Nicht als Pflichtort; nur nach neuer Evidenz neu bewerten.",IF(J17="KERNQUEST","In regulärer Quest gruppiert; aktuelle Sicht und blinden Test vor Release abschließen.",IF(J17="SONDERQUEST","Für Medien-, Hidden- oder Bossinhalt vorgesehen; separate Slot- oder Eventregel.",IF(J17="SUPPORT","Nur als Supportpunkt behalten; keine zusätzliche Pflichtquest.","Als Ersatz- oder späterer Questkandidat erhalten.")))) -> In regulärer Quest gruppiert; aktuelle Sicht und blinden Test vor Release abschließen.
A18: place_day_1_fontana_del_nettuno | B18: DAY_1 | C18: D1_NAVONA_PANTHEON | D18: Neptunsbrunnen | E18: GRUEN | F18: GRUEN_KONZEPTREIF | H18: =COUNTIFS(Ortszuordnung!$E$5:$E$85,A18,Ortszuordnung!$B$5:$B$85,"REGULAER") -> 1 | I18: =COUNTIF(Ortszuordnung!$E$5:$E$85,A18)-H18 -> 1 | J18: =IF(E18="ROT","AUSSCHLUSS",IF(H18>0,"KERNQUEST",IF(I18>0,"SONDERQUEST",IF(G18<>"","SUPPORT","RESERVE")))) -> KERNQUEST | K18: 88 | M18: =IF(J18="AUSSCHLUSS","Nicht als Pflichtort; nur nach neuer Evidenz neu bewerten.",IF(J18="KERNQUEST","In regulärer Quest gruppiert; aktuelle Sicht und blinden Test vor Release abschließen.",IF(J18="SONDERQUEST","Für Medien-, Hidden- oder Bossinhalt vorgesehen; separate Slot- oder Eventregel.",IF(J18="SUPPORT","Nur als Supportpunkt behalten; keine zusätzliche Pflichtquest.","Als Ersatz- oder späterer Questkandidat erhalten.")))) -> In regulärer Quest gruppiert; aktuelle Sicht und blinden Test vor Release abschließen.
A19: place_day_1_fontana_del_moro | B19: DAY_1 | C19: D1_NAVONA_PANTHEON | D19: Mohrenbrunnen | E19: GRUEN | F19: GRUEN_KONZEPTREIF | H19: =COUNTIFS(Ortszuordnung!$E$5:$E$85,A19,Ortszuordnung!$B$5:$B$85,"REGULAER") -> 1 | I19: =COUNTIF(Ortszuordnung!$E$5:$E$85,A19)-H19 -> 1 | J19: =IF(E19="ROT","AUSSCHLUSS",IF(H19>0,"KERNQUEST",IF(I19>0,"SONDERQUEST",IF(G19<>"","SUPPORT","RESERVE")))) -> KERNQUEST | K19: 88 | M19: =IF(J19="AUSSCHLUSS","Nicht als Pflichtort; nur nach neuer Evidenz neu bewerten.",IF(J19="KERNQUEST","In regulärer Quest gruppiert; aktuelle Sicht und blinden Test vor Release abschließen.",IF(J19="SONDERQUEST","Für Medien-, Hidden- oder Bossinhalt vorgesehen; separate Slot- oder Eventregel.",IF(J19="SUPPORT","Nur als Supportpunkt behalten; keine zusätzliche Pflichtquest.","Als Ersatz- oder späterer Questkandidat erhalten.")))) -> In regulärer Quest gruppiert; aktuelle Sicht und blinden Test vor Release abschließen.
A20: place_day_1_pantheon | B20: DAY_1 | C20: D1_NAVONA_PANTHEON | D20: Pantheon | E20: GRUEN | F20: GRUEN_AUSSENPUNKT | H20: =COUNTIFS(Ortszuordnung!$E$5:$E$85,A20,Ortszuordnung!$B$5:$B$85,"REGULAER") -> 1 | I20: =COUNTIF(Ortszuordnung!$E$5:$E$85,A20)-H20 -> 0 | J20: =IF(E20="ROT","AUSSCHLUSS",IF(H20>0,"KERNQUEST",IF(I20>0,"SONDERQUEST",IF(G20<>"","SUPPORT","RESERVE")))) -> KERNQUEST | K20: 83 | M20: =IF(J20="AUSSCHLUSS","Nicht als Pflichtort; nur nach neuer Evidenz neu bewerten.",IF(J20="KERNQUEST","In regulärer Quest gruppiert; aktuelle Sicht und blinden Test vor Release abschließen.",IF(J20="SONDERQUEST","Für Medien-, Hidden- oder Bossinhalt vorgesehen; separate Slot- oder Eventregel.",IF(J20="SUPPORT","Nur als Supportpunkt behalten; keine zusätzliche Pflichtquest.","Als Ersatz- oder späterer Questkandidat erhalten.")))) -> In regulärer Quest gruppiert; aktuelle Sicht und blinden Test vor Release abschließen.
A21: place_day_1_colonna_di_marco_aurelio | B21: DAY_1 | C21: D1_NAVONA_PANTHEON | D21: Mark-Aurel-Säule | E21: GRUEN | F21: GRUEN_KONZEPTREIF | H21: =COUNTIFS(Ortszuordnung!$E$5:$E$85,A21,Ortszuordnung!$B$5:$B$85,"REGULAER") -> 1 | I21: =COUNTIF(Ortszuordnung!$E$5:$E$85,A21)-H21 -> 0 | J21: =IF(E21="ROT","AUSSCHLUSS",IF(H21>0,"KERNQUEST",IF(I21>0,"SONDERQUEST",IF(G21<>"","SUPPORT","RESERVE")))) -> KERNQUEST | K21: 89 | L21: Legionario della Colonna | M21: =IF(J21="AUSSCHLUSS","Nicht als Pflichtort; nur nach neuer Evidenz neu bewerten.",IF(J21="KERNQUEST","In regulärer Quest gruppiert; aktuelle Sicht und blinden Test vor Release abschließen.",IF(J21="SONDERQUEST","Für Medien-, Hidden- oder Bossinhalt vorgesehen; separate Slot- oder Eventregel.",IF(J21="SUPPORT","Nur als Supportpunkt behalten; keine zusätzliche Pflichtquest.","Als Ersatz- oder späterer Questkandidat erhalten.")))) -> In regulärer Quest gruppiert; aktuelle Sicht und blinden Test vor Release abschließen.
A22: place_day_1_fontana_di_trevi | B22: DAY_1 | C22: D1_TREVI_QUIRINALE | D22: Trevi-Brunnen | E22: GELB | F22: GELB_EXTREME_MENSCHENMENGE | H22: =COUNTIFS(Ortszuordnung!$E$5:$E$85,A22,Ortszuordnung!$B$5:$B$85,"REGULAER") -> 1 | I22: =COUNTIF(Ortszuordnung!$E$5:$E$85,A22)-H22 -> 0 | J22: =IF(E22="ROT","AUSSCHLUSS",IF(H22>0,"KERNQUEST",IF(I22>0,"SONDERQUEST",IF(G22<>"","SUPPORT","RESERVE")))) -> KERNQUEST | K22: 91 | M22: =IF(J22="AUSSCHLUSS","Nicht als Pflichtort; nur nach neuer Evidenz neu bewerten.",IF(J22="KERNQUEST","In regulärer Quest gruppiert; aktuelle Sicht und blinden Test vor Release abschließen.",IF(J22="SONDERQUEST","Für Medien-, Hidden- oder Bossinhalt vorgesehen; separate Slot- oder Eventregel.",IF(J22="SUPPORT","Nur als Supportpunkt behalten; keine zusätzliche Pflichtquest.","Als Ersatz- oder späterer Questkandidat erhalten.")))) -> In regulärer Quest gruppiert; aktuelle Sicht und blinden Test vor Release abschließen.
A23: place_day_1_fontana_del_tritone | B23: DAY_1 | C23: D1_TREVI_QUIRINALE | D23: Tritonenbrunnen | E23: GRUEN | F23: GRUEN_KONZEPTREIF | H23: =COUNTIFS(Ortszuordnung!$E$5:$E$85,A23,Ortszuordnung!$B$5:$B$85,"REGULAER") -> 1 | I23: =COUNTIF(Ortszuordnung!$E$5:$E$85,A23)-H23 -> 0 | J23: =IF(E23="ROT","AUSSCHLUSS",IF(H23>0,"KERNQUEST",IF(I23>0,"SONDERQUEST",IF(G23<>"","SUPPORT","RESERVE")))) -> KERNQUEST | K23: 88 | M23: =IF(J23="AUSSCHLUSS","Nicht als Pflichtort; nur nach neuer Evidenz neu bewerten.",IF(J23="KERNQUEST","In regulärer Quest gruppiert; aktuelle Sicht und blinden Test vor Release abschließen.",IF(J23="SONDERQUEST","Für Medien-, Hidden- oder Bossinhalt vorgesehen; separate Slot- oder Eventregel.",IF(J23="SUPPORT","Nur als Supportpunkt behalten; keine zusätzliche Pflichtquest.","Als Ersatz- oder späterer Questkandidat erhalten.")))) -> In regulärer Quest gruppiert; aktuelle Sicht und blinden Test vor Release abschließen.
A24: place_day_1_obelisco_del_quirinale | B24: DAY_1 | C24: D1_TREVI_QUIRINALE | D24: Obelisco del Quirinale | E24: GRUEN | F24: GRUEN_KONZEPTREIF | H24: =COUNTIFS(Ortszuordnung!$E$5:$E$85,A24,Ortszuordnung!$B$5:$B$85,"REGULAER") -> 1 | I24: =COUNTIF(Ortszuordnung!$E$5:$E$85,A24)-H24 -> 0 | J24: =IF(E24="ROT","AUSSCHLUSS",IF(H24>0,"KERNQUEST",IF(I24>0,"SONDERQUEST",IF(G24<>"","SUPPORT","RESERVE")))) -> KERNQUEST | K24: 90 | M24: =IF(J24="AUSSCHLUSS","Nicht als Pflichtort; nur nach neuer Evidenz neu bewerten.",IF(J24="KERNQUEST","In regulärer Quest gruppiert; aktuelle Sicht und blinden Test vor Release abschließen.",IF(J24="SONDERQUEST","Für Medien-, Hidden- oder Bossinhalt vorgesehen; separate Slot- oder Eventregel.",IF(J24="SUPPORT","Nur als Supportpunkt behalten; keine zusätzliche Pflichtquest.","Als Ersatz- oder späterer Questkandidat erhalten.")))) -> In regulärer Quest gruppiert; aktuelle Sicht und blinden Test vor Release abschließen.
A25: place_day_1_colonna_dell_immacolata | B25: DAY_1 | C25: D1_TREVI_QUIRINALE | D25: Colonna dell'Immacolata | E25: GRUEN | F25: GRUEN_KONZEPTREIF | H25: =COUNTIFS(Ortszuordnung!$E$5:$E$85,A25,Ortszuordnung!$B$5:$B$85,"REGULAER") -> 1 | I25: =COUNTIF(Ortszuordnung!$E$5:$E$85,A25)-H25 -> 0 | J25: =IF(E25="ROT","AUSSCHLUSS",IF(H25>0,"KERNQUEST",IF(I25>0,"SONDERQUEST",IF(G25<>"","SUPPORT","RESERVE")))) -> KERNQUEST | K25: 89 | M25: =IF(J25="AUSSCHLUSS","Nicht als Pflichtort; nur nach neuer Evidenz neu bewerten.",IF(J25="KERNQUEST","In regulärer Quest gruppiert; aktuelle Sicht und blinden Test vor Release abschließen.",IF(J25="SONDERQUEST","Für Medien-, Hidden- oder Bossinhalt vorgesehen; separate Slot- oder Eventregel.",IF(J25="SUPPORT","Nur als Supportpunkt behalten; keine zusätzliche Pflichtquest.","Als Ersatz- oder späterer Questkandidat erhalten.")))) -> In regulärer Quest gruppiert; aktuelle Sicht und blinden Test vor Release abschließen.
A26: place_day_1_piazza_scanderbeg | B26: DAY_1 | C26: D1_TREVI_QUIRINALE | D26: Piazza Scanderbeg | E26: GELB | F26: GELB_KLEINES_FASSADENDETAIL | H26: =COUNTIFS(Ortszuordnung!$E$5:$E$85,A26,Ortszuordnung!$B$5:$B$85,"REGULAER") -> 1 | I26: =COUNTIF(Ortszuordnung!$E$5:$E$85,A26)-H26 -> 0 | J26: =IF(E26="ROT","AUSSCHLUSS",IF(H26>0,"KERNQUEST",IF(I26>0,"SONDERQUEST",IF(G26<>"","SUPPORT","RESERVE")))) -> KERNQUEST | K26: 89 | M26: =IF(J26="AUSSCHLUSS","Nicht als Pflichtort; nur nach neuer Evidenz neu bewerten.",IF(J26="KERNQUEST","In regulärer Quest gruppiert; aktuelle Sicht und blinden Test vor Release abschließen.",IF(J26="SONDERQUEST","Für Medien-, Hidden- oder Bossinhalt vorgesehen; separate Slot- oder Eventregel.",IF(J26="SUPPORT","Nur als Supportpunkt behalten; keine zusätzliche Pflichtquest.","Als Ersatz- oder späterer Questkandidat erhalten.")))) -> In regulärer Quest gruppiert; aktuelle Sicht und blinden Test vor Release abschließen.
A27: place_day_1_isola_tiberina | B27: DAY_1 | C27: D1_CAMPO_REGOLA_GHETTO | D27: Isola Tiberina | E27: GELB | F27: GELB_SICHTWINKEL | H27: =COUNTIFS(Ortszuordnung!$E$5:$E$85,A27,Ortszuordnung!$B$5:$B$85,"REGULAER") -> 1 | I27: =COUNTIF(Ortszuordnung!$E$5:$E$85,A27)-H27 -> 0 | J27: =IF(E27="ROT","AUSSCHLUSS",IF(H27>0,"KERNQUEST",IF(I27>0,"SONDERQUEST",IF(G27<>"","SUPPORT","RESERVE")))) -> KERNQUEST | K27: 83 | L27: Serpente di Esculapio | M27: =IF(J27="AUSSCHLUSS","Nicht als Pflichtort; nur nach neuer Evidenz neu bewerten.",IF(J27="KERNQUEST","In regulärer Quest gruppiert; aktuelle Sicht und blinden Test vor Release abschließen.",IF(J27="SONDERQUEST","Für Medien-, Hidden- oder Bossinhalt vorgesehen; separate Slot- oder Eventregel.",IF(J27="SUPPORT","Nur als Supportpunkt behalten; keine zusätzliche Pflichtquest.","Als Ersatz- oder späterer Questkandidat erhalten.")))) -> In regulärer Quest gruppiert; aktuelle Sicht und blinden Test vor Release abschließen.
A28: place_day_1_ponte_sisto | B28: DAY_1 | C28: D1_CAMPO_REGOLA_GHETTO | D28: Ponte Sisto | E28: GRUEN | F28: GRUEN_MIT_BLICKPUNKT | H28: =COUNTIFS(Ortszuordnung!$E$5:$E$85,A28,Ortszuordnung!$B$5:$B$85,"REGULAER") -> 1 | I28: =COUNTIF(Ortszuordnung!$E$5:$E$85,A28)-H28 -> 0 | J28: =IF(E28="ROT","AUSSCHLUSS",IF(H28>0,"KERNQUEST",IF(I28>0,"SONDERQUEST",IF(G28<>"","SUPPORT","RESERVE")))) -> KERNQUEST | K28: 83 | L28: Occhio del Tevere | M28: =IF(J28="AUSSCHLUSS","Nicht als Pflichtort; nur nach neuer Evidenz neu bewerten.",IF(J28="KERNQUEST","In regulärer Quest gruppiert; aktuelle Sicht und blinden Test vor Release abschließen.",IF(J28="SONDERQUEST","Für Medien-, Hidden- oder Bossinhalt vorgesehen; separate Slot- oder Eventregel.",IF(J28="SUPPORT","Nur als Supportpunkt behalten; keine zusätzliche Pflichtquest.","Als Ersatz- oder späterer Questkandidat erhalten.")))) -> In regulärer Quest gruppiert; aktuelle Sicht und blinden Test vor Release abschließen.
A29: place_day_1_palazzo_farnese | B29: DAY_1 | C29: D1_CAMPO_REGOLA_GHETTO | D29: Palazzo Farnese | E29: GELB | F29: GELB_SICHERHEITSBEREICH | H29: =COUNTIFS(Ortszuordnung!$E$5:$E$85,A29,Ortszuordnung!$B$5:$B$85,"REGULAER") -> 1 | I29: =COUNTIF(Ortszuordnung!$E$5:$E$85,A29)-H29 -> 0 | J29: =IF(E29="ROT","AUSSCHLUSS",IF(H29>0,"KERNQUEST",IF(I29>0,"SONDERQUEST",IF(G29<>"","SUPPORT","RESERVE")))) -> KERNQUEST | K29: 88 | M29: =IF(J29="AUSSCHLUSS","Nicht als Pflichtort; nur nach neuer Evidenz neu bewerten.",IF(J29="KERNQUEST","In regulärer Quest gruppiert; aktuelle Sicht und blinden Test vor Release abschließen.",IF(J29="SONDERQUEST","Für Medien-, Hidden- oder Bossinhalt vorgesehen; separate Slot- oder Eventregel.",IF(J29="SUPPORT","Nur als Supportpunkt behalten; keine zusätzliche Pflichtquest.","Als Ersatz- oder späterer Questkandidat erhalten.")))) -> In regulärer Quest gruppiert; aktuelle Sicht und blinden Test vor Release abschließen.
A30: place_day_1_largo_di_torre_argentina | B30: DAY_1 | C30: D1_CAMPO_REGOLA_GHETTO | D30: Largo di Torre Argentina | E30: GELB | F30: GELB_ZAEHLPERSPEKTIVE | H30: =COUNTIFS(Ortszuordnung!$E$5:$E$85,A30,Ortszuordnung!$B$5:$B$85,"REGULAER") -> 1 | I30: =COUNTIF(Ortszuordnung!$E$5:$E$85,A30)-H30 -> 0 | J30: =IF(E30="ROT","AUSSCHLUSS",IF(H30>0,"KERNQUEST",IF(I30>0,"SONDERQUEST",IF(G30<>"","SUPPORT","RESERVE")))) -> KERNQUEST | K30: 80 | M30: =IF(J30="AUSSCHLUSS","Nicht als Pflichtort; nur nach neuer Evidenz neu bewerten.",IF(J30="KERNQUEST","In regulärer Quest gruppiert; aktuelle Sicht und blinden Test vor Release abschließen.",IF(J30="SONDERQUEST","Für Medien-, Hidden- oder Bossinhalt vorgesehen; separate Slot- oder Eventregel.",IF(J30="SUPPORT","Nur als Supportpunkt behalten; keine zusätzliche Pflichtquest.","Als Ersatz- oder späterer Questkandidat erhalten.")))) -> In regulärer Quest gruppiert; aktuelle Sicht und blinden Test vor Release abschließen.
A31: place_day_1_campo_de_fiori | B31: DAY_1 | C31: D1_CAMPO_REGOLA_GHETTO | D31: Campo de' Fiori | E31: GRUEN | F31: GRUEN_MIT_MARKTRISIKO | G31: STORE_LOCATION_CANDIDATE | H31: =COUNTIFS(Ortszuordnung!$E$5:$E$85,A31,Ortszuordnung!$B$5:$B$85,"REGULAER") -> 1 | I31: =COUNTIF(Ortszuordnung!$E$5:$E$85,A31)-H31 -> 0 | J31: =IF(E31="ROT","AUSSCHLUSS",IF(H31>0,"KERNQUEST",IF(I31>0,"SONDERQUEST",IF(G31<>"","SUPPORT","RESERVE")))) -> KERNQUEST | K31: 89 | M31: =IF(J31="AUSSCHLUSS","Nicht als Pflichtort; nur nach neuer Evidenz neu bewerten.",IF(J31="KERNQUEST","In regulärer Quest gruppiert; aktuelle Sicht und blinden Test vor Release abschließen.",IF(J31="SONDERQUEST","Für Medien-, Hidden- oder Bossinhalt vorgesehen; separate Slot- oder Eventregel.",IF(J31="SUPPORT","Nur als Supportpunkt behalten; keine zusätzliche Pflichtquest.","Als Ersatz- oder späterer Questkandidat erhalten.")))) -> In regulärer Quest gruppiert; aktuelle Sicht und blinden Test vor Release abschließen.
A32: place_day_1_basilica_di_santa_cecilia_in_trastevere | B32: DAY_1 | C32: D1_TRASTEVERE_TIBER_ISLAND | D32: Basilica di Santa Cecilia in Trastevere | E32: GELB | F32: GELB_KLASSENANKER_OHNE_INNENHOF | H32: =COUNTIFS(Ortszuordnung!$E$5:$E$85,A32,Ortszuordnung!$B$5:$B$85,"REGULAER") -> 1 | I32: =COUNTIF(Ortszuordnung!$E$5:$E$85,A32)-H32 -> 0 | J32: =IF(E32="ROT","AUSSCHLUSS",IF(H32>0,"KERNQUEST",IF(I32>0,"SONDERQUEST",IF(G32<>"","SUPPORT","RESERVE")))) -> KERNQUEST | K32: 82 | M32: =IF(J32="AUSSCHLUSS","Nicht als Pflichtort; nur nach neuer Evidenz neu bewerten.",IF(J32="KERNQUEST","In regulärer Quest gruppiert; aktuelle Sicht und blinden Test vor Release abschließen.",IF(J32="SONDERQUEST","Für Medien-, Hidden- oder Bossinhalt vorgesehen; separate Slot- oder Eventregel.",IF(J32="SUPPORT","Nur als Supportpunkt behalten; keine zusätzliche Pflichtquest.","Als Ersatz- oder späterer Questkandidat erhalten.")))) -> In regulärer Quest gruppiert; aktuelle Sicht und blinden Test vor Release abschließen.
A33: place_day_1_basilica_di_santa_maria_in_trastevere | B33: DAY_1 | C33: D1_TRASTEVERE_TIBER_ISLAND | D33: Santa Maria in Trastevere | E33: GRUEN | F33: GRUEN_AUSSENPUNKT | H33: =COUNTIFS(Ortszuordnung!$E$5:$E$85,A33,Ortszuordnung!$B$5:$B$85,"REGULAER") -> 1 | I33: =COUNTIF(Ortszuordnung!$E$5:$E$85,A33)-H33 -> 0 | J33: =IF(E33="ROT","AUSSCHLUSS",IF(H33>0,"KERNQUEST",IF(I33>0,"SONDERQUEST",IF(G33<>"","SUPPORT","RESERVE")))) -> KERNQUEST | K33: 81 | M33: =IF(J33="AUSSCHLUSS","Nicht als Pflichtort; nur nach neuer Evidenz neu bewerten.",IF(J33="KERNQUEST","In regulärer Quest gruppiert; aktuelle Sicht und blinden Test vor Release abschließen.",IF(J33="SONDERQUEST","Für Medien-, Hidden- oder Bossinhalt vorgesehen; separate Slot- oder Eventregel.",IF(J33="SUPPORT","Nur als Supportpunkt behalten; keine zusätzliche Pflichtquest.","Als Ersatz- oder späterer Questkandidat erhalten.")))) -> In regulärer Quest gruppiert; aktuelle Sicht und blinden Test vor Release abschließen.
A34: place_day_1_porta_settimiana | B34: DAY_1 | C34: D1_TRASTEVERE_TIBER_ISLAND | D34: Porta Settimiana | E34: GRUEN | F34: GRUEN_KONZEPTREIF | H34: =COUNTIFS(Ortszuordnung!$E$5:$E$85,A34,Ortszuordnung!$B$5:$B$85,"REGULAER") -> 0 | I34: =COUNTIF(Ortszuordnung!$E$5:$E$85,A34)-H34 -> 0 | J34: =IF(E34="ROT","AUSSCHLUSS",IF(H34>0,"KERNQUEST",IF(I34>0,"SONDERQUEST",IF(G34<>"","SUPPORT","RESERVE")))) -> RESERVE | K34: 89 | M34: =IF(J34="AUSSCHLUSS","Nicht als Pflichtort; nur nach neuer Evidenz neu bewerten.",IF(J34="KERNQUEST","In regulärer Quest gruppiert; aktuelle Sicht und blinden Test vor Release abschließen.",IF(J34="SONDERQUEST","Für Medien-, Hidden- oder Bossinhalt vorgesehen; separate Slot- oder Eventregel.",IF(J34="SUPPORT","Nur als Supportpunkt behalten; keine zusätzliche Pflichtquest.","Als Ersatz- oder späterer Questkandidat erhalten.")))) -> Als Ersatz- oder späterer Questkandidat erhalten.
A35: place_day_1_mausoleo_ossario_garibaldino | B35: DAY_1 | C35: D1_TRASTEVERE_TIBER_ISLAND | D35: Mausoleo Ossario Garibaldino | E35: GRUEN | F35: GRUEN_KONZEPTREIF | H35: =COUNTIFS(Ortszuordnung!$E$5:$E$85,A35,Ortszuordnung!$B$5:$B$85,"REGULAER") -> 1 | I35: =COUNTIF(Ortszuordnung!$E$5:$E$85,A35)-H35 -> 0 | J35: =IF(E35="ROT","AUSSCHLUSS",IF(H35>0,"KERNQUEST",IF(I35>0,"SONDERQUEST",IF(G35<>"","SUPPORT","RESERVE")))) -> KERNQUEST | K35: 87 | M35: =IF(J35="AUSSCHLUSS","Nicht als Pflichtort; nur nach neuer Evidenz neu bewerten.",IF(J35="KERNQUEST","In regulärer Quest gruppiert; aktuelle Sicht und blinden Test vor Release abschließen.",IF(J35="SONDERQUEST","Für Medien-, Hidden- oder Bossinhalt vorgesehen; separate Slot- oder Eventregel.",IF(J35="SUPPORT","Nur als Supportpunkt behalten; keine zusätzliche Pflichtquest.","Als Ersatz- oder späterer Questkandidat erhalten.")))) -> In regulärer Quest gruppiert; aktuelle Sicht und blinden Test vor Release abschließen.
A36: place_day_1_fontana_del_prigione | B36: DAY_1 | C36: D1_TRASTEVERE_TIBER_ISLAND | D36: Fontana del Prigione | E36: GRUEN | F36: GRUEN_KONZEPTREIF | H36: =COUNTIFS(Ortszuordnung!$E$5:$E$85,A36,Ortszuordnung!$B$5:$B$85,"REGULAER") -> 0 | I36: =COUNTIF(Ortszuordnung!$E$5:$E$85,A36)-H36 -> 0 | J36: =IF(E36="ROT","AUSSCHLUSS",IF(H36>0,"KERNQUEST",IF(I36>0,"SONDERQUEST",IF(G36<>"","SUPPORT","RESERVE")))) -> RESERVE | K36: 87 | M36: =IF(J36="AUSSCHLUSS","Nicht als Pflichtort; nur nach neuer Evidenz neu bewerten.",IF(J36="KERNQUEST","In regulärer Quest gruppiert; aktuelle Sicht und blinden Test vor Release abschließen.",IF(J36="SONDERQUEST","Für Medien-, Hidden- oder Bossinhalt vorgesehen; separate Slot- oder Eventregel.",IF(J36="SUPPORT","Nur als Supportpunkt behalten; keine zusätzliche Pflichtquest.","Als Ersatz- oder späterer Questkandidat erhalten.")))) -> Als Ersatz- oder späterer Questkandidat erhalten.
A37: place_day_1_fontana_dell_acqua_paola | B37: DAY_1 | C37: D1_GIANICOLO | D37: Fontana Dell'Acqua Paola | E37: GRUEN | F37: GRUEN_KONZEPTREIF | G37: REVIVE_POINT_CANDIDATE | H37: =COUNTIFS(Ortszuordnung!$E$5:$E$85,A37,Ortszuordnung!$B$5:$B$85,"REGULAER") -> 1 | I37: =COUNTIF(Ortszuordnung!$E$5:$E$85,A37)-H37 -> 0 | J37: =IF(E37="ROT","AUSSCHLUSS",IF(H37>0,"KERNQUEST",IF(I37>0,"SONDERQUEST",IF(G37<>"","SUPPORT","RESERVE")))) -> KERNQUEST | K37: 91 | M37: =IF(J37="AUSSCHLUSS","Nicht als Pflichtort; nur nach neuer Evidenz neu bewerten.",IF(J37="KERNQUEST","In regulärer Quest gruppiert; aktuelle Sicht und blinden Test vor Release abschließen.",IF(J37="SONDERQUEST","Für Medien-, Hidden- oder Bossinhalt vorgesehen; separate Slot- oder Eventregel.",IF(J37="SUPPORT","Nur als Supportpunkt behalten; keine zusätzliche Pflichtquest.","Als Ersatz- oder späterer Questkandidat erhalten.")))) -> In regulärer Quest gruppiert; aktuelle Sicht und blinden Test vor Release abschließen.
A38: place_day_1_monumento_a_garibaldi | B38: DAY_1 | C38: D1_GIANICOLO | D38: Monumento a Garibaldi | E38: GRUEN | F38: GRUEN_KONZEPTREIF | H38: =COUNTIFS(Ortszuordnung!$E$5:$E$85,A38,Ortszuordnung!$B$5:$B$85,"REGULAER") -> 1 | I38: =COUNTIF(Ortszuordnung!$E$5:$E$85,A38)-H38 -> 0 | J38: =IF(E38="ROT","AUSSCHLUSS",IF(H38>0,"KERNQUEST",IF(I38>0,"SONDERQUEST",IF(G38<>"","SUPPORT","RESERVE")))) -> KERNQUEST | K38: 91 | M38: =IF(J38="AUSSCHLUSS","Nicht als Pflichtort; nur nach neuer Evidenz neu bewerten.",IF(J38="KERNQUEST","In regulärer Quest gruppiert; aktuelle Sicht und blinden Test vor Release abschließen.",IF(J38="SONDERQUEST","Für Medien-, Hidden- oder Bossinhalt vorgesehen; separate Slot- oder Eventregel.",IF(J38="SUPPORT","Nur als Supportpunkt behalten; keine zusätzliche Pflichtquest.","Als Ersatz- oder späterer Questkandidat erhalten.")))) -> In regulärer Quest gruppiert; aktuelle Sicht und blinden Test vor Release abschließen.
A39: place_day_1_monumento_ad_anita_garibaldi | B39: DAY_1 | C39: D1_GIANICOLO | D39: Monumento ad Anita Garibaldi | E39: GRUEN | F39: GRUEN_KONZEPTREIF | H39: =COUNTIFS(Ortszuordnung!$E$5:$E$85,A39,Ortszuordnung!$B$5:$B$85,"REGULAER") -> 1 | I39: =COUNTIF(Ortszuordnung!$E$5:$E$85,A39)-H39 -> 0 | J39: =IF(E39="ROT","AUSSCHLUSS",IF(H39>0,"KERNQUEST",IF(I39>0,"SONDERQUEST",IF(G39<>"","SUPPORT","RESERVE")))) -> KERNQUEST | K39: 87 | M39: =IF(J39="AUSSCHLUSS","Nicht als Pflichtort; nur nach neuer Evidenz neu bewerten.",IF(J39="KERNQUEST","In regulärer Quest gruppiert; aktuelle Sicht und blinden Test vor Release abschließen.",IF(J39="SONDERQUEST","Für Medien-, Hidden- oder Bossinhalt vorgesehen; separate Slot- oder Eventregel.",IF(J39="SUPPORT","Nur als Supportpunkt behalten; keine zusätzliche Pflichtquest.","Als Ersatz- oder späterer Questkandidat erhalten.")))) -> In regulärer Quest gruppiert; aktuelle Sicht und blinden Test vor Release abschließen.
A40: place_day_1_ponte_giuseppe_mazzini | B40: DAY_1 | C40: D1_GIANICOLO | D40: Ponte Giuseppe Mazzini | E40: GRUEN | F40: GRUEN_MIT_BLICKPUNKT | H40: =COUNTIFS(Ortszuordnung!$E$5:$E$85,A40,Ortszuordnung!$B$5:$B$85,"REGULAER") -> 0 | I40: =COUNTIF(Ortszuordnung!$E$5:$E$85,A40)-H40 -> 0 | J40: =IF(E40="ROT","AUSSCHLUSS",IF(H40>0,"KERNQUEST",IF(I40>0,"SONDERQUEST",IF(G40<>"","SUPPORT","RESERVE")))) -> RESERVE | K40: 85 | M40: =IF(J40="AUSSCHLUSS","Nicht als Pflichtort; nur nach neuer Evidenz neu bewerten.",IF(J40="KERNQUEST","In regulärer Quest gruppiert; aktuelle Sicht und blinden Test vor Release abschließen.",IF(J40="SONDERQUEST","Für Medien-, Hidden- oder Bossinhalt vorgesehen; separate Slot- oder Eventregel.",IF(J40="SUPPORT","Nur als Supportpunkt behalten; keine zusätzliche Pflichtquest.","Als Ersatz- oder späterer Questkandidat erhalten.")))) -> Als Ersatz- oder späterer Questkandidat erhalten.
A41: place_day_1_fontana_degli_undici_zampilli | B41: DAY_1 | C41: D1_GIANICOLO | D41: Fontana degli undici zampilli | E41: GRUEN | F41: GRUEN_KONZEPTREIF | H41: =COUNTIFS(Ortszuordnung!$E$5:$E$85,A41,Ortszuordnung!$B$5:$B$85,"REGULAER") -> 0 | I41: =COUNTIF(Ortszuordnung!$E$5:$E$85,A41)-H41 -> 0 | J41: =IF(E41="ROT","AUSSCHLUSS",IF(H41>0,"KERNQUEST",IF(I41>0,"SONDERQUEST",IF(G41<>"","SUPPORT","RESERVE")))) -> RESERVE | K41: 85 | M41: =IF(J41="AUSSCHLUSS","Nicht als Pflichtort; nur nach neuer Evidenz neu bewerten.",IF(J41="KERNQUEST","In regulärer Quest gruppiert; aktuelle Sicht und blinden Test vor Release abschließen.",IF(J41="SONDERQUEST","Für Medien-, Hidden- oder Bossinhalt vorgesehen; separate Slot- oder Eventregel.",IF(J41="SUPPORT","Nur als Supportpunkt behalten; keine zusätzliche Pflichtquest.","Als Ersatz- oder späterer Questkandidat erhalten.")))) -> Als Ersatz- oder späterer Questkandidat erhalten.
A42: place_day_1_obelisco_della_minerva | B42: DAY_1 | C42: D1_NAVONA_PANTHEON | D42: Obelisco della Minerva | E42: ROT | F42: ROT_AKTUELL_GESPERRT | H42: =COUNTIFS(Ortszuordnung!$E$5:$E$85,A42,Ortszuordnung!$B$5:$B$85,"REGULAER") -> 0 | I42: =COUNTIF(Ortszuordnung!$E$5:$E$85,A42)-H42 -> 0 | J42: =IF(E42="ROT","AUSSCHLUSS",IF(H42>0,"KERNQUEST",IF(I42>0,"SONDERQUEST",IF(G42<>"","SUPPORT","RESERVE")))) -> AUSSCHLUSS | K42: 91 | L42: Elefante Minerveo | M42: =IF(J42="AUSSCHLUSS","Nicht als Pflichtort; nur nach neuer Evidenz neu bewerten.",IF(J42="KERNQUEST","In regulärer Quest gruppiert; aktuelle Sicht und blinden Test vor Release abschließen.",IF(J42="SONDERQUEST","Für Medien-, Hidden- oder Bossinhalt vorgesehen; separate Slot- oder Eventregel.",IF(J42="SUPPORT","Nur als Supportpunkt behalten; keine zusätzliche Pflichtquest.","Als Ersatz- oder späterer Questkandidat erhalten.")))) -> Nicht als Pflichtort; nur nach neuer Evidenz neu bewerten.
A43: place_day_1_basilica_di_sant_andrea_della_valle | B43: DAY_1 | C43: D1_CAMPO_REGOLA_GHETTO | D43: Basilica di Sant'Andrea della Valle | E43: GELB | F43: GELB_FASSADENSICHT | H43: =COUNTIFS(Ortszuordnung!$E$5:$E$85,A43,Ortszuordnung!$B$5:$B$85,"REGULAER") -> 1 | I43: =COUNTIF(Ortszuordnung!$E$5:$E$85,A43)-H43 -> 0 | J43: =IF(E43="ROT","AUSSCHLUSS",IF(H43>0,"KERNQUEST",IF(I43>0,"SONDERQUEST",IF(G43<>"","SUPPORT","RESERVE")))) -> KERNQUEST | K43: 83 | L43: Custode della Cupola | M43: =IF(J43="AUSSCHLUSS","Nicht als Pflichtort; nur nach neuer Evidenz neu bewerten.",IF(J43="KERNQUEST","In regulärer Quest gruppiert; aktuelle Sicht und blinden Test vor Release abschließen.",IF(J43="SONDERQUEST","Für Medien-, Hidden- oder Bossinhalt vorgesehen; separate Slot- oder Eventregel.",IF(J43="SUPPORT","Nur als Supportpunkt behalten; keine zusätzliche Pflichtquest.","Als Ersatz- oder späterer Questkandidat erhalten.")))) -> In regulärer Quest gruppiert; aktuelle Sicht und blinden Test vor Release abschließen.
A44: place_day_1_obelisco_di_antinoo | B44: DAY_1 | C44: D1_POPOLO_PINCIO_SPAGNA | D44: Obelisco di Antinoo | E44: GRUEN | F44: GRUEN_PARKZUGANG | H44: =COUNTIFS(Ortszuordnung!$E$5:$E$85,A44,Ortszuordnung!$B$5:$B$85,"REGULAER") -> 1 | I44: =COUNTIF(Ortszuordnung!$E$5:$E$85,A44)-H44 -> 0 | J44: =IF(E44="ROT","AUSSCHLUSS",IF(H44>0,"KERNQUEST",IF(I44>0,"SONDERQUEST",IF(G44<>"","SUPPORT","RESERVE")))) -> KERNQUEST | K44: 91 | L44: Ombra di Antinoo | M44: =IF(J44="AUSSCHLUSS","Nicht als Pflichtort; nur nach neuer Evidenz neu bewerten.",IF(J44="KERNQUEST","In regulärer Quest gruppiert; aktuelle Sicht und blinden Test vor Release abschließen.",IF(J44="SONDERQUEST","Für Medien-, Hidden- oder Bossinhalt vorgesehen; separate Slot- oder Eventregel.",IF(J44="SUPPORT","Nur als Supportpunkt behalten; keine zusätzliche Pflichtquest.","Als Ersatz- oder späterer Questkandidat erhalten.")))) -> In regulärer Quest gruppiert; aktuelle Sicht und blinden Test vor Release abschließen.
A45: place_day_1_terrazza_del_gianicolo | B45: DAY_1 | C45: D1_GIANICOLO | D45: Terrazza del Gianicolo | E45: GRUEN | F45: GRUEN_SONDERROLLE | G45: WORLD_BOSS_LOCATION|BOSS_STAGING_SAFE_ZONE | H45: =COUNTIFS(Ortszuordnung!$E$5:$E$85,A45,Ortszuordnung!$B$5:$B$85,"REGULAER") -> 0 | I45: =COUNTIF(Ortszuordnung!$E$5:$E$85,A45)-H45 -> 1 | J45: =IF(E45="ROT","AUSSCHLUSS",IF(H45>0,"KERNQUEST",IF(I45>0,"SONDERQUEST",IF(G45<>"","SUPPORT","RESERVE")))) -> SONDERQUEST | K45: 86 | L45: Il Cannoniere del Gianicolo | M45: =IF(J45="AUSSCHLUSS","Nicht als Pflichtort; nur nach neuer Evidenz neu bewerten.",IF(J45="KERNQUEST","In regulärer Quest gruppiert; aktuelle Sicht und blinden Test vor Release abschließen.",IF(J45="SONDERQUEST","Für Medien-, Hidden- oder Bossinhalt vorgesehen; separate Slot- oder Eventregel.",IF(J45="SUPPORT","Nur als Supportpunkt behalten; keine zusätzliche Pflichtquest.","Als Ersatz- oder späterer Questkandidat erhalten.")))) -> Für Medien-, Hidden- oder Bossinhalt vorgesehen; separate Slot- oder Eventregel.
A46: place_day_1_teatro_di_marcello | B46: DAY_1 | C46: D1_CAMPO_REGOLA_GHETTO | D46: Marcellustheater | E46: GRUEN | F46: GRUEN_AUSSENPUNKT | H46: =COUNTIFS(Ortszuordnung!$E$5:$E$85,A46,Ortszuordnung!$B$5:$B$85,"REGULAER") -> 1 | I46: =COUNTIF(Ortszuordnung!$E$5:$E$85,A46)-H46 -> 1 | J46: =IF(E46="ROT","AUSSCHLUSS",IF(H46>0,"KERNQUEST",IF(I46>0,"SONDERQUEST",IF(G46<>"","SUPPORT","RESERVE")))) -> KERNQUEST | L46: Maschera del Dramma | M46: =IF(J46="AUSSCHLUSS","Nicht als Pflichtort; nur nach neuer Evidenz neu bewerten.",IF(J46="KERNQUEST","In regulärer Quest gruppiert; aktuelle Sicht und blinden Test vor Release abschließen.",IF(J46="SONDERQUEST","Für Medien-, Hidden- oder Bossinhalt vorgesehen; separate Slot- oder Eventregel.",IF(J46="SUPPORT","Nur als Supportpunkt behalten; keine zusätzliche Pflichtquest.","Als Ersatz- oder späterer Questkandidat erhalten.")))) -> In regulärer Quest gruppiert; aktuelle Sicht und blinden Test vor Release abschließen.
A47: place_day_1_fontana_delle_tartarughe | B47: DAY_1 | C47: D1_TREVI_QUIRINALE | D47: Fontana delle Tartarughe | E47: GRUEN | F47: GRUEN_KONZEPTREIF | H47: =COUNTIFS(Ortszuordnung!$E$5:$E$85,A47,Ortszuordnung!$B$5:$B$85,"REGULAER") -> 1 | I47: =COUNTIF(Ortszuordnung!$E$5:$E$85,A47)-H47 -> 1 | J47: =IF(E47="ROT","AUSSCHLUSS",IF(H47>0,"KERNQUEST",IF(I47>0,"SONDERQUEST",IF(G47<>"","SUPPORT","RESERVE")))) -> KERNQUEST | K47: 84 | L47: Custode delle Tartarughe | M47: =IF(J47="AUSSCHLUSS","Nicht als Pflichtort; nur nach neuer Evidenz neu bewerten.",IF(J47="KERNQUEST","In regulärer Quest gruppiert; aktuelle Sicht und blinden Test vor Release abschließen.",IF(J47="SONDERQUEST","Für Medien-, Hidden- oder Bossinhalt vorgesehen; separate Slot- oder Eventregel.",IF(J47="SUPPORT","Nur als Supportpunkt behalten; keine zusätzliche Pflichtquest.","Als Ersatz- oder späterer Questkandidat erhalten.")))) -> In regulärer Quest gruppiert; aktuelle Sicht und blinden Test vor Release abschließen.
A48: place_day_1_fontana_della_dea_di_roma | B48: DAY_1 | C48: D1_POPOLO_PINCIO_SPAGNA | D48: Fontana della Dea di Roma | E48: GRUEN | F48: GRUEN_PARKZUGANG | H48: =COUNTIFS(Ortszuordnung!$E$5:$E$85,A48,Ortszuordnung!$B$5:$B$85,"REGULAER") -> 1 | I48: =COUNTIF(Ortszuordnung!$E$5:$E$85,A48)-H48 -> 0 | J48: =IF(E48="ROT","AUSSCHLUSS",IF(H48>0,"KERNQUEST",IF(I48>0,"SONDERQUEST",IF(G48<>"","SUPPORT","RESERVE")))) -> KERNQUEST | K48: 83 | L48: Dea Roma del Pincio | M48: =IF(J48="AUSSCHLUSS","Nicht als Pflichtort; nur nach neuer Evidenz neu bewerten.",IF(J48="KERNQUEST","In regulärer Quest gruppiert; aktuelle Sicht und blinden Test vor Release abschließen.",IF(J48="SONDERQUEST","Für Medien-, Hidden- oder Bossinhalt vorgesehen; separate Slot- oder Eventregel.",IF(J48="SUPPORT","Nur als Supportpunkt behalten; keine zusätzliche Pflichtquest.","Als Ersatz- oder späterer Questkandidat erhalten.")))) -> In regulärer Quest gruppiert; aktuelle Sicht und blinden Test vor Release abschließen.
A49: place_day_1_fontana_dei_satirelli | B49: DAY_1 | C49: D1_TRASTEVERE_TIBER_ISLAND | D49: Fontana dei Satirelli | E49: GELB | F49: GELB_PARKOEFFNUNG | H49: =COUNTIFS(Ortszuordnung!$E$5:$E$85,A49,Ortszuordnung!$B$5:$B$85,"REGULAER") -> 0 | I49: =COUNTIF(Ortszuordnung!$E$5:$E$85,A49)-H49 -> 1 | J49: =IF(E49="ROT","AUSSCHLUSS",IF(H49>0,"KERNQUEST",IF(I49>0,"SONDERQUEST",IF(G49<>"","SUPPORT","RESERVE")))) -> SONDERQUEST | K49: 82 | L49: I Satirelli Gemelli | M49: =IF(J49="AUSSCHLUSS","Nicht als Pflichtort; nur nach neuer Evidenz neu bewerten.",IF(J49="KERNQUEST","In regulärer Quest gruppiert; aktuelle Sicht und blinden Test vor Release abschließen.",IF(J49="SONDERQUEST","Für Medien-, Hidden- oder Bossinhalt vorgesehen; separate Slot- oder Eventregel.",IF(J49="SUPPORT","Nur als Supportpunkt behalten; keine zusätzliche Pflichtquest.","Als Ersatz- oder späterer Questkandidat erhalten.")))) -> Für Medien-, Hidden- oder Bossinhalt vorgesehen; separate Slot- oder Eventregel.
A50: place_day_1_obelisco_macuteo | B50: DAY_1 | C50: D1_NAVONA_PANTHEON | D50: Obelisco Macuteo | E50: GRUEN | F50: GRUEN_MENSCHENMENGE | H50: =COUNTIFS(Ortszuordnung!$E$5:$E$85,A50,Ortszuordnung!$B$5:$B$85,"REGULAER") -> 1 | I50: =COUNTIF(Ortszuordnung!$E$5:$E$85,A50)-H50 -> 0 | J50: =IF(E50="ROT","AUSSCHLUSS",IF(H50>0,"KERNQUEST",IF(I50>0,"SONDERQUEST",IF(G50<>"","SUPPORT","RESERVE")))) -> KERNQUEST | K50: 91 | L50: Mummia dell’Iseo | M50: =IF(J50="AUSSCHLUSS","Nicht als Pflichtort; nur nach neuer Evidenz neu bewerten.",IF(J50="KERNQUEST","In regulärer Quest gruppiert; aktuelle Sicht und blinden Test vor Release abschließen.",IF(J50="SONDERQUEST","Für Medien-, Hidden- oder Bossinhalt vorgesehen; separate Slot- oder Eventregel.",IF(J50="SUPPORT","Nur als Supportpunkt behalten; keine zusätzliche Pflichtquest.","Als Ersatz- oder späterer Questkandidat erhalten.")))) -> In regulärer Quest gruppiert; aktuelle Sicht und blinden Test vor Release abschließen.
A51: place_day_1_acquedotto_vergine | B51: DAY_1 | C51: D1_TREVI_QUIRINALE | D51: Acquedotto Vergine | E51: GELB | F51: GELB_TEILWEISE_VERDECKT | H51: =COUNTIFS(Ortszuordnung!$E$5:$E$85,A51,Ortszuordnung!$B$5:$B$85,"REGULAER") -> 1 | I51: =COUNTIF(Ortszuordnung!$E$5:$E$85,A51)-H51 -> 1 | J51: =IF(E51="ROT","AUSSCHLUSS",IF(H51>0,"KERNQUEST",IF(I51>0,"SONDERQUEST",IF(G51<>"","SUPPORT","RESERVE")))) -> KERNQUEST | K51: 80 | L51: Ratto dell’Acqua Virgo | M51: =IF(J51="AUSSCHLUSS","Nicht als Pflichtort; nur nach neuer Evidenz neu bewerten.",IF(J51="KERNQUEST","In regulärer Quest gruppiert; aktuelle Sicht und blinden Test vor Release abschließen.",IF(J51="SONDERQUEST","Für Medien-, Hidden- oder Bossinhalt vorgesehen; separate Slot- oder Eventregel.",IF(J51="SUPPORT","Nur als Supportpunkt behalten; keine zusätzliche Pflichtquest.","Als Ersatz- oder späterer Questkandidat erhalten.")))) -> In regulärer Quest gruppiert; aktuelle Sicht und blinden Test vor Release abschließen.
A52: place_day_1_palazzo_del_quirinale | B52: DAY_1 | C52: D1_TREVI_QUIRINALE | D52: Quirinalspalast | E52: GRUEN | F52: GRUEN_SICHERHEITSABSTAND | H52: =COUNTIFS(Ortszuordnung!$E$5:$E$85,A52,Ortszuordnung!$B$5:$B$85,"REGULAER") -> 1 | I52: =COUNTIF(Ortszuordnung!$E$5:$E$85,A52)-H52 -> 0 | J52: =IF(E52="ROT","AUSSCHLUSS",IF(H52>0,"KERNQUEST",IF(I52>0,"SONDERQUEST",IF(G52<>"","SUPPORT","RESERVE")))) -> KERNQUEST | K52: 80 | L52: Corazziere del Colle | M52: =IF(J52="AUSSCHLUSS","Nicht als Pflichtort; nur nach neuer Evidenz neu bewerten.",IF(J52="KERNQUEST","In regulärer Quest gruppiert; aktuelle Sicht und blinden Test vor Release abschließen.",IF(J52="SONDERQUEST","Für Medien-, Hidden- oder Bossinhalt vorgesehen; separate Slot- oder Eventregel.",IF(J52="SUPPORT","Nur als Supportpunkt behalten; keine zusätzliche Pflichtquest.","Als Ersatz- oder späterer Questkandidat erhalten.")))) -> In regulärer Quest gruppiert; aktuelle Sicht und blinden Test vor Release abschließen.
A53: place_day_1_balconata_del_pincio | B53: DAY_1 | C53: D1_POPOLO_PINCIO_SPAGNA | D53: Balconata del Pincio | E53: GRUEN | F53: GRUEN_PARKZUGANG | H53: =COUNTIFS(Ortszuordnung!$E$5:$E$85,A53,Ortszuordnung!$B$5:$B$85,"REGULAER") -> 1 | I53: =COUNTIF(Ortszuordnung!$E$5:$E$85,A53)-H53 -> 0 | J53: =IF(E53="ROT","AUSSCHLUSS",IF(H53>0,"KERNQUEST",IF(I53>0,"SONDERQUEST",IF(G53<>"","SUPPORT","RESERVE")))) -> KERNQUEST | K53: 85 | L53: Ombra del Belvedere | M53: =IF(J53="AUSSCHLUSS","Nicht als Pflichtort; nur nach neuer Evidenz neu bewerten.",IF(J53="KERNQUEST","In regulärer Quest gruppiert; aktuelle Sicht und blinden Test vor Release abschließen.",IF(J53="SONDERQUEST","Für Medien-, Hidden- oder Bossinhalt vorgesehen; separate Slot- oder Eventregel.",IF(J53="SUPPORT","Nur als Supportpunkt behalten; keine zusätzliche Pflichtquest.","Als Ersatz- oder späterer Questkandidat erhalten.")))) -> In regulärer Quest gruppiert; aktuelle Sicht und blinden Test vor Release abschließen.
A54: place_day_1_mura_gianicolensi_2 | B54: DAY_1 | C54: D1_GIANICOLO | D54: Gianicolense-Mauern | E54: GRUEN | F54: GRUEN_MIT_GEWEGPUNKT | H54: =COUNTIFS(Ortszuordnung!$E$5:$E$85,A54,Ortszuordnung!$B$5:$B$85,"REGULAER") -> 1 | I54: =COUNTIF(Ortszuordnung!$E$5:$E$85,A54)-H54 -> 0 | J54: =IF(E54="ROT","AUSSCHLUSS",IF(H54>0,"KERNQUEST",IF(I54>0,"SONDERQUEST",IF(G54<>"","SUPPORT","RESERVE")))) -> KERNQUEST | K54: 89 | L54: Garibaldino delle Mura | M54: =IF(J54="AUSSCHLUSS","Nicht als Pflichtort; nur nach neuer Evidenz neu bewerten.",IF(J54="KERNQUEST","In regulärer Quest gruppiert; aktuelle Sicht und blinden Test vor Release abschließen.",IF(J54="SONDERQUEST","Für Medien-, Hidden- oder Bossinhalt vorgesehen; separate Slot- oder Eventregel.",IF(J54="SUPPORT","Nur als Supportpunkt behalten; keine zusätzliche Pflichtquest.","Als Ersatz- oder späterer Questkandidat erhalten.")))) -> In regulärer Quest gruppiert; aktuelle Sicht und blinden Test vor Release abschließen.
A55: place_day_1_chiesa_di_san_pietro_in_montorio | B55: DAY_1 | C55: D1_TRASTEVERE_TIBER_ISLAND | D55: Kirche von San Pietro in Montorio | E55: GELB | F55: GELB_AUSSENFASSADE | H55: =COUNTIFS(Ortszuordnung!$E$5:$E$85,A55,Ortszuordnung!$B$5:$B$85,"REGULAER") -> 0 | I55: =COUNTIF(Ortszuordnung!$E$5:$E$85,A55)-H55 -> 0 | J55: =IF(E55="ROT","AUSSCHLUSS",IF(H55>0,"KERNQUEST",IF(I55>0,"SONDERQUEST",IF(G55<>"","SUPPORT","RESERVE")))) -> RESERVE | K55: 80 | L55: Custode del Tempietto | M55: =IF(J55="AUSSCHLUSS","Nicht als Pflichtort; nur nach neuer Evidenz neu bewerten.",IF(J55="KERNQUEST","In regulärer Quest gruppiert; aktuelle Sicht und blinden Test vor Release abschließen.",IF(J55="SONDERQUEST","Für Medien-, Hidden- oder Bossinhalt vorgesehen; separate Slot- oder Eventregel.",IF(J55="SUPPORT","Nur als Supportpunkt behalten; keine zusätzliche Pflichtquest.","Als Ersatz- oder späterer Questkandidat erhalten.")))) -> Als Ersatz- oder späterer Questkandidat erhalten.
A56: place_day_1_piazza_di_santa_maria_in_trastevere | B56: DAY_1 | C56: D1_TRASTEVERE_TIBER_ISLAND | D56: Piazza di Santa Maria in Trastevere | E56: GRUEN | F56: GRUEN_REVIVE_PUNKT | G56: REVIVE_POINT_CANDIDATE | H56: =COUNTIFS(Ortszuordnung!$E$5:$E$85,A56,Ortszuordnung!$B$5:$B$85,"REGULAER") -> 0 | I56: =COUNTIF(Ortszuordnung!$E$5:$E$85,A56)-H56 -> 0 | J56: =IF(E56="ROT","AUSSCHLUSS",IF(H56>0,"KERNQUEST",IF(I56>0,"SONDERQUEST",IF(G56<>"","SUPPORT","RESERVE")))) -> SUPPORT | K56: 89 | L56: Leone del Mosaico | M56: =IF(J56="AUSSCHLUSS","Nicht als Pflichtort; nur nach neuer Evidenz neu bewerten.",IF(J56="KERNQUEST","In regulärer Quest gruppiert; aktuelle Sicht und blinden Test vor Release abschließen.",IF(J56="SONDERQUEST","Für Medien-, Hidden- oder Bossinhalt vorgesehen; separate Slot- oder Eventregel.",IF(J56="SUPPORT","Nur als Supportpunkt behalten; keine zusätzliche Pflichtquest.","Als Ersatz- oder späterer Questkandidat erhalten.")))) -> Nur als Supportpunkt behalten; keine zusätzliche Pflichtquest.
A57: place_day_1_portico_d_ottavia | B57: DAY_1 | C57: D1_CAMPO_REGOLA_GHETTO | D57: Portico d'Ottavia | E57: ROT | F57: ROT_AKTUELL_GESPERRT | H57: =COUNTIFS(Ortszuordnung!$E$5:$E$85,A57,Ortszuordnung!$B$5:$B$85,"REGULAER") -> 0 | I57: =COUNTIF(Ortszuordnung!$E$5:$E$85,A57)-H57 -> 0 | J57: =IF(E57="ROT","AUSSCHLUSS",IF(H57>0,"KERNQUEST",IF(I57>0,"SONDERQUEST",IF(G57<>"","SUPPORT","RESERVE")))) -> AUSSCHLUSS | K57: 80 | L57: Pesce Fantasma del Ghetto | M57: =IF(J57="AUSSCHLUSS","Nicht als Pflichtort; nur nach neuer Evidenz neu bewerten.",IF(J57="KERNQUEST","In regulärer Quest gruppiert; aktuelle Sicht und blinden Test vor Release abschließen.",IF(J57="SONDERQUEST","Für Medien-, Hidden- oder Bossinhalt vorgesehen; separate Slot- oder Eventregel.",IF(J57="SUPPORT","Nur als Supportpunkt behalten; keine zusätzliche Pflichtquest.","Als Ersatz- oder späterer Questkandidat erhalten.")))) -> Nicht als Pflichtort; nur nach neuer Evidenz neu bewerten.
A58: place_day_1_piazza_del_teatro_di_pompeo | B58: DAY_1 | C58: D1_CAMPO_REGOLA_GHETTO | D58: Piazza del Teatro di Pompeo | E58: ROT | F58: ROT_NICHT_ALS_PFLICHT | H58: =COUNTIFS(Ortszuordnung!$E$5:$E$85,A58,Ortszuordnung!$B$5:$B$85,"REGULAER") -> 0 | I58: =COUNTIF(Ortszuordnung!$E$5:$E$85,A58)-H58 -> 0 | J58: =IF(E58="ROT","AUSSCHLUSS",IF(H58>0,"KERNQUEST",IF(I58>0,"SONDERQUEST",IF(G58<>"","SUPPORT","RESERVE")))) -> AUSSCHLUSS | K58: 89 | L58: Pugnale della Curia | M58: =IF(J58="AUSSCHLUSS","Nicht als Pflichtort; nur nach neuer Evidenz neu bewerten.",IF(J58="KERNQUEST","In regulärer Quest gruppiert; aktuelle Sicht und blinden Test vor Release abschließen.",IF(J58="SONDERQUEST","Für Medien-, Hidden- oder Bossinhalt vorgesehen; separate Slot- oder Eventregel.",IF(J58="SUPPORT","Nur als Supportpunkt behalten; keine zusätzliche Pflichtquest.","Als Ersatz- oder späterer Questkandidat erhalten.")))) -> Nicht als Pflichtort; nur nach neuer Evidenz neu bewerten.
A59: place_day_1_porta_cavalleggeri | B59: DAY_1 | C59: D1_VATICANO_PRATI_BORGO | D59: Porta Cavalleggeri | E59: GELB | F59: GELB_KLEINER_MAUERREST | H59: =COUNTIFS(Ortszuordnung!$E$5:$E$85,A59,Ortszuordnung!$B$5:$B$85,"REGULAER") -> 1 | I59: =COUNTIF(Ortszuordnung!$E$5:$E$85,A59)-H59 -> 0 | J59: =IF(E59="ROT","AUSSCHLUSS",IF(H59>0,"KERNQUEST",IF(I59>0,"SONDERQUEST",IF(G59<>"","SUPPORT","RESERVE")))) -> KERNQUEST | K59: 85 | L59: Cavalleggero Pontificio | M59: =IF(J59="AUSSCHLUSS","Nicht als Pflichtort; nur nach neuer Evidenz neu bewerten.",IF(J59="KERNQUEST","In regulärer Quest gruppiert; aktuelle Sicht und blinden Test vor Release abschließen.",IF(J59="SONDERQUEST","Für Medien-, Hidden- oder Bossinhalt vorgesehen; separate Slot- oder Eventregel.",IF(J59="SUPPORT","Nur als Supportpunkt behalten; keine zusätzliche Pflichtquest.","Als Ersatz- oder späterer Questkandidat erhalten.")))) -> In regulärer Quest gruppiert; aktuelle Sicht und blinden Test vor Release abschließen.
A60: place_day_2_piazza_del_campidoglio | B60: DAY_2 | C60: D2_CAMPIDOGLIO_FORI_TRAIANEI | D60: Kapitolsplatz | E60: GRUEN | F60: GRUEN_KONZEPTREIF | G60: REVIVE_POINT_CANDIDATE | H60: =COUNTIFS(Ortszuordnung!$E$5:$E$85,A60,Ortszuordnung!$B$5:$B$85,"REGULAER") -> 1 | I60: =COUNTIF(Ortszuordnung!$E$5:$E$85,A60)-H60 -> 0 | J60: =IF(E60="ROT","AUSSCHLUSS",IF(H60>0,"KERNQUEST",IF(I60>0,"SONDERQUEST",IF(G60<>"","SUPPORT","RESERVE")))) -> KERNQUEST | K60: 93 | M60: =IF(J60="AUSSCHLUSS","Nicht als Pflichtort; nur nach neuer Evidenz neu bewerten.",IF(J60="KERNQUEST","In regulärer Quest gruppiert; aktuelle Sicht und blinden Test vor Release abschließen.",IF(J60="SONDERQUEST","Für Medien-, Hidden- oder Bossinhalt vorgesehen; separate Slot- oder Eventregel.",IF(J60="SUPPORT","Nur als Supportpunkt behalten; keine zusätzliche Pflichtquest.","Als Ersatz- oder späterer Questkandidat erhalten.")))) -> In regulärer Quest gruppiert; aktuelle Sicht und blinden Test vor Release abschließen.
A61: place_day_2_giulio_cesare | B61: DAY_2 | C61: D2_CAMPIDOGLIO_FORI_TRAIANEI | D61: Giulio Cesare | E61: GELB | F61: GELB_QUELLENLAGE | H61: =COUNTIFS(Ortszuordnung!$E$5:$E$85,A61,Ortszuordnung!$B$5:$B$85,"REGULAER") -> 1 | I61: =COUNTIF(Ortszuordnung!$E$5:$E$85,A61)-H61 -> 0 | J61: =IF(E61="ROT","AUSSCHLUSS",IF(H61>0,"KERNQUEST",IF(I61>0,"SONDERQUEST",IF(G61<>"","SUPPORT","RESERVE")))) -> KERNQUEST | K61: 84 | L61: Cesare di Bronzo | M61: =IF(J61="AUSSCHLUSS","Nicht als Pflichtort; nur nach neuer Evidenz neu bewerten.",IF(J61="KERNQUEST","In regulärer Quest gruppiert; aktuelle Sicht und blinden Test vor Release abschließen.",IF(J61="SONDERQUEST","Für Medien-, Hidden- oder Bossinhalt vorgesehen; separate Slot- oder Eventregel.",IF(J61="SUPPORT","Nur als Supportpunkt behalten; keine zusätzliche Pflichtquest.","Als Ersatz- oder späterer Questkandidat erhalten.")))) -> In regulärer Quest gruppiert; aktuelle Sicht und blinden Test vor Release abschließen.
